Workbook

Sheet Dashboard

Sheet KPI's & Pivot Tables
A1: Total Leads | B1: Hot Leads | C1: Warm Leads | D1: Cold Leads | E1: Avg Lead Score | F1: Total Campaign Spend | G1: Avg Cost Per Lead | H1: Avg ROAS
A2: =COUNTA(scoring_results!A2:A1001) -> 1000 | B2: =COUNTIF(scoring_results!M2:M1001,"HOT") -> 110 | C2: =COUNTIF(scoring_results!M2:M1001,"WARM") -> 537 | D2: =COUNTIF(scoring_results!M2:M1001,"COLD") -> 353 | E2: =ROUND(AVERAGE(scoring_results!L2:L1001),1) -> 41 | F2: =SUM(clean_spend!F:F) -> 758451 | G2: =ROUND(AVERAGE(clean_spend!M:M),2) -> 184.62 | H2: =ROUND(AVERAGE(clean_spend!Q:Q),2) -> 4.93
A8: Source | B8: Count of Leads | D8: Segment | E8: Count of Leads | H8: Industry | I8: Count of Leads
A9: COLD_EMAIL | B9: 109 | D9: COLD | E9: 353 | H9: AI/ML | I9: 45
A10: CONTENT_SYNDICATION | B10: 55 | D10: HOT | E10: 110 | H10: Automotive | I10: 34
A11: DIRECT | B11: 83 | D11: WARM | E11: 537 | H11: Biotech | I11: 43
A12: EVENT | B12: 99 | D12: Grand Total | E12: 1000 | H12: Cleantech | I12: 33
A13: ORGANIC | B13: 121 | H13: Cybersecurity | I13: 56
A14: PAID | B14: 109 | H14: Devops | I14: 35
A15: PARTNER | B15: 85 | H15: E-Commerce | I15: 49
A16: REFERRAL | B16: 107 | H16: Edtech | I16: 48
A17: SOCIAL | B17: 112 | H17: Energy | I17: 45
A18: UNKNOWN | B18: 52 | H18: Fintech | I18: 55
A19: WEBINAR | B19: 68 | D19: Campaign | E19: Sum of Monthly Spend | F19: Sum of Revenue Attributed | H19: Gaming | I19: 22
A20: Grand Total | B20: 1000 | D20: Cold Email Outbound | E20: 63789 | F20: 195264 | H20: Healthcare | I20: 54
D21: Content Syndication | E21: 56772 | F21: 78482 | H21: Hrtech | I21: 41
D22: Google Ads - Display | E22: 56723 | F22: 173580 | H22: Insurtech | I22: 30
D23: Google Ads - Search | E23: 93070 | F23: 339161 | H23: Legal Tech | I23: 24
D24: LinkedIn - ABM Campaign | E24: 108375 | F24: 202263 | H24: Logistics | I24: 53
D25: Meta - Brand Awareness | E25: 89830 | F25: 293248 | H25: Manufacturing | I25: 28
D26: Referral Program | E26: 37889 | F26: 364131 | H26: Martech | I26: 45
A27: Month | B27: Sum of Monthly spend | D27: SEO Content Program | E27: 46997 | F27: 634186 | H27: Media | I27: 26
A28: 2025-01 | B28: 52949 | D28: Trade Show Circuit | E28: 130023 | F28: 170542 | H28: Proptech | I28: 30
A29: 2025-02 | B29: 50794 | D29: Webinar Series | E29: 74983 | F29: 551435 | H29: Retail | I29: 52
A30: 2025-03 | B30: 64081 | D30: Grand Total | E30: 758451 | F30: 3002292 | H30: Saas | I30: 49
A31: 2025-04 | B31: 53201 | H31: Supply Chain | I31: 26
A32: 2025-05 | B32: 57309 | H32: Telecom | I32: 34
A33: 2025-06 | B33: 54630 | H33: Unknown | I33: 43
A34: 2025-07 | B34: 57655 | H34: Grand Total | I34: 1000
A35: 2025-08 | B35: 58293
A36: 2025-09 | B36: 59319
A37: 2025-10 | B37: 80743 | D37: Score Bucket | E37: Count of Leads
A38: 2025-11 | B38: 71190 | D38: 0-19 | E38: 91
A39: 2025-12 | B39: 98287 | D39: 20-39 | E39: 395
A40: Grand Total | B40: 758451 | D40: 40-59 | E40: 404 | H40: Name | I40: Total score
D41: 60-79 | E41: 108 | H41: Maya Chen | I41: 135
D42: 80-100 | E42: 2 | H42: Raphael Park | I42: 110.1
D43: Grand Total | E43: 1000 | H43: Wendy Chandra | I43: 103
H44: Nico Nakamura | I44: 97.6
H45: Hugo Bianchi | I45: 93.5
H46: Xena Kim | I46: 92
H47: Xena Torres | I47: 88.1
H48: Perseus Das | I48: 85.9
H49: Joaquin Gupta | I49: 84.7
H50: Hank Larsson | I50: 82.6
H51: Grand Total | I51: 972.5

Sheet scoring_results
A1: lead_id | B1: name | C1: company | D1: source | E1: company_size | F1: email_opens_score | G1: clicks_score | H1: visits_score | I1: demo_score | J1: size_score | K1: engagement_score | L1: TOTAL_SCORE | M1: segment | N1: recommended_action | O1: score_bucket
A2: {=model!A2:A1001} -> L0001 | B2: {=model!B2:B1001} -> Liora Jackson | C2: {=model!C2:C1001} -> AIRTABLE | D2: {=model!E2:E1001} -> UNKNOWN | E2: {=model!D2:D1001} -> SMB | F2: =ROUND(IFERROR(model!I2/scoring_weights!$C$2,0)*scoring_weights!$B$2,1) -> 10 | G2: =ROUND(IFERROR(model!J2/scoring_weights!$C$3,0)*scoring_weights!$B$3,1) -> 15 | H2: =ROUND(IFERROR(model!K2/scoring_weights!$C$4,0)*scoring_weights!$B$4,1) -> 4.3 | I2: =IF(model!L2="YES",scoring_weights!$B$5,0) -> 0 | J2: =IF(model!D2="ENTERPRISE",scoring_weights!$B$6,IF(model!D2="MID-MARKET",scoring_weights!$B$6*0.75,IF(model!D2="SMB",scoring_weights!$B$6*0.5,IF(model!D2="STARTUP",scoring_weights!$B$6*0.25,0)))) -> 7.5 | K2: =ROUND(MIN(IFERROR((model!O2/10+model!P2/5+model!R2*2+model!T2+model!U2*1.5)/6,0),1)*scoring_weights!$B$7,1) -> 18 | L2: =ROUND(F2+G2+H2+I2+J2+K2,1) -> 54.8 | M2: =IF(L2>=segment_thresholds!$B$2,"HOT",IF(L2>=segment_thresholds!$B$3,"WARM","COLD")) -> WARM | N2: =IF(M2="HOT","Schedule Call",IF(M2="WARM","Nurture Email Drip","Retarget with Ads")) -> Nurture Email Drip | O2: =IF(L2<20,"0-19",IF(L2<40,"20-39",IF(L2<60,"40-59",IF(L2<80,"60-79","80-100")))) -> 40-59
A3: L0002 | B3: Yara Malik | C3: AIRTABLE | D3: EVENT | E3: SMB | F3: =ROUND(IFERROR(model!I3/scoring_weights!$C$2,0)*scoring_weights!$B$2,1) -> 1.1 | G3: =ROUND(IFERROR(model!J3/scoring_weights!$C$3,0)*scoring_weights!$B$3,1) -> 0 | H3: =ROUND(IFERROR(model!K3/scoring_weights!$C$4,0)*scoring_weights!$B$4,1) -> 3 | I3: =IF(model!L3="YES",scoring_weights!$B$5,0) -> 20 | J3: =IF(model!D3="ENTERPRISE",scoring_weights!$B$6,IF(model!D3="MID-MARKET",scoring_weights!$B$6*0.75,IF(model!D3="SMB",scoring_weights!$B$6*0.5,IF(model!D3="STARTUP",scoring_weights!$B$6*0.25,0)))) -> 7.5 | K3: =ROUND(MIN(IFERROR((model!O3/10+model!P3/5+model!R3*2+model!T3+model!U3*1.5)/6,0),1)*scoring_weights!$B$7,1) -> 1.5 | L3: =ROUND(F3+G3+H3+I3+J3+K3,1) -> 33.1 | M3: =IF(L3>=segment_thresholds!$B$2,"HOT",IF(L3>=segment_thresholds!$B$3,"WARM","COLD")) -> COLD | N3: =IF(M3="HOT","Schedule Call",IF(M3="WARM","Nurture Email Drip","Retarget with Ads")) -> Retarget with Ads | O3: =IF(L3<20,"0-19",IF(L3<40,"20-39",IF(L3<60,"40-59",IF(L3<80,"60-79","80-100")))) -> 20-39
A4: L0003 | B4: Luna Harris | C4: CROWD STRIKE | D4: EVENT | E4: SMB | F4: =ROUND(IFERROR(model!I4/scoring_weights!$C$2,0)*scoring_weights!$B$2,1) -> 3.7 | G4: =ROUND(IFERROR(model!J4/scoring_weights!$C$3,0)*scoring_weights!$B$3,1) -> 13.5 | H4: =ROUND(IFERROR(model!K4/scoring_weights!$C$4,0)*scoring_weights!$B$4,1) -> 3.3 | I4: =IF(model!L4="YES",scoring_weights!$B$5,0) -> 20 | J4: =IF(model!D4="ENTERPRISE",scoring_weights!$B$6,IF(model!D4="MID-MARKET",scoring_weights!$B$6*0.75,IF(model!D4="SMB",scoring_weights!$B$6*0.5,IF(model!D4="STARTUP",scoring_weights!$B$6*0.25,0)))) -> 7.5 | K4: =ROUND(MIN(IFERROR((model!O4/10+model!P4/5+model!R4*2+model!T4+model!U4*1.5)/6,0),1)*scoring_weights!$B$7,1) -> 9.5 | L4: =ROUND(F4+G4+H4+I4+J4+K4,1) -> 57.5 | M4: =IF(L4>=segment_thresholds!$B$2,"HOT",IF(L4>=segment_thresholds!$B$3,"WARM","COLD")) -> WARM | N4: =IF(M4="HOT","Schedule Call",IF(M4="WARM","Nurture Email Drip","Retarget with Ads")) -> Nurture Email Drip | O4: =IF(L4<20,"0-19",IF(L4<40,"20-39",IF(L4<60,"40-59",IF(L4<80,"60-79","80-100")))) -> 40-59
A5: L0004 | B5: James Nakamura | C5: HUB SPOT | D5: PARTNER | E5: STARTUP | F5: =ROUND(IFERROR(model!I5/scoring_weights!$C$2,0)*scoring_weights!$B$2,1) -> 10 | G5: =ROUND(IFERROR(model!J5/scoring_weights!$C$3,0)*scoring_weights!$B$3,1) -> 0 | H5: =ROUND(IFERROR(model!K5/scoring_weights!$C$4,0)*scoring_weights!$B$4,1) -> 1.2 | I5: =IF(model!L5="YES",scoring_weights!$B$5,0) -> 0 | J5: =IF(model!D5="ENTERPRISE",scoring_weights!$B$6,IF(model!D5="MID-MARKET",scoring_weights!$B$6*0.75,IF(model!D5="SMB",scoring_weights!$B$6*0.5,IF(model!D5="STARTUP",scoring_weights!$B$6*0.25,0)))) -> 3.75 | K5: =ROUND(MIN(IFERROR((model!O5/10+model!P5/5+model!R5*2+model!T5+model!U5*1.5)/6,0),1)*scoring_weights!$B$7,1) -> 11 | L5: =ROUND(F5+G5+H5+I5+J5+K5,1) -> 26 | M5: =IF(L5>=segment_thresholds!$B$2,"HOT",IF(L5>=segment_thresholds!$B$3,"WARM","COLD")) -> COLD | N5: =IF(M5="HOT","Schedule Call",IF(M5="WARM","Nurture Email Drip","Retarget with Ads")) -> Retarget with Ads | O5: =IF(L5<20,"0-19",IF(L5<40,"20-39",IF(L5<60,"40-59",IF(L5<80,"60-79","80-100")))) -> 20-39
A6: L0005 | B6: Bastian Mishra | C6: DROPBOX | D6: UNKNOWN | E6: SMB | F6: =ROUND(IFERROR(model!I6/scoring_weights!$C$2,0)*scoring_weights!$B$2,1) -> 0 | G6: =ROUND(IFERROR(model!J6/scoring_weights!$C$3,0)*scoring_weights!$B$3,1) -> 6.8 | H6: =ROUND(IFERROR(model!K6/scoring_weights!$C$4,0)*scoring_weights!$B$4,1) -> 2.5 | I6: =IF(model!L6="YES",scoring_weights!$B$5,0) -> 20 | J6: =IF(model!D6="ENTERPRISE",scoring_weights!$B$6,IF(model!D6="MID-MARKET",scoring_weights!$B$6*0.75,IF(model!D6="SMB",scoring_weights!$B$6*0.5,IF(model!D6="STARTUP",scoring_weights!$B$6*0.25,0)))) -> 7.5 | K6: =ROUND(MIN(IFERROR((model!O6/10+model!P6/5+model!R6*2+model!T6+model!U6*1.5)/6,0),1)*scoring_weights!$B$7,1) -> 16.5 | L6: =ROUND(F6+G6+H6+I6+J6+K6,1) -> 53.3 | M6: =IF(L6>=segment_thresholds!$B$2,"HOT",IF(L6>=segment_thresholds!$B$3,"WARM","COLD")) -> WARM | N6: =IF(M6="HOT","Schedule Call",IF(M6="WARM","Nurture Email Drip","Retarget with Ads")) -> Nurture Email Drip | O6: =IF(L6<20,"0-19",IF(L6<40,"20-39",IF(L6<60,"40-59",IF(L6<80,"60-79","80-100")))) -> 40-59
A7: L0006 | B7: Yuki Robinson | C7: CLOUDFLARE | D7: ORGANIC | E7: SMB | F7: =ROUND(IFERROR(model!I7/scoring_weights!$C$2,0)*scoring_weights!$B$2,1) -> 4 | G7: =ROUND(IFERROR(model!J7/scoring_weights!$C$3,0)*scoring_weights!$B$3,1) -> 0 | H7: =ROUND(IFERROR(model!K7/scoring_weights!$C$4,0)*scoring_weights!$B$4,1) -> 0 | I7: =IF(model!L7="YES",scoring_weights!$B$5,0) -> 20 | J7: =IF(model!D7="ENTERPRISE",scoring_weights!$B$6,IF(model!D7="MID-MARKET",scoring_weights!$B$6*0.75,IF(model!D7="SMB",scoring_weights!$B$6*0.5,IF(model!D7="STARTUP",scoring_weights!$B$6*0.25,0)))) -> 7.5 | K7: =ROUND(MIN(IFERROR((model!O7/10+model!P7/5+model!R7*2+model!T7+model!U7*1.5)/6,0),1)*scoring_weights!$B$7,1) -> 11 | L7: =ROUND(F7+G7+H7+I7+J7+K7,1) -> 42.5 | M7: =IF(L7>=segment_thresholds!$B$2,"HOT",IF(L7>=segment_thresholds!$B$3,"WARM","COLD")) -> WARM | N7: =IF(M7="HOT","Schedule Call",IF(M7="WARM","Nurture Email Drip","Retarget with Ads")) -> Nurture Email Drip | O7: =IF(L7<20,"0-19",IF(L7<40,"20-39",IF(L7<60,"40-59",IF(L7<80,"60-79","80-100")))) -> 40-59
A8: L0007 | B8: Uriel Jensen | C8: STRIPE INC | D8: COLD_EMAIL | E8: STARTUP | F8: =ROUND(IFERROR(model!I8/scoring_weights!$C$2,0)*scoring_weights!$B$2,1) -> 1.7 | G8: =ROUND(IFERROR(model!J8/scoring_weights!$C$3,0)*scoring_weights!$B$3,1) -> 4.5 | H8: =ROUND(IFERROR(model!K8/scoring_weights!$C$4,0)*scoring_weights!$B$4,1) -> 1.3 | I8: =IF(model!L8="YES",scoring_weights!$B$5,0) -> 0 | J8: =IF(model!D8="ENTERPRISE",scoring_weights!$B$6,IF(model!D8="MID-MARKET",scoring_weights!$B$6*0.75,IF(model!D8="SMB",scoring_weights!$B$6*0.5,IF(model!D8="STARTUP",scoring_weights!$B$6*0.25,0)))) -> 3.75 | K8: =ROUND(MIN(IFERROR((model!O8/10+model!P8/5+model!R8*2+model!T8+model!U8*1.5)/6,0),1)*scoring_weights!$B$7,1) -> 19 | L8: =ROUND(F8+G8+H8+I8+J8+K8,1) -> 30.3 | M8: =IF(L8>=segment_thresholds!$B$2,"HOT",IF(L8>=segment_thresholds!$B$3,"WARM","COLD")) -> COLD | N8: =IF(M8="HOT","Schedule Call",IF(M8="WARM","Nurture Email Drip","Retarget with Ads")) -> Retarget with Ads | O8: =IF(L8<20,"0-19",IF(L8<40,"20-39",IF(L8<60,"40-59",IF(L8<80,"60-79","80-100")))) -> 20-39
A9: L0008 | B9: Vivian Young | C9: GOOGLE | D9: SOCIAL | E9: MID-MARKET | F9: =ROUND(IFERROR(model!I9/scoring_weights!$C$2,0)*scoring_weights!$B$2,1) -> 0.9 | G9: =ROUND(IFERROR(model!J9/scoring_weights!$C$3,0)*scoring_weights!$B$3,1) -> 12.8 | H9: =ROUND(IFERROR(model!K9/scoring_weights!$C$4,0)*scoring_weights!$B$4,1) -> 0 | I9: =IF(model!L9="YES",scoring_weights!$B$5,0) -> 20 | J9: =IF(model!D9="ENTERPRISE",scoring_weights!$B$6,IF(model!D9="MID-MARKET",scoring_weights!$B$6*0.75,IF(model!D9="SMB",scoring_weights!$B$6*0.5,IF(model!D9="STARTUP",scoring_weights!$B$6*0.25,0)))) -> 11.25 | K9: =ROUND(MIN(IFERROR((model!O9/10+model!P9/5+model!R9*2+model!T9+model!U9*1.5)/6,0),1)*scoring_weights!$B$7,1) -> 6 | L9: =ROUND(F9+G9+H9+I9+J9+K9,1) -> 51 | M9: =IF(L9>=segment_thresholds!$B$2,"HOT",IF(L9>=segment_thresholds!$B$3,"WARM","COLD")) -> WARM | N9: =IF(M9="HOT","Schedule Call",IF(M9="WARM","Nurture Email Drip","Retarget with Ads")) -> Nurture Email Drip | O9: =IF(L9<20,"0-19",IF(L9<40,"20-39",IF(L9<60,"40-59",IF(L9<80,"60-79","80-100")))) -> 40-59
A10: L0009 | B10: Elena Pandey | C10: ELASTIC | D10: EVENT | E10: SMB | F10: =ROUND(IFERROR(model!I10/scoring_weights!$C$2,0)*scoring_weights!$B$2,1) -> 5.4 | G10: =ROUND(IFERROR(model!J10/scoring_weights!$C$3,0)*scoring_weights!$B$3,1) -> 1.5 | H10: =ROUND(IFERROR(model!K10/scoring_weights!$C$4,0)*scoring_weights!$B$4,1) -> 0 | I10: =IF(model!L10="YES",scoring_weights!$B$5,0) -> 0 | J10: =IF(model!D10="ENTERPRISE",scoring_weights!$B$6,IF(model!D10="MID-MARKET",scoring_weights!$B$6*0.75,IF(model!D10="SMB",scoring_weights!$B$6*0.5,IF(model!D10="STARTUP",scoring_weights!$B$6*0.25,0)))) -> 7.5 | K10: =ROUND(MIN(IFERROR((model!O10/10+model!P10/5+model!R10*2+model!T10+model!U10*1.5)/6,0),1)*scoring_weights!$B$7,1) -> 4.5 | L10: =ROUND(F10+G10+H10+I10+J10+K10,1) -> 18.9 | M10: =IF(L10>=segment_thresholds!$B$2,"HOT",IF(L10>=segment_thresholds!$B$3,"WARM","COLD")) -> COLD | N10: =IF(M10="HOT","Schedule Call",IF(M10="WARM","Nurture Email Drip","Retarget with Ads")) -> Retarget with Ads | O10: =IF(L10<20,"0-19",IF(L10<40,"20-39",IF(L10<60,"40-59",IF(L10<80,"60-79","80-100")))) -> 0-19
A11: L0010 | B11: Priya Muller | C11: PALO ALTO | D11: PAID | E11: MID-MARKET | F11: =ROUND(IFERROR(model!I11/scoring_weights!$C$2,0)*scoring_weights!$B$2,1) -> 2.6 | G11: =ROUND(IFERROR(model!J11/scoring_weights!$C$3,0)*scoring_weights!$B$3,1) -> 14.3 | H11: =ROUND(IFERROR(model!K11/scoring_weights!$C$4,0)*scoring_weights!$B$4,1) -> 3.5 | I11: =IF(model!L11="YES",scoring_weights!$B$5,0) -> 20 | J11: =IF(model!D11="ENTERPRISE",scoring_weights!$B$6,IF(model!D11="MID-MARKET",scoring_weights!$B$6*0.75,IF(model!D11="SMB",scoring_weights!$B$6*0.5,IF(model!D11="STARTUP",scoring_weights!$B$6*0.25,0)))) -> 11.25 | K11: =ROUND(MIN(IFERROR((model!O11/10+model!P11/5+model!R11*2+model!T11+model!U11*1.5)/6,0),1)*scoring_weights!$B$7,1) -> 5.5 | L11: =ROUND(F11+G11+H11+I11+J11+K11,1) -> 57.2 | M11: =IF(L11>=segment_thresholds!$B$2,"HOT",IF(L11>=segment_thresholds!$B$3,"WARM","COLD")) -> WARM | N11: =IF(M11="HOT","Schedule Call",IF(M11="WARM","Nurture Email Drip","Retarget with Ads")) -> Nurture Email Drip | O11: =IF(L11<20,"0-19",IF(L11<40,"20-39",IF(L11<60,"40-59",IF(L11<80,"60-79","80-100")))) -> 40-59
A12: L0011 | B12: Landon Rossi | C12: CROWD STRIKE | D12: EVENT | E12: SMB | F12: =ROUND(IFERROR(model!I12/scoring_weights!$C$2,0)*scoring_weights!$B$2,1) -> 0.6 | G12: =ROUND(IFERROR(model!J12/scoring_weights!$C$3,0)*scoring_weights!$B$3,1) -> 4.5 | H12: =ROUND(IFERROR(model!K12/scoring_weights!$C$4,0)*scoring_weights!$B$4,1) -> 7 | I12: =IF(model!L12="YES",scoring_weights!$B$5,0) -> 0 | J12: =IF(model!D12="ENTERPRISE",scoring_weights!$B$6,IF(model!D12="MID-MARKET",scoring_weights!$B$6*0.75,IF(model!D12="SMB",scoring_weights!$B$6*0.5,IF(model!D12="STARTUP",scoring_weights!$B$6*0.25,0)))) -> 7.5 | K12: =ROUND(MIN(IFERROR((model!O12/10+model!P12/5+model!R12*2+model!T12+model!U12*1.5)/6,0),1)*scoring_weights!$B$7,1) -> 16 | L12: =ROUND(F12+G12+H12+I12+J12+K12,1) -> 35.6 | M12: =IF(L12>=segment_thresholds!$B$2,"HOT",IF(L12>=segment_thresholds!$B$3,"WARM","COLD")) -> WARM | N12: =IF(M12="HOT","Schedule Call",IF(M12="WARM","Nurture Email Drip","Retarget with Ads")) -> Nurture Email Drip | O12: =IF(L12<20,"0-19",IF(L12<40,"20-39",IF(L12<60,"40-59",IF(L12<80,"60-79","80-100")))) -> 20-39
A13: L0012 | B13: Jamal Soto | C13: NOTION | D13: COLD_EMAIL | E13: N/A | F13: =ROUND(IFERROR(model!I13/scoring_weights!$C$2,0)*scoring_weights!$B$2,1) -> 4 | G13: =ROUND(IFERROR(model!J13/scoring_weights!$C$3,0)*scoring_weights!$B$3,1) -> 4.5 | H13: =ROUND(IFERROR(model!K13/scoring_weights!$C$4,0)*scoring_weights!$B$4,1) -> 2.8 | I13: =IF(model!L13="YES",scoring_weights!$B$5,0) -> 20 | J13: =IF(model!D13="ENTERPRISE",scoring_weights!$B$6,IF(model!D13="MID-MARKET",scoring_weights!$B$6*0.75,IF(model!D13="SMB",scoring_weights!$B$6*0.5,IF(model!D13="STARTUP",scoring_weights!$B$6*0.25,0)))) -> 0 | K13: =ROUND(MIN(IFERROR((model!O13/10+model!P13/5+model!R13*2+model!T13+model!U13*1.5)/6,0),1)*scoring_weights!$B$7,1) -> 30 | L13: =ROUND(F13+G13+H13+I13+J13+K13,1) -> 61.3 | M13: =IF(L13>=segment_thresholds!$B$2,"HOT",IF(L13>=segment_thresholds!$B$3,"WARM","COLD")) -> HOT | N13: =IF(M13="HOT","Schedule Call",IF(M13="WARM","Nurture Email Drip","Retarget with Ads")) -> Schedule Call | O13: =IF(L13<20,"0-19",IF(L13<40,"20-39",IF(L13<60,"40-59",IF(L13<80,"60-79","80-100")))) -> 60-79
A14: L0013 | B14: Julian Shah | C14: DROPBOX | D14: ORGANIC | E14: STARTUP | F14: =ROUND(IFERROR(model!I14/scoring_weights!$C$2,0)*scoring_weights!$B$2,1) -> 9.7 | G14: =ROUND(IFERROR(model!J14/scoring_weights!$C$3,0)*scoring_weights!$B$3,1) -> 4.5 | H14: =ROUND(IFERROR(model!K14/scoring_weights!$C$4,0)*scoring_weights!$B$4,1) -> 0.7 | I14: =IF(model!L14="YES",scoring_weights!$B$5,0) -> 0 | J14: =IF(model!D14="ENTERPRISE",scoring_weights!$B$6,IF(model!D14="MID-MARKET",scoring_weights!$B$6*0.75,IF(model!D14="SMB",scoring_weights!$B$6*0.5,IF(model!D14="STARTUP",scoring_weights!$B$6*0.25,0)))) -> 3.75 | K14: =ROUND(MIN(IFERROR((model!O14/10+model!P14/5+model!R14*2+model!T14+model!U14*1.5)/6,0),1)*scoring_weights!$B$7,1) -> 13 | L14: =ROUND(F14+G14+H14+I14+J14+K14,1) -> 31.7 | M14: =IF(L14>=segment_thresholds!$B$2,"HOT",IF(L14>=segment_thresholds!$B$3,"WARM","COLD")) -> COLD | N14: =IF(M14="HOT","Schedule Call",IF(M14="WARM","Nurture Email Drip","Retarget with Ads")) -> Retarget with Ads | O14: =IF(L14<20,"0-19",IF(L14<40,"20-39",IF(L14<60,"40-59",IF(L14<80,"60-79","80-100")))) -> 20-39
... A1001: L1000 | B1001: Leo Taylor | C1001: HUBSPOT | D1001: ORGANIC | E1001: SMB | F1001: =ROUND(IFERROR(model!I1001/scoring_weights!$C$2,0)*scoring_weights!$B$2,1) -> 6.9 | G1001: =ROUND(IFERROR(model!J1001/scoring_weights!$C$3,0)*scoring_weights!$B$3,1) -> 10.5 | H1001: =ROUND(IFERROR(model!K1001/scoring_weights!$C$4,0)*scoring_weights!$B$4,1) -> 0.8 | I1001: =IF(model!L1001="YES",scoring_weights!$B$5,0) -> 0 | J1001: =IF(model!D1001="ENTERPRISE",scoring_weights!$B$6,IF(model!D1001="MID-MARKET",scoring_weights!$B$6*0.75,IF(model!D1001="SMB",scoring_weights!$B$6*0.5,IF(model!D1001="STARTUP",scoring_weights!$B$6*0.25,0)))) -> 7.5 | K1001: =ROUND(MIN(IFERROR((model!O1001/10+model!P1001/5+model!R1001*2+model!T1001+model!U1001*1.5)/6,0),1)*scoring_weights!$B$7,1) -> 5 | L1001: =ROUND(F1001+G1001+H1001+I1001+J1001+K1001,1) -> 30.7 | M1001: =IF(L1001>=segment_thresholds!$B$2,"HOT",IF(L1001>=segment_thresholds!$B$3,"WARM","COLD")) -> COLD | N1001: =IF(M1001="HOT","Schedule Call",IF(M1001="WARM","Nurture Email Drip","Retarget with Ads")) -> Retarget with Ads | O1001: =IF(L1001<20,"0-19",IF(L1001<40,"20-39",IF(L1001<60,"40-59",IF(L1001<80,"60-79","80-100")))) -> 20-39

Sheet model
A1: lead_id | B1: name | C1: company | D1: company_size | E1: source | F1: industry | G1: job_title | H1: country | I1: email_opens | J1: clicks | K1: website_visits | L1: demo_requested | M1: lead_status | N1: data_quality | O1: total_interactions | P1: high_engagement | Q1: total_time_mins | R1: demo_requests | S1: content_downloads | T1: webinars_attended | U1: pricing_page_views | V1: source_total_spend | W1: source_total_leads | X1: source_cost_per_lead | Y1: source_roas
A2: {=clean_leads!A2:A1001} -> L0001 | B2: {=clean_leads!B2:B1001} -> Liora Jackson | C2: {=clean_leads!E2:E1001} -> AIRTABLE | D2: {=clean_leads!F2:F1001} -> SMB | E2: {=clean_leads!G2:G1001} -> UNKNOWN | F2: {=clean_leads!N2:N1001} -> Saas | G2: {=clean_leads!O2:O1001} -> Product Manager | H2: {=clean_leads!P2:P1001} -> Thailand | I2: {=clean_leads!H2:H1001} -> 35 | J2: {=clean_leads!I2:I1001} -> 20 | K2: {=clean_leads!J2:J1001} -> 26 | L2: {=clean_leads!K2:K1001} -> NO | M2: {=clean_leads!M2:M1001} -> ENGAGED | N2: =IF(COUNTBLANK(clean_leads!B2:S2)>=8,"LOW",IF(COUNTBLANK(clean_leads!B2:S2)>=4,"MEDIUM","HIGH")) -> HIGH | O2: =COUNTIF(clean_interactions!B:B,A2) -> 6 | P2: =COUNTIFS(clean_interactions!B:B,A2,clean_interactions!N:N,"HIGH") -> 5 | Q2: =ROUND(SUMIF(clean_interactions!B:B,A2,clean_interactions!M:M),1) -> 125.4 | R2: =COUNTIFS(clean_interactions!B:B,A2,clean_interactions!C:C,"DEMO_REQUEST") -> 1 | S2: =COUNTIFS(clean_interactions!B:B,A2,clean_interactions!C:C,"CONTENT_DOWNLOAD") -> 0 | T2: =COUNTIFS(clean_interactions!B:B,A2,clean_interactions!C:C,"WEBINAR_ATTENDED") -> 0 | U2: =COUNTIFS(clean_interactions!B:B,A2,clean_interactions!C:C,"PRICING_PAGE_VIEW") -> 0 | V2: =SUMIF(clean_spend!D:D,E2,clean_spend!F:F) -> 0 | W2: =SUMIF(clean_spend!D:D,E2,clean_spend!J:J) -> 0 | X2: =IFERROR(V2/W2,0) -> 0 | Y2: =IFERROR(SUMIF(clean_spend!D:D,E2,clean_spend!L:L)/V2,0) -> 0
A3: L0002 | B3: Yara Malik | C3: AIRTABLE | D3: SMB | E3: EVENT | F3: Retail | G3: Sales Engineer | H3: IN | I3: 4 | J3: 0 | K3: 18 | L3: YES | M3: QUALIFIED | N3: =IF(COUNTBLANK(clean_leads!B3:S3)>=8,"LOW",IF(COUNTBLANK(clean_leads!B3:S3)>=4,"MEDIUM","HIGH")) -> HIGH | O3: =COUNTIF(clean_interactions!B:B,A3) -> 1 | P3: =COUNTIFS(clean_interactions!B:B,A3,clean_interactions!N:N,"HIGH") -> 1 | Q3: =ROUND(SUMIF(clean_interactions!B:B,A3,clean_interactions!M:M),1) -> 32.4 | R3: =COUNTIFS(clean_interactions!B:B,A3,clean_interactions!C:C,"DEMO_REQUEST") -> 0 | S3: =COUNTIFS(clean_interactions!B:B,A3,clean_interactions!C:C,"CONTENT_DOWNLOAD") -> 0 | T3: =COUNTIFS(clean_interactions!B:B,A3,clean_interactions!C:C,"WEBINAR_ATTENDED") -> 0 | U3: =COUNTIFS(clean_interactions!B:B,A3,clean_interactions!C:C,"PRICING_PAGE_VIEW") -> 0 | V3: =SUMIF(clean_spend!D:D,E3,clean_spend!F:F) -> 130023 | W3: =SUMIF(clean_spend!D:D,E3,clean_spend!J:J) -> 322 | X3: =IFERROR(V3/W3,0) -> 403.79814 | Y3: =IFERROR(SUMIF(clean_spend!D:D,E3,clean_spend!L:L)/V3,0) -> 1.3116295
A4: L0003 | B4: Luna Harris | C4: CROWD STRIKE | D4: SMB | E4: EVENT | F4: AI/ML | G4: Business Development Rep | H4: AU | I4: 13 | J4: 18 | K4: 20 | L4: YES | M4: QUALIFIED | N4: =IF(COUNTBLANK(clean_leads!B4:S4)>=8,"LOW",IF(COUNTBLANK(clean_leads!B4:S4)>=4,"MEDIUM","HIGH")) -> HIGH | O4: =COUNTIF(clean_interactions!B:B,A4) -> 7 | P4: =COUNTIFS(clean_interactions!B:B,A4,clean_interactions!N:N,"HIGH") -> 6 | Q4: =ROUND(SUMIF(clean_interactions!B:B,A4,clean_interactions!M:M),1) -> 136.8 | R4: =COUNTIFS(clean_interactions!B:B,A4,clean_interactions!C:C,"DEMO_REQUEST") -> 0 | S4: =COUNTIFS(clean_interactions!B:B,A4,clean_interactions!C:C,"CONTENT_DOWNLOAD") -> 1 | T4: =COUNTIFS(clean_interactions!B:B,A4,clean_interactions!C:C,"WEBINAR_ATTENDED") -> 0 | U4: =COUNTIFS(clean_interactions!B:B,A4,clean_interactions!C:C,"PRICING_PAGE_VIEW") -> 0 | V4: =SUMIF(clean_spend!D:D,E4,clean_spend!F:F) -> 130023 | W4: =SUMIF(clean_spend!D:D,E4,clean_spend!J:J) -> 322 | X4: =IFERROR(V4/W4,0) -> 403.79814 | Y4: =IFERROR(SUMIF(clean_spend!D:D,E4,clean_spend!L:L)/V4,0) -> 1.3116295
A5: L0004 | B5: James Nakamura | C5: HUB SPOT | D5: STARTUP | E5: PARTNER | F5: Logistics | G5: Revops Manager | H5: Netherlands | I5: 35 | J5: 0 | K5: 7 | L5: NO | M5: NEW | N5: =IF(COUNTBLANK(clean_leads!B5:S5)>=8,"LOW",IF(COUNTBLANK(clean_leads!B5:S5)>=4,"MEDIUM","HIGH")) -> HIGH | O5: =COUNTIF(clean_interactions!B:B,A5) -> 3 | P5: =COUNTIFS(clean_interactions!B:B,A5,clean_interactions!N:N,"HIGH") -> 2 | Q5: =ROUND(SUMIF(clean_interactions!B:B,A5,clean_interactions!M:M),1) -> 44.1 | R5: =COUNTIFS(clean_interactions!B:B,A5,clean_interactions!C:C,"DEMO_REQUEST") -> 0 | S5: =COUNTIFS(clean_interactions!B:B,A5,clean_interactions!C:C,"CONTENT_DOWNLOAD") -> 0 | T5: =COUNTIFS(clean_interactions!B:B,A5,clean_interactions!C:C,"WEBINAR_ATTENDED") -> 0 | U5: =COUNTIFS(clean_interactions!B:B,A5,clean_interactions!C:C,"PRICING_PAGE_VIEW") -> 1 | V5: =SUMIF(clean_spend!D:D,E5,clean_spend!F:F) -> 0 | W5: =SUMIF(clean_spend!D:D,E5,clean_spend!J:J) -> 0 | X5: =IFERROR(V5/W5,0) -> 0 | Y5: =IFERROR(SUMIF(clean_spend!D:D,E5,clean_spend!L:L)/V5,0) -> 0
A6: L0005 | B6: Bastian Mishra | C6: DROPBOX | D6: SMB | E6: UNKNOWN | F6: Healthcare | G6: Cto | H6: AU | I6: 0 | J6: 9 | K6: 15 | L6: YES | M6: NURTURING | N6: =IF(COUNTBLANK(clean_leads!B6:S6)>=8,"LOW",IF(COUNTBLANK(clean_leads!B6:S6)>=4,"MEDIUM","HIGH")) -> HIGH | O6: =COUNTIF(clean_interactions!B:B,A6) -> 5 | P6: =COUNTIFS(clean_interactions!B:B,A6,clean_interactions!N:N,"HIGH") -> 4 | Q6: =ROUND(SUMIF(clean_interactions!B:B,A6,clean_interactions!M:M),1) -> 119.4 | R6: =COUNTIFS(clean_interactions!B:B,A6,clean_interactions!C:C,"DEMO_REQUEST") -> 1 | S6: =COUNTIFS(clean_interactions!B:B,A6,clean_interactions!C:C,"CONTENT_DOWNLOAD") -> 1 | T6: =COUNTIFS(clean_interactions!B:B,A6,clean_interactions!C:C,"WEBINAR_ATTENDED") -> 0 | U6: =COUNTIFS(clean_interactions!B:B,A6,clean_interactions!C:C,"PRICING_PAGE_VIEW") -> 0 | V6: =SUMIF(clean_spend!D:D,E6,clean_spend!F:F) -> 0 | W6: =SUMIF(clean_spend!D:D,E6,clean_spend!J:J) -> 0 | X6: =IFERROR(V6/W6,0) -> 0 | Y6: =IFERROR(SUMIF(clean_spend!D:D,E6,clean_spend!L:L)/V6,0) -> 0
A7: L0006 | B7: Yuki Robinson | C7: CLOUDFLARE | D7: SMB | E7: ORGANIC | F7: Fintech | G7: Program Manager | H7: CA | I7: 14 | J7: 0 | K7: 0 | L7: YES | M7: QUALIFIED | N7: =IF(COUNTBLANK(clean_leads!B7:S7)>=8,"LOW",IF(COUNTBLANK(clean_leads!B7:S7)>=4,"MEDIUM","HIGH")) -> HIGH | O7: =COUNTIF(clean_interactions!B:B,A7) -> 3 | P7: =COUNTIFS(clean_interactions!B:B,A7,clean_interactions!N:N,"HIGH") -> 2 | Q7: =ROUND(SUMIF(clean_interactions!B:B,A7,clean_interactions!M:M),1) -> 54.2 | R7: =COUNTIFS(clean_interactions!B:B,A7,clean_interactions!C:C,"DEMO_REQUEST") -> 0 | S7: =COUNTIFS(clean_interactions!B:B,A7,clean_interactions!C:C,"CONTENT_DOWNLOAD") -> 0 | T7: =COUNTIFS(clean_interactions!B:B,A7,clean_interactions!C:C,"WEBINAR_ATTENDED") -> 0 | U7: =COUNTIFS(clean_interactions!B:B,A7,clean_interactions!C:C,"PRICING_PAGE_VIEW") -> 1 | V7: =SUMIF(clean_spend!D:D,E7,clean_spend!F:F) -> 46997 | W7: =SUMIF(clean_spend!D:D,E7,clean_spend!J:J) -> 970 | X7: =IFERROR(V7/W7,0) -> 48.450515 | Y7: =IFERROR(SUMIF(clean_spend!D:D,E7,clean_spend!L:L)/V7,0) -> 13.49418
A8: L0007 | B8: Uriel Jensen | C8: STRIPE INC | D8: STARTUP | E8: COLD_EMAIL | F8: E-Commerce | G8: Sales Operations | H8: DE | I8: 6 | J8: 6 | K8: 8 | L8: NO | M8: ENGAGED | N8: =IF(COUNTBLANK(clean_leads!B8:S8)>=8,"LOW",IF(COUNTBLANK(clean_leads!B8:S8)>=4,"MEDIUM","HIGH")) -> HIGH | O8: =COUNTIF(clean_interactions!B:B,A8) -> 4 | P8: =COUNTIFS(clean_interactions!B:B,A8,clean_interactions!N:N,"HIGH") -> 2 | Q8: =ROUND(SUMIF(clean_interactions!B:B,A8,clean_interactions!M:M),1) -> 58.8 | R8: =COUNTIFS(clean_interactions!B:B,A8,clean_interactions!C:C,"DEMO_REQUEST") -> 0 | S8: =COUNTIFS(clean_interactions!B:B,A8,clean_interactions!C:C,"CONTENT_DOWNLOAD") -> 0 | T8: =COUNTIFS(clean_interactions!B:B,A8,clean_interactions!C:C,"WEBINAR_ATTENDED") -> 0 | U8: =COUNTIFS(clean_interactions!B:B,A8,clean_interactions!C:C,"PRICING_PAGE_VIEW") -> 2 | V8: =SUMIF(clean_spend!D:D,E8,clean_spend!F:F) -> 63789 | W8: =SUMIF(clean_spend!D:D,E8,clean_spend!J:J) -> 306 | X8: =IFERROR(V8/W8,0) -> 208.46078 | Y8: =IFERROR(SUMIF(clean_spend!D:D,E8,clean_spend!L:L)/V8,0) -> 3.061092
A9: L0008 | B9: Vivian Young | C9: GOOGLE | D9: MID-MARKET | E9: SOCIAL | F9: Automotive | G9: Intern | H9: IN | I9: 3 | J9: 17 | K9: 0 | L9: YES | M9: NEW | N9: =IF(COUNTBLANK(clean_leads!B9:S9)>=8,"LOW",IF(COUNTBLANK(clean_leads!B9:S9)>=4,"MEDIUM","HIGH")) -> HIGH | O9: =COUNTIF(clean_interactions!B:B,A9) -> 4 | P9: =COUNTIFS(clean_interactions!B:B,A9,clean_interactions!N:N,"HIGH") -> 4 | Q9: =ROUND(SUMIF(clean_interactions!B:B,A9,clean_interactions!M:M),1) -> 63.1 | R9: =COUNTIFS(clean_interactions!B:B,A9,clean_interactions!C:C,"DEMO_REQUEST") -> 0 | S9: =COUNTIFS(clean_interactions!B:B,A9,clean_interactions!C:C,"CONTENT_DOWNLOAD") -> 0 | T9: =COUNTIFS(clean_interactions!B:B,A9,clean_interactions!C:C,"WEBINAR_ATTENDED") -> 0 | U9: =COUNTIFS(clean_interactions!B:B,A9,clean_interactions!C:C,"PRICING_PAGE_VIEW") -> 0 | V9: =SUMIF(clean_spend!D:D,E9,clean_spend!F:F) -> 198205 | W9: =SUMIF(clean_spend!D:D,E9,clean_spend!J:J) -> 961 | X9: =IFERROR(V9/W9,0) -> 206.2487 | Y9: =IFERROR(SUMIF(clean_spend!D:D,E9,clean_spend!L:L)/V9,0) -> 2.4999924
A10: L0009 | B10: Elena Pandey | C10: ELASTIC | D10: SMB | E10: EVENT | F10: Legal Tech | G10: Intern | H10: N/A | I10: 19 | J10: 2 | K10: 0 | L10: NO | M10: CONVERTED | N10: =IF(COUNTBLANK(clean_leads!B10:S10)>=8,"LOW",IF(COUNTBLANK(clean_leads!B10:S10)>=4,"MEDIUM","HIGH")) -> HIGH | O10: =COUNTIF(clean_interactions!B:B,A10) -> 3 | P10: =COUNTIFS(clean_interactions!B:B,A10,clean_interactions!N:N,"HIGH") -> 3 | Q10: =ROUND(SUMIF(clean_interactions!B:B,A10,clean_interactions!M:M),1) -> 66.7 | R10: =COUNTIFS(clean_interactions!B:B,A10,clean_interactions!C:C,"DEMO_REQUEST") -> 0 | S10: =COUNTIFS(clean_interactions!B:B,A10,clean_interactions!C:C,"CONTENT_DOWNLOAD") -> 0 | T10: =COUNTIFS(clean_interactions!B:B,A10,clean_interactions!C:C,"WEBINAR_ATTENDED") -> 0 | U10: =COUNTIFS(clean_interactions!B:B,A10,clean_interactions!C:C,"PRICING_PAGE_VIEW") -> 0 | V10: =SUMIF(clean_spend!D:D,E10,clean_spend!F:F) -> 130023 | W10: =SUMIF(clean_spend!D:D,E10,clean_spend!J:J) -> 322 | X10: =IFERROR(V10/W10,0) -> 403.79814 | Y10: =IFERROR(SUMIF(clean_spend!D:D,E10,clean_spend!L:L)/V10,0) -> 1.3116295
A11: L0010 | B11: Priya Muller | C11: PALO ALTO | D11: MID-MARKET | E11: PAID | F11: Proptech | G11: Head Of Growth | H11: DE | I11: 9 | J11: 19 | K11: 21 | L11: YES | M11: NURTURING | N11: =IF(COUNTBLANK(clean_leads!B11:S11)>=8,"LOW",IF(COUNTBLANK(clean_leads!B11:S11)>=4,"MEDIUM","HIGH")) -> HIGH | O11: =COUNTIF(clean_interactions!B:B,A11) -> 5 | P11: =COUNTIFS(clean_interactions!B:B,A11,clean_interactions!N:N,"HIGH") -> 3 | Q11: =ROUND(SUMIF(clean_interactions!B:B,A11,clean_interactions!M:M),1) -> 103.7 | R11: =COUNTIFS(clean_interactions!B:B,A11,clean_interactions!C:C,"DEMO_REQUEST") -> 0 | S11: =COUNTIFS(clean_interactions!B:B,A11,clean_interactions!C:C,"CONTENT_DOWNLOAD") -> 1 | T11: =COUNTIFS(clean_interactions!B:B,A11,clean_interactions!C:C,"WEBINAR_ATTENDED") -> 0 | U11: =COUNTIFS(clean_interactions!B:B,A11,clean_interactions!C:C,"PRICING_PAGE_VIEW") -> 0 | V11: =SUMIF(clean_spend!D:D,E11,clean_spend!F:F) -> 149793 | W11: =SUMIF(clean_spend!D:D,E11,clean_spend!J:J) -> 1090 | X11: =IFERROR(V11/W11,0) -> 137.42477 | Y11: =IFERROR(SUMIF(clean_spend!D:D,E11,clean_spend!L:L)/V11,0) -> 3.4229971
A12: L0011 | B12: Landon Rossi | C12: CROWD STRIKE | D12: SMB | E12: EVENT | F12: AI/ML | G12: Growth Hacker | H12: IN | I12: 2 | J12: 6 | K12: 42 | L12: NO | M12: CONTACTED | N12: =IF(COUNTBLANK(clean_leads!B12:S12)>=8,"LOW",IF(COUNTBLANK(clean_leads!B12:S12)>=4,"MEDIUM","HIGH")) -> HIGH | O12: =COUNTIF(clean_interactions!B:B,A12) -> 8 | P12: =COUNTIFS(clean_interactions!B:B,A12,clean_interactions!N:N,"HIGH") -> 7 | Q12: =ROUND(SUMIF(clean_interactions!B:B,A12,clean_interactions!M:M),1) -> 100.3 | R12: =COUNTIFS(clean_interactions!B:B,A12,clean_interactions!C:C,"DEMO_REQUEST") -> 0 | S12: =COUNTIFS(clean_interactions!B:B,A12,clean_interactions!C:C,"CONTENT_DOWNLOAD") -> 0 | T12: =COUNTIFS(clean_interactions!B:B,A12,clean_interactions!C:C,"WEBINAR_ATTENDED") -> 1 | U12: =COUNTIFS(clean_interactions!B:B,A12,clean_interactions!C:C,"PRICING_PAGE_VIEW") -> 0 | V12: =SUMIF(clean_spend!D:D,E12,clean_spend!F:F) -> 130023 | W12: =SUMIF(clean_spend!D:D,E12,clean_spend!J:J) -> 322 | X12: =IFERROR(V12/W12,0) -> 403.79814 | Y12: =IFERROR(SUMIF(clean_spend!D:D,E12,clean_spend!L:L)/V12,0) -> 1.3116295
A13: L0012 | B13: Jamal Soto | C13: NOTION | D13: N/A | E13: COLD_EMAIL | F13: Energy | G13: Pr Manager | H13: Mexico | I13: 14 | J13: 6 | K13: 17 | L13: YES | M13: NEW | N13: =IF(COUNTBLANK(clean_leads!B13:S13)>=8,"LOW",IF(COUNTBLANK(clean_leads!B13:S13)>=4,"MEDIUM","HIGH")) -> HIGH | O13: =COUNTIF(clean_interactions!B:B,A13) -> 5 | P13: =COUNTIFS(clean_interactions!B:B,A13,clean_interactions!N:N,"HIGH") -> 4 | Q13: =ROUND(SUMIF(clean_interactions!B:B,A13,clean_interactions!M:M),1) -> 71.7 | R13: =COUNTIFS(clean_interactions!B:B,A13,clean_interactions!C:C,"DEMO_REQUEST") -> 3 | S13: =COUNTIFS(clean_interactions!B:B,A13,clean_interactions!C:C,"CONTENT_DOWNLOAD") -> 0 | T13: =COUNTIFS(clean_interactions!B:B,A13,clean_interactions!C:C,"WEBINAR_ATTENDED") -> 0 | U13: =COUNTIFS(clean_interactions!B:B,A13,clean_interactions!C:C,"PRICING_PAGE_VIEW") -> 0 | V13: =SUMIF(clean_spend!D:D,E13,clean_spend!F:F) -> 63789 | W13: =SUMIF(clean_spend!D:D,E13,clean_spend!J:J) -> 306 | X13: =IFERROR(V13/W13,0) -> 208.46078 | Y13: =IFERROR(SUMIF(clean_spend!D:D,E13,clean_spend!L:L)/V13,0) -> 3.061092
A14: L0013 | B14: Julian Shah | C14: DROPBOX | D14: STARTUP | E14: ORGANIC | F14: Cybersecurity | G14: Marketing Coordinator | H14: Ireland | I14: 34 | J14: 6 | K14: 4 | L14: NO | M14: CONTACTED | N14: =IF(COUNTBLANK(clean_leads!B14:S14)>=8,"LOW",IF(COUNTBLANK(clean_leads!B14:S14)>=4,"MEDIUM","HIGH")) -> HIGH | O14: =COUNTIF(clean_interactions!B:B,A14) -> 2 | P14: =COUNTIFS(clean_interactions!B:B,A14,clean_interactions!N:N,"HIGH") -> 2 | Q14: =ROUND(SUMIF(clean_interactions!B:B,A14,clean_interactions!M:M),1) -> 56.3 | R14: =COUNTIFS(clean_interactions!B:B,A14,clean_interactions!C:C,"DEMO_REQUEST") -> 1 | S14: =COUNTIFS(clean_interactions!B:B,A14,clean_interactions!C:C,"CONTENT_DOWNLOAD") -> 0 | T14: =COUNTIFS(clean_interactions!B:B,A14,clean_interactions!C:C,"WEBINAR_ATTENDED") -> 0 | U14: =COUNTIFS(clean_interactions!B:B,A14,clean_interactions!C:C,"PRICING_PAGE_VIEW") -> 0 | V14: =SUMIF(clean_spend!D:D,E14,clean_spend!F:F) -> 46997 | W14: =SUMIF(clean_spend!D:D,E14,clean_spend!J:J) -> 970 | X14: =IFERROR(V14/W14,0) -> 48.450515 | Y14: =IFERROR(SUMIF(clean_spend!D:D,E14,clean_spend!L:L)/V14,0) -> 13.49418
... A1001: L1000 | B1001: Leo Taylor | C1001: HUBSPOT | D1001: SMB | E1001: ORGANIC | F1001: Gaming | G1001: Marketing Operations | H1001: US | I1001: 24 | J1001: 14 | K1001: 5 | L1001: NO | M1001: DISQUALIFIED | N1001: =IF(COUNTBLANK(clean_leads!B1001:S1001)>=8,"LOW",IF(COUNTBLANK(clean_leads!B1001:S1001)>=4,"MEDIUM","HIGH")) -> HIGH | O1001: =COUNTIF(clean_interactions!B:B,A1001) -> 4 | P1001: =COUNTIFS(clean_interactions!B:B,A1001,clean_interactions!N:N,"HIGH") -> 3 | Q1001: =ROUND(SUMIF(clean_interactions!B:B,A1001,clean_interactions!M:M),1) -> 60.9 | R1001: =COUNTIFS(clean_interactions!B:B,A1001,clean_interactions!C:C,"DEMO_REQUEST") -> 0 | S1001: =COUNTIFS(clean_interactions!B:B,A1001,clean_interactions!C:C,"CONTENT_DOWNLOAD") -> 0 | T1001: =COUNTIFS(clean_interactions!B:B,A1001,clean_interactions!C:C,"WEBINAR_ATTENDED") -> 0 | U1001: =COUNTIFS(clean_interactions!B:B,A1001,clean_interactions!C:C,"PRICING_PAGE_VIEW") -> 0 | V1001: =SUMIF(clean_spend!D:D,E1001,clean_spend!F:F) -> 46997 | W1001: =SUMIF(clean_spend!D:D,E1001,clean_spend!J:J) -> 970 | X1001: =IFERROR(V1001/W1001,0) -> 48.450515 | Y1001: =IFERROR(SUMIF(clean_spend!D:D,E1001,clean_spend!L:L)/V1001,0) -> 13.49418

Sheet segment_thresholds
A1: Segment | B1: Min Score
A2: HOT | B2: 60
A3: WARM | B3: 35
A4: COLD | B4: 0

Sheet scoring_weights
A1: Metric | B1: Weight | C1: Max Raw
A2: Email Opens | B2: 10 | C2: 35
A3: Clicks | B3: 15 | C3: 20
A4: Website Visits | B4: 10 | C4: 60
A5: Demo Requested | B5: 20 | C5: 1
A6: Company Size | B6: 15 | C6: 1
A7: Engagement Score | B7: 30 | C7: 1

Sheet clean_leads
A1: lead_id | B1: name | C1: email | D1: phone | E1: company | F1: company_size | G1: source | H1: email_opens | I1: clicks | J1: website_visits | K1: demo_requested | L1: last_activity | M1: lead_status | N1: industry | O1: job_title | P1: country | Q1: annual_revenue | R1: lead_created_date | S1: linkedin_url
A2: {=raw_leads!A2:A1001} -> L0001 | B2: {=IF(TRIM(raw_leads!B2:B1001)="","Unknown",PROPER(TRIM(raw_leads!B2:B1001)))} -> Liora Jackson | C2: {=IF(TRIM(raw_leads!C2:C1001)="","missing",LOWER(TRIM(raw_leads!C2:C1001)))} -> liora.jackson@airtable.com | D2: {=IF(TRIM(raw_leads!D2:D1001)="","missing",TRIM(raw_leads!D2:D1001))} -> 232-130-2535 | E2: {=IF(TRIM(raw_leads!E2:E1001)="","UNKNOWN",UPPER(TRIM(raw_leads!E2:E1001)))} -> AIRTABLE | F2: {=IF(TRIM(raw_leads!F2:F1001)="","N/A",IF((UPPER(TRIM(raw_leads!F2:F1001))="SMALL BUSINESS")+(UPPER(TRIM(raw_leads!F2:F1001))="SMB"),"SMB",IF((UPPER(TRIM(raw_leads!F2:F1001))="MID-MARKET")+(UPPER(TRIM(raw_leads!F2:F1001))="MID MARKET"),"MID-MARKET",IF(UPPER(TRIM(raw_leads!F2:F1001))="GROWTH","GROWTH",UPPER(TRIM(raw_leads!F2:F1001))))))} -> SMB | G2: {=IF(TRIM(raw_leads!G2:G1001)="","UNKNOWN",IF((UPPER(TRIM(raw_leads!G2:G1001))="COLD EMAIL")+(UPPER(TRIM(raw_leads!G2:G1001))="COLD_EMAIL"),"COLD_EMAIL",IF((UPPER(TRIM(raw_leads!G2:G1001))="CONTENT SYNDICATION")+(UPPER(TRIM(raw_leads!G2:G1001))="CONTENT_SYNDICATION"),"CONTENT_SYNDICATION",UPPER(TRIM(raw_leads!G2:G1001)))))} -> UNKNOWN | H2: {=IF((raw_leads!H2:H1001="")+(NOT(ISNUMBER(raw_leads!H2:H1001))),0,raw_leads!H2:H1001)} -> 35 | I2: {=IF((raw_leads!I2:I1001="")+(NOT(ISNUMBER(raw_leads!I2:I1001))),0,raw_leads!I2:I1001)} -> 20 | J2: {=IF((raw_leads!J2:J1001="")+(NOT(ISNUMBER(raw_leads!J2:J1001))),0,raw_leads!J2:J1001)} -> 26 | K2: {=IF((UPPER(TRIM(raw_leads!K2:K1001))="YES")+(UPPER(TRIM(raw_leads!K2:K1001))="Y")+(UPPER(TRIM(raw_leads!K2:K1001))="TRUE")+(TRIM(raw_leads!K2:K1001)="1"),"YES","NO")} -> NO | L2: {=IF(raw_leads!L2:L1001="","",raw_leads!L2:L1001)} -> 45803 | M2: {=IF(TRIM(raw_leads!M2:M1001)="","NEW",UPPER(TRIM(raw_leads!M2:M1001)))} -> ENGAGED | N2: {=IF(TRIM(raw_leads!N2:N1001)="","Unknown",IF((UPPER(TRIM(raw_leads!N2:N1001))="ECOMMERCE")+(UPPER(TRIM(raw_leads!N2:N1001))="E-COMMERCE"),"E-Commerce",IF((UPPER(TRIM(raw_leads!N2:N1001))="AI/ML")+(UPPER(TRIM(raw_leads!N2:N1001))="AI / ML"),"AI/ML",IF((UPPER(TRIM(raw_leads!N2:N1001))="LEGALTECH")+(UPPER(TRIM(raw_leads!N2:N1001))="LEGAL TECH"),"Legal Tech",IF((UPPER(TRIM(raw_leads!N2:N1001))="SUPPLYCHAIN")+(UPPER(TRIM(raw_leads!N2:N1001))="SUPPLY CHAIN"),"Supply Chain",PROPER(TRIM(raw_leads!N2:N1001)))))))} -> Saas | O2: {=IF(TRIM(raw_leads!O2:O1001)="","Unknown",PROPER(TRIM(raw_leads!O2:O1001)))} -> Product Manager | P2: {=IF(TRIM(raw_leads!P2:P1001)="","N/A",IF((UPPER(TRIM(raw_leads!P2:P1001))="UNITED STATES")+(UPPER(TRIM(raw_leads!P2:P1001))="USA")+(UPPER(TRIM(raw_leads!P2:P1001))="US"),"US",IF((UPPER(TRIM(raw_leads!P2:P1001))="UNITED KINGDOM")+(UPPER(TRIM(raw_leads!P2:P1001))="UK"),"UK",IF((UPPER(TRIM(raw_leads!P2:P1001))="CANADA")+(UPPER(TRIM(raw_leads!P2:P1001))="CA"),"CA",IF((UPPER(TRIM(raw_leads!P2:P1001))="GERMANY")+(UPPER(TRIM(raw_leads!P2:P1001))="DE"),"DE",IF((UPPER(TRIM(raw_leads!P2:P1001))="FRANCE")+(UPPER(TRIM(raw_leads!P2:P1001))="FR"),"FR",IF((UPPER(TRIM(raw_leads!P2:P1001))="AUSTRALIA")+(UPPER(TRIM(raw_leads!P2:P1001))="AU"),"AU",IF((UPPER(TRIM(raw_leads!P2:P1001))="INDIA")+(UPPER(TRIM(raw_leads!P2:P1001))="IN"),"IN",IF((UPPER(TRIM(raw_leads!P2:P1001))="JAPAN")+(UPPER(TRIM(raw_leads!P2:P1001))="JP"),"JP",IF((UPPER(TRIM(raw_leads!P2:P1001))="BRAZIL")+(UPPER(TRIM(raw_leads!P2:P1001))="BR"),"BR",IF((UPPER(TRIM(raw_leads!P2:P1001))="SINGAPORE")+(UPPER(TRIM(raw_leads!P2:P1001))="SG"),"SG",PROPER(TRIM(raw_leads!P2:P1001)))))))))))))} -> Thailand | Q2: {=IF(TRIM(raw_leads!Q2:Q1001)="","Unknown",TRIM(raw_leads!Q2:Q1001))} -> $100M-500M | R2: {=IF(raw_leads!R2:R1001="","",raw_leads!R2:R1001)} -> 45812 | S2: {=IF(TRIM(raw_leads!S2:S1001)="","missing",LOWER(TRIM(raw_leads!S2:S1001)))} -> missing
A3: L0002 | B3: Yara Malik | C3: yara.malik@airtable.com | D3: missing | E3: AIRTABLE | F3: SMB | G3: EVENT | H3: 4 | I3: 0 | J3: 18 | K3: YES | L3: 45701 | M3: QUALIFIED | N3: Retail | O3: Sales Engineer | P3: IN | Q3: $1B+ | R3: 46013 | S3: linkedin.com/in/dashiellpopov22
A4: L0003 | B4: Luna Harris | C4: luna.harris@crowdstrike.com | D4: 434.941.1525 | E4: CROWD STRIKE | F4: SMB | G4: EVENT | H4: 13 | I4: 18 | J4: 20 | K4: YES | L4: 45859 | M4: QUALIFIED | N4: AI/ML | O4: Business Development Rep | P4: AU | Q4: $50M - $100M | R4: 46010 | S4: https://linkedin.com/in/xylanguyen47
A5: L0004 | B5: James Nakamura | C5: james.nakamura@hubspot.com | D5: missing | E5: HUB SPOT | F5: STARTUP | G5: PARTNER | H5: 35 | I5: 0 | J5: 7 | K5: NO | L5: 45802 | M5: NEW | N5: Logistics | O5: Revops Manager | P5: Netherlands | Q5: Unknown | S5: https://linkedin.com/in/ravischneider98
A6: L0005 | B6: Bastian Mishra | C6: bastian.mishra@dropbox.com | D6: +1-997-643-1009 | E6: DROPBOX | F6: SMB | G6: UNKNOWN | H6: 0 | I6: 9 | J6: 15 | K6: YES | L6: 45712 | M6: NURTURING | N6: Healthcare | O6: Cto | P6: AU | Q6: $50M - $100M | R6: 45928 | S6: linkedin.com/in/deepasaxena70
A7: L0006 | B7: Yuki Robinson | C7: yuki.robinson@cloudflare.com | D7: missing | E7: CLOUDFLARE | F7: SMB | G7: ORGANIC | H7: 14 | I7: 0 | J7: 0 | K7: YES | M7: QUALIFIED | N7: Fintech | O7: Program Manager | P7: CA | Q7: 1M-10M | R7: 45765 | S7: missing
A8: L0007 | B8: Uriel Jensen | C8: uriel.jensen@stripeinc.com | D8: (946) 155-2612 | E8: STRIPE INC | F8: STARTUP | G8: COLD_EMAIL | H8: 6 | I8: 6 | J8: 8 | K8: NO | L8: 45877 | M8: ENGAGED | N8: E-Commerce | O8: Sales Operations | P8: DE | Q8: Unknown | R8: 45660 | S8: www.linkedin.com/in/jasminesanchez53
A9: L0008 | B9: Vivian Young | C9: vivian.young@google.com | D9: 633-813-8973 | E9: GOOGLE | F9: MID-MARKET | G9: SOCIAL | H9: 3 | I9: 17 | J9: 0 | K9: YES | M9: NEW | N9: Automotive | O9: Intern | P9: IN | Q9: Unknown | R9: 45719 | S9: www.linkedin.com/in/umbraiyer31
A10: L0009 | B10: Elena Pandey | C10: elena.pandey@elastic.com | D10: 467-309-6147 | E10: ELASTIC | F10: SMB | G10: EVENT | H10: 19 | I10: 2 | J10: 0 | K10: NO | L10: 45691 | M10: CONVERTED | N10: Legal Tech | O10: Intern | P10: N/A | Q10: Unknown | R10: 45696 | S10: missing
A11: L0010 | B11: Priya Muller | C11: priya.muller@paloalto.com | D11: 3069993200 | E11: PALO ALTO | F11: MID-MARKET | G11: PAID | H11: 9 | I11: 19 | J11: 21 | K11: YES | L11: 45794 | M11: NURTURING | N11: Proptech | O11: Head Of Growth | P11: DE | Q11: Series C+ | R11: 45668 | S11: linkedin.com/in/liorascott21
A12: L0011 | B12: Landon Rossi | C12: landon.rossi@crowdstrike.com | D12: (351) 540-3088 | E12: CROWD STRIKE | F12: SMB | G12: EVENT | H12: 2 | I12: 6 | J12: 42 | K12: NO | L12: 45928 | M12: CONTACTED | N12: AI/ML | O12: Growth Hacker | P12: IN | Q12: Series B | R12: 45839 | S12: missing
A13: L0012 | B13: Jamal Soto | C13: jamal.soto@notion.com | D13: 681.327.4269 | E13: NOTION | F13: N/A | G13: COLD_EMAIL | H13: 14 | I13: 6 | J13: 17 | K13: YES | L13: 45789 | M13: NEW | N13: Energy | O13: Pr Manager | P13: Mexico | Q13: $50M-100M | R13: 45783 | S13: linkedin.com/in/ravijones14
A14: L0013 | B14: Julian Shah | C14: julian.shah@dropbox.com | D14: missing | E14: DROPBOX | F14: STARTUP | G14: ORGANIC | H14: 34 | I14: 6 | J14: 4 | K14: NO | L14: 45941 | M14: CONTACTED | N14: Cybersecurity | O14: Marketing Coordinator | P14: Ireland | Q14: 50M+ | R14: 45795 | S14: missing
A15: L0014 | B15: Finn Torres | C15: finn.torres@databricks.com | D15: +14155406279 | E15: DATABRICKS | F15: N/A | G15: PARTNER | H15: 32 | I15: 5 | J15: 18 | K15: YES | L15: 45941 | M15: QUALIFIED | N15: Insurtech | O15: Marketing Analyst | P15: BR | Q15: $100M-500M | S15: missing
A16: L0015 | B16: Tatiana Dubois | C16: tatiana.dubois@elastic.com | D16: 351.771.1090 | E16: ELASTIC | F16: MID-MARKET | G16: CONTENT_SYNDICATION | H16: 33 | I16: 17 | J16: 54 | K16: NO | L16: 45891 | M16: LOST | N16: Unknown | O16: Sales Operations | P16: Thailand | Q16: $50M - $100M | R16: 45740 | S16: https://linkedin.com/in/nicoscott97
A17: L0016 | B17: Liora Adams | C17: liora.adams@datadog.com | D17: 753-182-3267 | E17: DATADOG | F17: SMB | G17: EVENT | H17: 13 | I17: 0 | J17: 34 | K17: NO | L17: 45774 | M17: CONTACTED | N17: Supply Chain | O17: Cmo | P17: South Africa | Q17: < $1M | R17: 45866 | S17: linkedin.com/in/finnolsen96
A18: L0017 | B18: Margaux Aguilar | C18: margaux.aguilar@asana.com | D18: 941-269-8657 | E18: ASANA | F18: MID-MARKET | G18: DIRECT | H18: 0 | I18: 18 | J18: 5 | K18: YES | L18: 45875 | M18: CONTACTED | N18: Cleantech | O18: Channel Manager | P18: South Korea | Q18: 50M+ | R18: 45847 | S18: www.linkedin.com/in/finnhill11
A19: L0018 | B19: Eve Mendoza | C19: missing | D19: missing | E19: SPLUNK | F19: SMB | G19: WEBINAR | H19: 9 | I19: 15 | J19: 36 | K19: YES | L19: 45802 | M19: CONVERTED | N19: Martech | O19: Revops Manager | P19: IN | Q19: $50M-100M | R19: 45796 | S19: https://linkedin.com/in/umaro'brien92
A20: L0019 | B20: Tina Petrov | C20: tina.petrov@linear.com | D20: 7799011672 | E20: LINEAR | F20: ENTERPRISE | G20: CONTENT_SYNDICATION | H20: 4 | I20: 10 | J20: 0 | K20: NO | L20: 45702 | M20: CONVERTED | N20: Retail | O20: Co-Founder | P20: Vietnam | Q20: $1M - $10M | R20: 45797 | S20: www.linkedin.com/in/kaiavega62
A21: L0020 | B21: Julian Mehta | C21: julian.mehta@microsoft.com | D21: (884) 488-6511 | E21: MICROSOFT | F21: N/A | G21: COLD_EMAIL | H21: 13 | I21: 8 | J21: 56 | K21: NO | L21: 45795 | M21: NEW | N21: Hrtech | O21: Sdr Manager | P21: BR | Q21: Unknown | R21: 45770 | S21: linkedin.com/in/xiomarajohansson3
A22: L0021 | B22: Zachary Allen | C22: zachary.allen@cloudflare.com | D22: 5384608434 | E22: CLOUDFLARE | F22: SMB | G22: SOCIAL | H22: 12 | I22: 17 | J22: 44 | K22: NO | L22: 46007 | M22: QUALIFIED | N22: Biotech | O22: Head Of Sales | P22: SG | Q22: < $1M | R22: 45680 | S22: linkedin.com/in/ursulagarcia7
A23: L0022 | B23: Yvonne Diaz | C23: yvonne.diaz@microsoftcorp.com | D23: 388.152.5136 | E23: MICROSOFT CORP | F23: N/A | G23: PAID | H23: 25 | I23: 18 | J23: 3 | K23: NO | L23: 45940 | M23: QUALIFIED | N23: Proptech | O23: Ceo | P23: Indonesia | Q23: Series B | R23: 45913 | S23: www.linkedin.com/in/landonnelson76
A24: L0023 | B24: Camila Decker | C24: camila.decker@linear.com | D24: missing | E24: LINEAR | F24: MID-MARKET | G24: DIRECT | H24: 0 | I24: 0 | J24: 38 | K24: NO | L24: 45757 | M24: DISQUALIFIED | N24: Biotech | O24: Chief Growth Officer | P24: CA | Q24: 1M-10M | R24: 45980 | S24: linkedin.com/in/zarapark15
A25: L0024 | B25: George Reyes | C25: george.reyes@amazon.com | D25: +14955493037 | E25: AMAZON | F25: GROWTH | G25: COLD_EMAIL | H25: 17 | I25: 15 | J25: 38 | K25: YES | L25: 46002 | M25: NEW | N25: Proptech | O25: Director Of Marketing | P25: DE | Q25: $5M-$25M | R25: 45949 | S25: linkedin.com/in/umbramehta35
A26: L0025 | B26: Karen Ortiz | C26: karen.ortiz@datadog.com | D26: +12935816700 | E26: DATADOG | F26: SMB | G26: COLD_EMAIL | H26: 10 | I26: 15 | J26: 60 | K26: NO | L26: 45902 | M26: QUALIFIED | N26: E-Commerce | O26: Data Analyst | P26: N/A | Q26: Series A | R26: 45927 | S26: www.linkedin.com/in/quinlanbose70
A27: L0026 | B27: Dante Martinez | C27: dante.martinez@elastic.com | D27: missing | E27: ELASTIC | F27: SMB | G27: PARTNER | H27: 31 | I27: 20 | J27: 15 | K27: NO | L27: 45675 | M27: CONTACTED | N27: E-Commerce | O27: Digital Marketing Manager | P27: FR | Q27: $50M-100M | R27: 45732 | S27: https://www.linkedin.com/in/yvonnenakamura91
... A38: L0037 | B38: Nico Kapoor | C38: nico.kapoor@zendesk.com | D38: (356) 803-8770 | E38: ZENDESK | F38: ENTERPRISE | G38: PAID | H38: 0 | I38: 0 | J38: 51 | K38: NO | L38: 45948 | M38: CONVERTED | N38: Fintech | O38: Ceo | P38: Colombia | Q38: $5M-$25M | R38: 45866 | S38: linkedin.com/in/nickmalhotra37
A39: L0038 | B39: Dmitri Malik | C39: dmitri.malik@freshworks.com | D39: 980.385.4705 | E39: FRESHWORKS | F39: STARTUP | G39: DIRECT | H39: 35 | I39: 0 | J39: 53 | K39: YES | M39: QUALIFIED | N39: Unknown | O39: Technical Lead | P39: Italy | Q39: Unknown | R39: 45952 | S39: linkedin.com/in/kiraguerrero82
A40: L0039 | B40: Xander Mendoza | C40: xander.mendoza@slack.com | D40: 286-153-3549 | E40: SLACK | F40: MID-MARKET | G40: ORGANIC | H40: 17 | I40: 13 | J40: 28 | K40: NO | L40: 45904 | M40: CONVERTED | N40: Telecom | O40: Revops Manager | P40: UK | Q40: $100M+ | R40: 45971 | S40: missing
A41: L0040 | B41: Zion Novak | C41: zion.novak@linear.com | D41: missing | E41: LINEAR | F41: GROWTH | G41: CONTENT_SYNDICATION | H41: 24 | I41: 7 | J41: 53 | K41: NO | L41: 45701 | M41: ENGAGED | N41: Fintech | O41: Marketing Operations | P41: US | Q41: $10M-50M | R41: 45944 | S41: linkedin.com/in/liorachen38
A42: L0041 | B42: Bennett Williams | C42: bennett.williams@docusign.com | D42: +1-449-546-7560 | E42: DOCUSIGN | F42: ENTERPRISE | G42: EVENT | H42: 21 | I42: 5 | J42: 0 | K42: YES | L42: 45907 | M42: DISQUALIFIED | N42: Logistics | O42: Engineering Manager | P42: AU | Q42: $100M-500M | R42: 45736 | S42: missing
A43: L0042 | B43: Perseus Wilson | C43: perseus.wilson@miro.com | D43: 858.750.6295 | E43: MIRO | F43: ENTERPRISE | G43: COLD_EMAIL | H43: 4 | I43: 20 | J43: 17 | K43: YES | M43: LOST | N43: E-Commerce | O43: Marketing Analyst | P43: Bangladesh | Q43: $1M-10M | R43: 45780 | S43: linkedin.com/in/xanderdubois77
A44: L0043 | B44: Winston Costa | C44: winston.costa@meta.com | D44: (687) 613-3471 | E44: META | F44: N/A | G44: PAID | H44: 21 | I44: 2 | J44: 11 | K44: YES | L44: 45884 | M44: LOST | N44: AI/ML | O44: Sales Engineer | P44: Saudi Arabia | Q44: $10M+ | R44: 45830 | S44: linkedin.com/in/juniperreyes43
A45: L0044 | B45: Isla Taylor | C45: isla.taylor@paloaltonetworks.com | D45: missing | E45: PALO ALTO NETWORKS | F45: MID-MARKET | G45: REFERRAL | H45: 19 | I45: 12 | J45: 45 | K45: YES | L45: 45859 | M45: ENGAGED | N45: Fintech | O45: Cto | P45: DE | Q45: unknown | R45: 45669 | S45: missing
A46: L0045 | B46: Deepa Ali | C46: deepa.ali@hubspot.com | D46: (752) 955-9626 | E46: HUBSPOT | F46: MID-MARKET | G46: COLD_EMAIL | H46: 8 | I46: 4 | J46: 53 | K46: NO | L46: 45740 | M46: QUALIFIED | N46: Fintech | O46: Events Manager | P46: Uae | Q46: 0-1M | R46: 45940 | S46: https://linkedin.com/in/marisolking69
A47: L0046 | B47: Dmitri Malhotra | C47: dmitri.malhotra@cloudflare.com | D47: +1-996-491-9239 | E47: CLOUDFLARE | F47: STARTUP | G47: REFERRAL | H47: 8 | I47: 1 | J47: 55 | K47: YES | L47: 45711 | M47: ENGAGED | N47: Cybersecurity | O47: Vp Sales | P47: DE | Q47: 1M-10M | R47: 45905 | S47: www.linkedin.com/in/xanderverma29
A48: L0047 | B48: Nolan Tiwari | C48: nolan.tiwari@notion.com | D48: 301.959.6493 | E48: NOTION | F48: MID-MARKET | G48: REFERRAL | H48: 0 | I48: 15 | J48: 8 | K48: NO | L48: 45660 | M48: NEW | N48: Proptech | O48: Director Of Demand Gen | P48: IN | Q48: self-funded | R48: 45842 | S48: linkedin.com/in/jasminenelson16
A49: L0048 | B49: Kevin Chen | C49: kevin.chen@canva.com | D49: missing | E49: CANVA | F49: MID-MARKET | G49: SOCIAL | H49: 22 | I49: 13 | J49: 42 | K49: YES | L49: 45811 | M49: LOST | N49: Energy | O49: Intern | P49: US | Q49: Unknown | S49: missing
A50: L0049 | B50: Thea Hill | C50: thea.hill@notion.com | D50: 5402361726 | E50: NOTION | F50: ENTERPRISE | G50: COLD_EMAIL | H50: 11 | I50: 14 | J50: 30 | K50: YES | L50: 45719 | M50: DISQUALIFIED | N50: Retail | O50: Growth Lead | P50: Netherlands | Q50: Series B | R50: 45668 | S50: www.linkedin.com/in/doriano'brien70
A51: L0050 | B51: Nadia Jones | C51: nadia.jones@meta.com | D51: +16098618204 | E51: META | F51: SMB | G51: REFERRAL | H51: 31 | I51: 16 | J51: 5 | K51: NO | L51: 45957 | M51: CONVERTED | N51: Biotech | O51: Operations Manager | P51: FR | Q51: Unknown | R51: 45792 | S51: www.linkedin.com/in/henriksanchez89
A52: L0051 | B52: Nolan Johansson | C52: nolan.johansson@asana.com | D52: missing | E52: ASANA | F52: ENTERPRISE | G52: EVENT | H52: 10 | I52: 4 | J52: 43 | K52: NO | M52: QUALIFIED | N52: Insurtech | O52: Sales Engineer | P52: Uae | Q52: $100M+ | S52: missing
A53: L0052 | B53: Nico Verma | C53: nico.verma@hubspot.com | D53: missing | E53: HUBSPOT | F53: MID-MARKET | G53: ORGANIC | H53: 31 | I53: 17 | J53: 49 | K53: YES | L53: 45767 | M53: NURTURING | N53: Automotive | O53: Vp Marketing | P53: FR | Q53: Unknown | R53: 45739 | S53: https://www.linkedin.com/in/wendydominguez88
A54: L0053 | B54: Soren Shah | C54: soren.shah@snowflake.com | D54: (570) 620-4673 | E54: SNOWFLAKE | F54: MID-MARKET | G54: REFERRAL | H54: 31 | I54: 0 | J54: 23 | K54: NO | L54: 45905 | M54: NEW | N54: E-Commerce | O54: Vp Of Marketing | P54: Ireland | Q54: $25M-$100M | R54: 45914 | S54: https://www.linkedin.com/in/vesperwilson17
A55: L0054 | B55: Magnus Wilson | C55: magnus.wilson@workday.com | D55: +1-256-951-3034 | E55: WORKDAY | F55: MID-MARKET | G55: COLD_EMAIL | H55: 20 | I55: 7 | J55: 60 | K55: YES | L55: 45697 | M55: NEW | N55: Biotech | O55: Cto | P55: Sweden | Q55: $10M-50M | R55: 45735 | S55: linkedin.com/in/noahsanchez85
A56: L0055 | B56: Cordelia Ali | C56: cordelia.ali@googleinc.com | D56: +1-415-885-7825 | E56: GOOGLE INC | F56: ENTERPRISE | G56: ORGANIC | H56: 34 | I56: 9 | J56: 51 | K56: NO | L56: 45872 | M56: DISQUALIFIED | N56: Healthcare | O56: Product Manager | P56: Philippines | Q56: Unknown | R56: 45935 | S56: missing
A57: L0056 | B57: Farhan Castillo | C57: farhan.castillo@linear.com | D57: 473-560-5061 | E57: LINEAR | F57: MID-MARKET | G57: ORGANIC | H57: 24 | I57: 13 | J57: 55 | K57: NO | L57: 45954 | M57: LOST | N57: Hrtech | O57: Product Manager | P57: Turkey | Q57: Unknown | R57: 45793 | S57: missing
A58: L0057 | B58: Yasmin Schneider | C58: missing | D58: (681) 392-9793 | E58: META | F58: MID-MARKET | G58: CONTENT_SYNDICATION | H58: 16 | I58: 12 | J58: 25 | K58: YES | L58: 45759 | M58: CONVERTED | N58: Biotech | O58: Chief Marketing Officer | P58: New Zealand | Q58: Series A | R58: 45952 | S58: https://www.linkedin.com/in/ginataylor51
A59: L0058 | B59: Katrina Fischer | C59: katrina.fischer@dropbox.com | D59: 685-631-8487 | E59: DROPBOX | F59: MID-MARKET | G59: UNKNOWN | H59: 20 | I59: 19 | J59: 19 | K59: YES | L59: 45918 | M59: NURTURING | N59: Unknown | O59: Head Of Strategy | P59: US | Q59: $5M-$25M | R59: 45857 | S59: missing
A60: L0059 | B60: Yuki Ivanov | C60: yuki.ivanov@palantirtechnologies.com | D60: missing | E60: PALANTIR TECHNOLOGIES | F60: ENTERPRISE | G60: EVENT | H60: 15 | I60: 0 | J60: 7 | K60: YES | M60: LOST | N60: Media | O60: Co-Founder | P60: Colombia | Q60: unknown | R60: 45946 | S60: linkedin.com/in/paulherrera18
A61: L0060 | B61: Carlos Fischer | C61: carlos.fischer@twilio.com | D61: +1-892-890-5331 | E61: TWILIO | F61: N/A | G61: WEBINAR | H61: 17 | I61: 7 | J61: 19 | K61: NO | L61: 46014 | M61: NURTURING | N61: Unknown | O61: Director Of Analytics | P61: Italy | Q61: Series B | R61: 45781 | S61: https://www.linkedin.com/in/margauxsingh51
A62: L0061 | B62: Liam Gonzalez | C62: liam.gonzalez@intercom.com | D62: 477-675-5450 | E62: INTERCOM | F62: MID-MARKET | G62: SOCIAL | H62: 33 | I62: 7 | J62: 0 | K62: NO | L62: 45873 | M62: CONTACTED | N62: Cybersecurity | O62: Marketing Manager | P62: IN | Q62: Unknown | R62: 45772 | S62: linkedin.com/in/gabriellabaker83
A63: L0062 | B63: Wendy Cruz | C63: wendy.cruz@meta.com | D63: missing | E63: META | F63: ENTERPRISE | G63: EVENT | H63: 11 | I63: 9 | J63: 0 | K63: NO | L63: 45699 | M63: NURTURING | N63: Retail | O63: Junior Analyst | P63: AU | Q63: Unknown | R63: 45699 | S63: missing
A64: L0063 | B64: Penelope Reyes | C64: penelope.reyes@snowflake.com | D64: +1-615-946-8007 | E64: SNOWFLAKE | F64: SMB | G64: PAID | H64: 6 | I64: 4 | J64: 59 | K64: NO | M64: NEW | N64: Insurtech | O64: Gtm Lead | P64: US | Q64: 10M-50M | R64: 45931 | S64: missing
A65: L0064 | B65: Qasim Gomez | C65: qasim.gomez@slack.com | D65: (518) 806-2923 | E65: SLACK | F65: SMB | G65: EVENT | H65: 14 | I65: 15 | J65: 47 | K65: NO | L65: 46009 | M65: NURTURING | N65: Legal Tech | O65: Customer Success Manager | P65: DE | Q65: $1M - $10M | R65: 45707 | S65: missing
A66: L0065 | B66: Nikolai Joshi | C66: nikolai.joshi@atlassian.com | D66: +17001939361 | E66: ATLASSIAN | F66: ENTERPRISE | G66: PARTNER | H66: 26 | I66: 1 | J66: 43 | K66: NO | L66: 45847 | M66: ENGAGED | N66: Saas | O66: Director Of Demand Gen | P66: CA | Q66: Unknown | R66: 45706 | S66: linkedin.com/in/racheltiwari61
A67: L0066 | B67: Xavier Kim | C67: xavier.kim@airtable.com | D67: (586) 484-2314 | E67: AIRTABLE | F67: MID-MARKET | G67: DIRECT | H67: 22 | I67: 0 | J67: 25 | K67: YES | L67: 45774 | M67: NEW | N67: Saas | O67: Marketing Coordinator | P67: Bangladesh | Q67: $50M - $100M | R67: 45865 | S67: missing
A68: L0067 | B68: Penelope Shah | C68: penelope.shah@linear.com | D68: (216) 346-4376 | E68: LINEAR | F68: MID-MARKET | G68: ORGANIC | H68: 3 | I68: 1 | J68: 14 | K68: NO | L68: 45662 | M68: LOST | N68: Biotech | O68: Content Marketing Lead | P68: Israel | Q68: Series A | R68: 45816 | S68: missing
A69: L0068 | B69: Kira Ramos | C69: kira.ramos@workday.com | D69: (637) 669-9120 | E69: WORKDAY | F69: STARTUP | G69: EVENT | H69: 20 | I69: 13 | J69: 24 | K69: NO | L69: 45877 | M69: ENGAGED | N69: Legal Tech | O69: Marketing Coordinator | P69: AU | Q69: $1M-10M | R69: 45856 | S69: https://linkedin.com/in/ximenalopez33
A70: L0069 | B70: Isla Reyes | C70: isla.reyes@servicenow.com | D70: 817-140-2192 | E70: SERVICE NOW | F70: SMB | G70: DIRECT | H70: 13 | I70: 10 | J70: 58 | K70: YES | L70: 45771 | M70: NURTURING | N70: Automotive | O70: Customer Success Manager | P70: JP | Q70: 0-1M | R70: 45790 | S70: https://www.linkedin.com/in/onyxmalik40
A71: L0070 | B71: Qasim Nakamura | C71: qasim.nakamura@hashicorp.com | D71: (623) 146-4625 | E71: HASHICORP | F71: MID-MARKET | G71: ORGANIC | H71: 26 | I71: 6 | J71: 24 | K71: YES | L71: 45887 | M71: NEW | N71: Logistics | O71: Account Executive | P71: Egypt | Q71: Over $1B | R71: 45875 | S71: linkedin.com/in/opheliasanchez18
A72: L0071 | B72: Margaux Moreau | C72: margaux.moreau@amazon.com | D72: +12498821104 | E72: AMAZON | F72: MID-MARKET | G72: WEBINAR | H72: 0 | I72: 6 | J72: 23 | K72: YES | L72: 45981 | M72: NURTURING | N72: Automotive | O72: Cmo | P72: US | Q72: unknown | S72: linkedin.com/in/ursulaolsen37
A73: L0072 | B73: Adeline Chandra | C73: adeline.chandra@stripe.com | D73: missing | E73: STRIPE | F73: N/A | G73: SOCIAL | H73: 17 | I73: 2 | J73: 25 | K73: NO | L73: 45999 | M73: NURTURING | N73: E-Commerce | O73: Growth Lead | P73: DE | Q73: $10M+ | R73: 45678 | S73: missing
A74: L0073 | B74: Samir Anderson | C74: samir.anderson@palantir.com | D74: 4353168790 | E74: PALANTIR | F74: ENTERPRISE | G74: PAID | H74: 17 | I74: 18 | J74: 11 | K74: YES | M74: NEW | N74: AI/ML | O74: Communications Director | P74: CA | Q74: $100M+ | R74: 45860 | S74: linkedin.com/in/islakumar97
A75: L0074 | B75: James Rojas | C75: missing | D75: 987.728.7499 | E75: MONGODB | F75: SMB | G75: ORGANIC | H75: 28 | I75: 11 | J75: 24 | K75: NO | L75: 45952 | M75: NEW | N75: E-Commerce | O75: Vp Revenue | P75: N/A | Q75: $10M-50M | R75: 45861 | S75: https://www.linkedin.com/in/noahguerrero50
A76: L0075 | B76: Qasim Moore | C76: qasim.moore@linear.com | D76: (768) 624-7685 | E76: LINEAR | F76: ENTERPRISE | G76: PAID | H76: 5 | I76: 10 | J76: 0 | K76: NO | L76: 45712 | M76: CONVERTED | N76: Proptech | O76: Senior Associate | P76: IN | Q76: $500M-1B | R76: 45786 | S76: https://www.linkedin.com/in/quinnsanchez56
A77: L0076 | B77: Finn Nelson | C77: finn.nelson@notion.com | D77: +13384111110 | E77: NOTION | F77: SMB | G77: EVENT | H77: 21 | I77: 13 | J77: 55 | K77: YES | L77: 45726 | M77: LOST | N77: Hrtech | O77: Director Of Analytics | P77: Israel | Q77: $10M+ | R77: 45801 | S77: https://linkedin.com/in/xiomaramalhotra74
A78: L0077 | B78: Hugo Singh | C78: hugo.singh@palantir.com | D78: (227) 844-8563 | E78: PALANTIR | F78: MID-MARKET | G78: PARTNER | H78: 4 | I78: 13 | J78: 8 | K78: YES | L78: 45799 | M78: LOST | N78: Telecom | O78: Channel Manager | P78: CA | Q78: Under $1M | R78: 45856 | S78: linkedin.com/in/zinniachen70
A79: L0078 | B79: Qasim Diaz | C79: qasim.diaz@amazoninc.com | D79: missing | E79: AMAZON INC | F79: MID-MARKET | G79: ORGANIC | H79: 25 | I79: 10 | J79: 27 | K79: NO | M79: QUALIFIED | N79: Legal Tech | O79: Associate | P79: BR | Q79: $10M+ | R79: 45980 | S79: www.linkedin.com/in/mayashah4
A80: L0079 | B80: Aisha Gonzalez | C80: aisha.gonzalez@airtable.com | D80: missing | E80: AIRTABLE | F80: N/A | G80: COLD_EMAIL | H80: 28 | I80: 14 | J80: 19 | K80: YES | L80: 45689 | M80: ENGAGED | N80: Logistics | O80: Revenue Operations | P80: IN | Q80: self-funded | R80: 45734 | S80: missing
A81: L0080 | B81: Raphael Park | C81: raphael.park@stripe.com | D81: +14025608037 | E81: STRIPE | F81: ENTERPRISE | G81: WEBINAR | H81: 4 | I81: 17 | J81: 20 | K81: YES | L81: 45799 | M81: ENGAGED | N81: Automotive | O81: Data Analyst | P81: New Zealand | Q81: $100M+ | R81: 45836 | S81: linkedin.com/in/tarachandra87
A82: L0081 | B82: Amara Das | C82: amara.das@salesforce.com | D82: missing | E82: SALESFORCE | F82: STARTUP | G82: CONTENT_SYNDICATION | H82: 24 | I82: 15 | J82: 44 | K82: YES | L82: 45734 | M82: CONVERTED | N82: Automotive | O82: Vp Sales | P82: AU | Q82: Series C+ | R82: 45685 | S82: missing
A83: L0082 | B83: Charlie Moreau | C83: charlie.moreau@dropbox.com | D83: (654) 600-3740 | E83: DROPBOX | F83: SMB | G83: ORGANIC | H83: 14 | I83: 8 | J83: 18 | K83: NO | L83: 45954 | M83: DISQUALIFIED | N83: Energy | O83: Associate | P83: FR | Q83: 1M-10M | R83: 45826 | S83: www.linkedin.com/in/karenortiz93
A84: L0083 | B84: Margaux Young | C84: margaux.young@miro.com | D84: 289.549.2923 | E84: MIRO | F84: SMB | G84: WEBINAR | H84: 22 | I84: 19 | J84: 10 | K84: NO | L84: 45774 | M84: NEW | N84: Healthcare | O84: Engineering Manager | P84: US | Q84: $500M-1B | R84: 46001 | S84: missing
A85: L0084 | B85: Sophie Verma | C85: sophie.verma@microsoft.com | D85: missing | E85: MICROSOFT | F85: SMB | G85: REFERRAL | H85: 8 | I85: 10 | J85: 48 | K85: NO | L85: 45735 | M85: NEW | N85: Cleantech | O85: Field Marketing Manager | P85: South Africa | Q85: Over $1B | R85: 45701 | S85: www.linkedin.com/in/vikramgomez48
A86: L0085 | B86: Wesley Khan | C86: wesley.khan@microsoft.com | D86: +12649149756 | E86: MICROSOFT | F86: MID-MARKET | G86: CONTENT_SYNDICATION | H86: 31 | I86: 9 | J86: 36 | K86: NO | L86: 45895 | M86: LOST | N86: Healthcare | O86: Demand Gen Manager | P86: DE | Q86: Series C+ | R86: 45716 | S86: missing
A87: L0086 | B87: Orion Johnson | C87: orion.johnson@salesforcecom.com | D87: 2957706905 | E87: SALESFORCE.COM | F87: ENTERPRISE | G87: EVENT | H87: 10 | I87: 0 | J87: 46 | K87: NO | L87: 45711 | M87: NURTURING | N87: Saas | O87: Director Of Demand Gen | P87: Kenya | Q87: Unknown | R87: 45922 | S87: linkedin.com/in/charliediaz44
A88: L0087 | B88: Genevieve Gomez | C88: genevieve.gomez@airtable.com | D88: (591) 892-3181 | E88: AIRTABLE | F88: MID-MARKET | G88: REFERRAL | H88: 0 | I88: 19 | J88: 28 | K88: YES | L88: 45985 | M88: LOST | N88: Media | O88: Sales Operations | P88: JP | Q88: Unknown | R88: 45707 | S88: https://www.linkedin.com/in/nolanmalhotra55
A89: L0088 | B89: James Lopez | C89: james.lopez@databricks.com | D89: missing | E89: DATABRICKS | F89: MID-MARKET | G89: COLD_EMAIL | H89: 32 | I89: 12 | J89: 3 | K89: NO | L89: 45696 | M89: NURTURING | N89: E-Commerce | O89: Vp Marketing | P89: Uae | Q89: $100M-500M | R89: 45944 | S89: missing
A90: L0089 | B90: Winona Clark | C90: winona.clark@google.com | D90: (607) 618-5693 | E90: GOOGLE | F90: GROWTH | G90: UNKNOWN | H90: 27 | I90: 2 | J90: 34 | K90: NO | L90: 45698 | M90: QUALIFIED | N90: Energy | O90: Marketing Manager | P90: IN | Q90: $10M+ | R90: 45983 | S90: linkedin.com/in/dmitridiaz56
A91: L0090 | B91: Kevin Davis | C91: kevin.davis@databricks.com | D91: (322) 112-3248 | E91: DATABRICKS | F91: ENTERPRISE | G91: REFERRAL | H91: 22 | I91: 8 | J91: 8 | K91: YES | L91: 45713 | M91: NEW | N91: Fintech | O91: Abm Manager | P91: US | Q91: 1M-10M | R91: 45951 | S91: missing
... A96: L0095 | B96: Liam Thomas | C96: liam.thomas@meta.com | D96: missing | E96: META | F96: STARTUP | G96: PARTNER | H96: 35 | I96: 14 | J96: 50 | K96: NO | L96: 45684 | M96: DISQUALIFIED | N96: Legal Tech | O96: Cto | P96: JP | Q96: < $1M | R96: 45964 | S96: linkedin.com/in/piperdas10
A97: L0096 | B97: Quinn Robinson | C97: quinn.robinson@atlassian.com | D97: +16439417471 | E97: ATLASSIAN | F97: ENTERPRISE | G97: EVENT | H97: 11 | I97: 5 | J97: 28 | K97: NO | M97: NEW | N97: Proptech | O97: Vp Revenue | P97: Turkey | Q97: $50M - $100M | R97: 45697 | S97: missing
A98: L0097 | B98: Finn Robinson | C98: finn.robinson@workday.com | D98: 7579008940 | E98: WORKDAY | F98: SMB | G98: UNKNOWN | H98: 17 | I98: 10 | J98: 1 | K98: YES | M98: NURTURING | N98: Logistics | O98: Content Marketing Lead | P98: IN | Q98: Unknown | R98: 45795 | S98: linkedin.com/in/oliviaortiz29
A99: L0098 | B99: Ximena Malik | C99: ximena.malik@notion.com | D99: +1-228-820-6761 | E99: NOTION | F99: SMB | G99: REFERRAL | H99: 12 | I99: 15 | J99: 11 | K99: NO | M99: CONTACTED | N99: Insurtech | O99: Digital Marketing Manager | P99: US | Q99: $0-1M | R99: 45937 | S99: https://www.linkedin.com/in/lorenzomedina23
A100: L0099 | B100: Paul Williams | C100: paul.williams@salesforce.com | D100: 8785052655 | E100: SALESFORCE | F100: SMB | G100: COLD_EMAIL | H100: 10 | I100: 13 | J100: 31 | K100: YES | L100: 46009 | M100: DISQUALIFIED | N100: Logistics | O100: Digital Marketing Manager | P100: SG | Q100: self-funded | R100: 45722 | S100: linkedin.com/in/urielo'brien99
A101: L0100 | B101: Ivy Ramirez | C101: ivy.ramirez@zoom.com | D101: 2793436682 | E101: ZOOM | F101: MID-MARKET | G101: PAID | H101: 21 | I101: 8 | J101: 44 | K101: YES | L101: 45712 | M101: NEW | N101: Healthcare | O101: Brand Manager | P101: Philippines | Q101: $500M-1B | R101: 45882 | S101: missing
A102: L0101 | B102: Umar Taylor | C102: umar.taylor@linear.com | D102: 5011206221 | E102: LINEAR | F102: MID-MARKET | G102: PAID | H102: 24 | I102: 2 | J102: 57 | K102: YES | L102: 45946 | M102: DISQUALIFIED | N102: Fintech | O102: Marketing Operations | P102: IN | Q102: unknown | R102: 45699 | S102: missing
A103: L0102 | B103: Xena Kim | C103: xena.kim@figma.com | D103: 762-960-9043 | E103: FIGMA | F103: ENTERPRISE | G103: EVENT | H103: 0 | I103: 0 | J103: 40 | K103: NO | L103: 45689 | M103: NEW | N103: Martech | O103: Vp Revenue | P103: DE | Q103: $50M-100M | R103: 45854 | S103: linkedin.com/in/reveriescott12
A104: L0103 | B104: Margaux Kumar | C104: missing | D104: 777.163.3476 | E104: INTERCOM | F104: GROWTH | G104: PAID | H104: 0 | I104: 17 | J104: 48 | K104: YES | L104: 45684 | M104: NEW | N104: Media | O104: Head Of Strategy | P104: BR | Q104: $10M-50M | R104: 45993 | S104: linkedin.com/in/esmeraldaaguilar74
A105: L0104 | B105: Gideon Thompson | C105: gideon.thompson@slack.com | D105: 899.545.4308 | E105: SLACK | F105: ENTERPRISE | G105: REFERRAL | H105: 16 | I105: 2 | J105: 35 | K105: NO | L105: 45794 | M105: QUALIFIED | N105: Saas | O105: Senior Associate | P105: Indonesia | Q105: Unknown | R105: 45949 | S105: linkedin.com/in/zanesaxena14
A106: L0105 | B106: Zane Soto | C106: zane.soto@zendesk.com | D106: 376-382-7602 | E106: ZENDESK | F106: MID-MARKET | G106: EVENT | H106: 0 | I106: 10 | J106: 3 | K106: NO | L106: 45809 | M106: LOST | N106: Unknown | O106: Marketing Analyst | P106: US | Q106: $25M-$100M | R106: 45752 | S106: missing
A107: L0106 | B107: Landon Vega | C107: landon.vega@splunk.com | D107: 696.877.9462 | E107: SPLUNK | F107: STARTUP | G107: ORGANIC | H107: 10 | I107: 0 | J107: 25 | K107: NO | L107: 45919 | M107: NEW | N107: Martech | O107: Unknown | P107: JP | Q107: 0-1M | S107: missing
A108: L0107 | B108: Qasim Herrera | C108: qasim.herrera@okta.com | D108: 808.556.3909 | E108: OKTA | F108: N/A | G108: DIRECT | H108: 10 | I108: 8 | J108: 44 | K108: YES | L108: 45840 | M108: CONVERTED | N108: Legal Tech | O108: Digital Marketing Manager | P108: BR | Q108: 1M-10M | R108: 45901 | S108: https://linkedin.com/in/winonasmith61
A109: L0108 | B109: Nyx Clark | C109: nyx.clark@snowflakeinc.com | D109: 557-570-5128 | E109: SNOWFLAKE INC | F109: N/A | G109: COLD_EMAIL | H109: 25 | I109: 0 | J109: 42 | K109: YES | L109: 45950 | M109: NURTURING | N109: Unknown | O109: Revenue Operations | P109: Kenya | Q109: Unknown | R109: 45972 | S109: linkedin.com/in/pipercruz92
A110: L0109 | B110: Amara Lewis | C110: amara.lewis@databricks.com | D110: missing | E110: DATABRICKS | F110: N/A | G110: SOCIAL | H110: 26 | I110: 1 | J110: 36 | K110: YES | L110: 45999 | M110: CONTACTED | N110: Retail | O110: Solutions Architect | P110: Sweden | Q110: Series C+ | R110: 45906 | S110: missing
A111: L0110 | B111: Sebastian Lee | C111: sebastian.lee@stripe.com | D111: missing | E111: STRIPE | F111: SMB | G111: COLD_EMAIL | H111: 21 | I111: 18 | J111: 54 | K111: NO | L111: 45980 | M111: NEW | N111: E-Commerce | O111: Head Of Strategy | P111: SG | Q111: $5M-$25M | R111: 45791 | S111: missing
A112: L0111 | B112: Maya Perez | C112: maya.perez@docusign.com | D112: missing | E112: DOCUSIGN | F112: SMB | G112: REFERRAL | H112: 3 | I112: 0 | J112: 48 | K112: NO | L112: 45732 | M112: ENGAGED | N112: E-Commerce | O112: Cto | P112: Vietnam | Q112: $10M+ | R112: 45882 | S112: missing
A113: L0112 | B113: Joaquin Robinson | C113: joaquin.robinson@miro.com | D113: 4543316641 | E113: MIRO | F113: MID-MARKET | G113: PAID | H113: 19 | I113: 1 | J113: 18 | K113: NO | L113: 45947 | M113: LOST | N113: Telecom | O113: Coo | P113: Spain | Q113: Unknown | R113: 45753 | S113: https://linkedin.com/in/bennettwilliams30
A114: L0113 | B114: Hassan Young | C114: hassan.young@cloudflare.com | D114: +1-989-647-1796 | E114: CLOUDFLARE | F114: ENTERPRISE | G114: PAID | H114: 1 | I114: 0 | J114: 28 | K114: NO | L114: 45793 | M114: DISQUALIFIED | N114: AI/ML | O114: Marketing Manager | P114: US | Q114: $5M-$25M | R114: 45909 | S114: linkedin.com/in/jameschen14
...

Sheet clean_spend
A1: campaign_id | B1: campaign_name | C1: campaign_desc | D1: source | E1: channel | F1: monthly_spend | G1: month | H1: impressions | I1: clicks_generated | J1: leads_generated | K1: conversions | L1: revenue_attributed | M1: cost_per_lead | N1: cost_per_click | O1: click_through_rate | P1: conversion_rate | Q1: ROAS
A2: {=raw_spend!A2:A136} -> C007 | B2: {=IF(raw_spend!A2:A136="C001","Google Ads - Search",IF(raw_spend!A2:A136="C002","Google Ads - Display",IF(raw_spend!A2:A136="C003","Meta - Brand Awareness",IF(raw_spend!A2:A136="C004","LinkedIn - ABM Campaign",IF(raw_spend!A2:A136="C005","Webinar Series",IF(raw_spend!A2:A136="C006","Referral Program",IF(raw_spend!A2:A136="C007","SEO Content Program",IF(raw_spend!A2:A136="C008","Cold Email Outbound",IF(raw_spend!A2:A136="C009","Trade Show Circuit",IF(raw_spend!A2:A136="C010","Content Syndication","UNKNOWN"))))))))))} -> SEO Content Program | C2: {=IF(TRIM(raw_spend!C2:C136)="","Unknown",PROPER(TRIM(raw_spend!C2:C136)))} -> Seo Content Program | D2: {=IF(TRIM(raw_spend!D2:D136)="","UNKNOWN",IF((UPPER(TRIM(raw_spend!D2:D136))="COLD EMAIL")+(UPPER(TRIM(raw_spend!D2:D136))="COLD_EMAIL"),"COLD_EMAIL",IF((UPPER(TRIM(raw_spend!D2:D136))="CONTENT SYNDICATION")+(UPPER(TRIM(raw_spend!D2:D136))="CONTENT_SYNDICATION"),"CONTENT_SYNDICATION",UPPER(TRIM(raw_spend!D2:D136)))))} -> ORGANIC | E2: {=IF(TRIM(raw_spend!E2:E136)="","UNKNOWN",IF((UPPER(TRIM(raw_spend!E2:E136))="FB/IG")+(UPPER(TRIM(raw_spend!E2:E136))="META")+(UPPER(TRIM(raw_spend!E2:E136))="FACEBOOK/INSTAGRAM"),"Facebook/Instagram",IF((UPPER(TRIM(raw_spend!E2:E136))="BLOG/SEO")+(UPPER(TRIM(raw_spend!E2:E136))="BLOG"),"Blog/SEO",IF((UPPER(TRIM(raw_spend!E2:E136))="3RD PARTY")+(UPPER(TRIM(raw_spend!E2:E136))="THIRD PARTY"),"3rd Party",IF(UPPER(TRIM(raw_spend!E2:E136))="OWNED MEDIA","Owned Media",PROPER(TRIM(raw_spend!E2:E136)))))))} -> Blog/SEO | F2: {=raw_spend!F2:F136} -> 4423 | G2: {=raw_spend!G2:G136} -> 2025-12 | H2: {=raw_spend!H2:H136} -> 108294 | I2: {=raw_spend!I2:I136} -> 5972 | J2: {=raw_spend!J2:J136} -> 99 | K2: {=raw_spend!K2:K136} -> 21 | L2: {=raw_spend!L2:L136} -> 77911 | M2: {=IFERROR(raw_spend!F2:F136/raw_spend!J2:J136,0)} -> 44.676768 | N2: {=IFERROR(raw_spend!F2:F136/raw_spend!I2:I136,0)} -> 0.74062291 | O2: {=IFERROR(raw_spend!I2:I136/raw_spend!H2:H136,0)} -> 0.055146176 | P2: {=IFERROR(raw_spend!K2:K136/raw_spend!J2:J136,0)} -> 0.21212121 | Q2: {=IFERROR(raw_spend!L2:L136/raw_spend!F2:F136,0)} -> 17.614967
A3: C001 | B3: Google Ads - Search | C3: Google Ads — Search | D3: PAID | E3: Search | F3: 6401 | G3: 2025-01 | H3: 61308 | I3: 2283 | J3: 48 | K3: 5 | L3: 12313 | M3: 133.35417 | N3: 2.803767 | O3: 0.037238207 | P3: 0.10416667 | Q3: 1.9236057
A4: C001 | B4: Google Ads - Search | C4: Google Ads — Search | D4: PAID | E4: Search | F4: 6171 | G4: 2025-02 | H4: 54265 | I4: 1683 | J4: 34 | K4: 7 | L4: 33082 | M4: 181.5 | N4: 3.6666667 | O4: 0.031014466 | P4: 0.20588235 | Q4: 5.3608815
A5: C001 | B5: Google Ads - Search | C5: Google Ads — Search | D5: PAID | E5: Search | F5: 6022 | G5: 2025-03 | H5: 45356 | I5: 1769 | J5: 36 | K5: 10 | L5: 24392 | M5: 167.27778 | N5: 3.4041832 | O5: 0.039002558 | P5: 0.27777778 | Q5: 4.0504816
A6: C001 | B6: Google Ads - Search | C6: Google Ads — Search | D6: PAID | E6: Search | F6: 6863 | G6: 2025-04 | H6: 62990 | I6: 2113 | J6: 48 | K6: 6 | L6: 9330 | M6: 142.97917 | N6: 3.2479886 | O6: 0.033545007 | P6: 0.125 | Q6: 1.3594638
A7: C001 | B7: Google Ads - Search | C7: Google Ads — Search | D7: PAID | E7: Search | F7: 6982 | G7: 2025-05 | H7: 49599 | I7: 2197 | J7: 60 | K7: 7 | L7: 11457 | M7: 116.36667 | N7: 3.17797 | O7: 0.044295248 | P7: 0.11666667 | Q7: 1.6409338
A8: C001 | B8: Google Ads - Search | C8: Google Ads — Search | D8: PAID | E8: Search | F8: 6013 | G8: 2025-06 | H8: 56402 | I8: 1617 | J8: 48 | K8: 10 | L8: 17657 | M8: 125.27083 | N8: 3.7186147 | O8: 0.028669196 | P8: 0.20833333 | Q8: 2.936471
A9: C006 | B9: Referral Program | C9: Referral Program | D9: REFERRAL | E9: Partner | F9: 2199 | G9: 2025-03 | H9: 5080 | I9: 1128 | J9: 56 | K9: 12 | L9: 19507 | M9: 39.267857 | N9: 1.9494681 | O9: 0.22204724 | P9: 0.21428571 | Q9: 8.8708504
A10: C001 | B10: Google Ads - Search | C10: Google Ads — Search | D10: PAID | E10: Search | F10: 6560 | G10: 2025-07 | H10: 48495 | I10: 2278 | J10: 61 | K10: 12 | L10: 38764 | M10: 107.54098 | N10: 2.8797191 | O10: 0.046973915 | P10: 0.19672131 | Q10: 5.9091463
A11: C001 | B11: Google Ads - Search | C11: Google Ads — Search | D11: PAID | E11: Search | F11: 6885 | G11: 2025-08 | H11: 62783 | I11: 2670 | J11: 56 | K11: 6 | L11: 26525 | M11: 122.94643 | N11: 2.5786517 | O11: 0.042527436 | P11: 0.10714286 | Q11: 3.8525781
A12: C001 | B12: Google Ads - Search | C12: Google Ads — Search | D12: PAID | E12: Search | F12: 7831 | G12: 2025-09 | H12: 72266 | I12: 2799 | J12: 63 | K12: 14 | L12: 39525 | M12: 124.30159 | N12: 2.7977849 | O12: 0.038731907 | P12: 0.22222222 | Q12: 5.0472481
A13: C001 | B13: Google Ads - Search | C13: Google Ads — Search | D13: PAID | E13: Search | F13: 9046 | G13: 2025-10 | H13: 66262 | I13: 2551 | J13: 85 | K13: 9 | L13: 10705 | M13: 106.42353 | N13: 3.5460604 | O13: 0.038498687 | P13: 0.10588235 | Q13: 1.183396
A14: C001 | B14: Google Ads - Search | C14: Google Ads — Search | D14: PAID | E14: Search | F14: 8538 | G14: 2025-11 | H14: 60811 | I14: 2325 | J14: 71 | K14: 10 | L14: 44184 | M14: 120.25352 | N14: 3.6722581 | O14: 0.038233214 | P14: 0.14084507 | Q14: 5.1749824
... A136: C010 | B136: Content Syndication | C136: Content Syndication | D136: CONTENT_SYNDICATION | E136: 3rd Party | F136: 5929 | G136: 2025-12 | H136: 40080 | I136: 1247 | J136: 27 | K136: 2 | L136: 4823 | M136: 219.59259 | N136: 4.7546111 | O136: 0.031112774 | P136: 0.074074074 | Q136: 0.81345927

Sheet clean_interactions
A1: interaction_id | B1: lead_id | C1: interaction_type | D1: interaction_date | E1: channel | F1: campaign_id | G1: content_asset | H1: response | I1: time_spent_seconds | J1: device | K1: page_url | L1: notes | M1: time_spent_minutes | N1: engagement_level
A2: {=raw_interactions!A2:A3001} -> INT-00001 | B2: {=raw_interactions!B2:B3001} -> L0268 | C2: {=IF(TRIM(raw_interactions!C2:C3001)="","UNKNOWN",UPPER(SUBSTITUTE(TRIM(raw_interactions!C2:C3001)," ","_")))} -> CASE_STUDY_VIEW | D2: {=IF(raw_interactions!D2:D3001="","",raw_interactions!D2:D3001)} -> 45939 | E2: {=IF(TRIM(raw_interactions!E2:E3001)="","UNKNOWN",IF((UPPER(TRIM(raw_interactions!E2:E3001))="IN-PERSON")+(UPPER(TRIM(raw_interactions!E2:E3001))="IN PERSON"),"IN-PERSON",IF(UPPER(TRIM(raw_interactions!E2:E3001))="PUSH_NOTIFICATION","PUSH_NOTIFICATION",UPPER(TRIM(raw_interactions!E2:E3001)))))} -> SOCIAL | F2: {=IF(TRIM(raw_interactions!F2:F3001)="","N/A",UPPER(TRIM(raw_interactions!F2:F3001)))} -> C007 | G2: {=IF(TRIM(raw_interactions!G2:G3001)="","Unknown",PROPER(TRIM(raw_interactions!G2:G3001)))} -> Newsletter Issue #42 | H2: {=IF(TRIM(raw_interactions!H2:H3001)="","NO_RESPONSE",IF(UPPER(TRIM(raw_interactions!H2:H3001))="PARTIAL_VIEW","PARTIAL_VIEW",UPPER(SUBSTITUTE(TRIM(raw_interactions!H2:H3001)," ","_"))))} -> DOWNLOADED | I2: {=IF((raw_interactions!I2:I3001="")+(NOT(ISNUMBER(raw_interactions!I2:I3001))),0,raw_interactions!I2:I3001)} -> 1508 | J2: {=IF(TRIM(raw_interactions!J2:J3001)="","UNKNOWN",IF((UPPER(TRIM(raw_interactions!J2:J3001))="IOS")+(UPPER(TRIM(raw_interactions!J2:J3001))="ANDROID"),"MOBILE",IF((UPPER(TRIM(raw_interactions!J2:J3001))="WINDOWS")+(UPPER(TRIM(raw_interactions!J2:J3001))="MAC"),"DESKTOP",UPPER(TRIM(raw_interactions!J2:J3001)))))} -> MOBILE | K2: {=IF(TRIM(raw_interactions!K2:K3001)="","N/A",LOWER(TRIM(raw_interactions!K2:K3001)))} -> https://example.com/case-studies | L2: {=IF(TRIM(raw_interactions!L2:L3001)="","",PROPER(TRIM(raw_interactions!L2:L3001)))} | M2: {=IFERROR(IF((raw_interactions!I2:I3001="")+(NOT(ISNUMBER(raw_interactions!I2:I3001))),0,ROUND(raw_interactions!I2:I3001/60,1)),0)} -> 25.1 | N2: {=IF((raw_interactions!I2:I3001="")+(NOT(ISNUMBER(raw_interactions!I2:I3001))),"NONE",IF(raw_interactions!I2:I3001>=300,"HIGH",IF(raw_interactions!I2:I3001>=60,"MEDIUM","LOW")))} -> HIGH
A3: INT-00002 | B3: L0445 | C3: FORM_SUBMIT | D3: 45803 | E3: SOCIAL | F3: C003 | G3: 10 Lead Scoring Tips | H3: CLICKED | I3: 362 | J3: DESKTOP | K3: N/A | M3: 6 | N3: HIGH
A4: INT-00003 | B4: L0257 | C4: CHATBOT_CONVO | D4: 45813 | E4: EMAIL | F4: C004 | G4: Event Registration: Summit 2025 | H4: BOUNCED | I4: 382 | J4: DESKTOP | K4: N/A | M4: 6.4 | N4: HIGH
A5: INT-00004 | B5: L0967 | C5: FREE_TRIAL_SIGNUP | E5: PHONE | F5: C007 | G5: Case Study: Smb Growth Story | H5: BOUNCED | I5: 0 | J5: TABLET | K5: https://example.com/integrations | M5: 0 | N5: NONE
A6: INT-00005 | B6: L0561 | C6: CONTENT_DOWNLOAD | E6: EMAIL | F6: N/A | G6: Newsletter Issue #44 | H6: REGISTERED | I6: 764 | J6: DESKTOP | K6: N/A | M6: 12.7 | N6: HIGH
A7: INT-00006 | B7: L0488 | C7: UNSUBSCRIBE | D7: 45998 | E7: WEB | F7: C008 | G7: Crm Buyer'S Guide 2025 | H7: NO_RESPONSE | I7: 1146 | J7: MOBILE | K7: https://example.com/free-trial | M7: 19.1 | N7: HIGH
A8: INT-00007 | B8: L0099 | C8: EMAIL_OPEN | D8: 46017 | E8: IN-PERSON | F8: C010 | G8: Product Demo Video | H8: NO_RESPONSE | I8: 180 | J8: DESKTOP | K8: https://example.com/blog | M8: 3 | N8: MEDIUM
A9: INT-00008 | B9: L0618 | C9: EMAIL_CLICK | D9: 45823 | E9: SMS | F9: N/A | G9: Retargeting Ad Creative A | H9: OPENED | I9: 1667 | J9: UNKNOWN | K9: https://example.com/demo | M9: 27.8 | N9: HIGH
A10: INT-00009 | B10: L0342 | C10: REFERRAL_LINK_CLICK | D10: 45680 | E10: WEB | F10: C006 | G10: Template: Campaign Planning | H10: CONVERTED | I10: 1190 | J10: TABLET | K10: https://example.com/integrations | M10: 19.8 | N10: HIGH
A11: INT-00010 | B11: L0516 | C11: AD_CLICK | D11: 45805 | E11: EMAIL | F11: N/A | G11: Guide: Email Deliverability | H11: CONVERTED | I11: 1503 | J11: MOBILE | K11: https://example.com/contact | L11: High Intent | M11: 25.1 | N11: HIGH
A12: INT-00011 | B12: L0012 | C12: CASE_STUDY_VIEW | D12: 45720 | E12: CHAT | F12: C009 | G12: Crm Buyer'S Guide 2025 | H12: BOUNCED | I12: 826 | J12: MOBILE | K12: https://example.com/case-studies | M12: 13.8 | N12: HIGH
A13: INT-00012 | B13: L0458 | C13: DEMO_REQUEST | D13: 45718 | E13: PHONE | F13: C004 | G13: Case Study: Enterprise Win | H13: CLICKED | I13: 0 | J13: UNKNOWN | K13: https://example.com/contact | M13: 0 | N13: NONE
A14: INT-00013 | B14: L0184 | C14: SOCIAL_ENGAGE | D14: 45821 | E14: EMAIL | F14: C003 | G14: Newsletter Issue #42 | H14: REGISTERED | I14: 1698 | J14: UNKNOWN | K14: https://example.com/integrations | M14: 28.3 | N14: HIGH
A15: INT-00014 | B15: L0429 | C15: BLOG_READ | D15: 45880 | E15: PHONE | F15: C006 | G15: Ebook: Abm Playbook | H15: CLICKED | I15: 571 | J15: DESKTOP | K15: https://example.com/contact | M15: 9.5 | N15: HIGH
A16: INT-00015 | B16: L0914 | C16: CHATBOT_CONVO | D16: 45731 | E16: UNKNOWN | F16: C006 | G16: Whitepaper: State Of Gtm 2025 | H16: OPENED | I16: 0 | J16: UNKNOWN | K16: https://example.com/competitors | M16: 0 | N16: NONE
A17: INT-00016 | B17: L0043 | C17: SOCIAL_ENGAGE | D17: 45823 | E17: EMAIL | F17: N/A | G17: Product Demo Video | H17: DOWNLOADED | I17: 0 | J17: MOBILE | K17: https://example.com/blog/reduce-cac | M17: 0 | N17: NONE
A18: INT-00017 | B18: L0465 | C18: REFERRAL_LINK_CLICK | D18: 45773 | E18: WEB | F18: C004 | G18: Case Study: Smb Growth Story | H18: OPENED | I18: 2355 | J18: TABLET | K18: https://example.com/contact | L18: Proposal Under Review | M18: 39.3 | N18: HIGH
A19: INT-00018 | B19: L0280 | C19: PHONE_CALL | D19: 45953 | E19: PHONE | F19: C002 | G19: Video: Customer Testimonial | H19: IGNORED | I19: 232 | J19: MOBILE | K19: https://example.com/pricing | M19: 3.9 | N19: MEDIUM
A20: INT-00019 | B20: L0149 | C20: REFERRAL_LINK_CLICK | D20: 45908 | E20: EMAIL | F20: C003 | G20: Social Post: Product Launch | H20: DOWNLOADED | I20: 1088 | J20: MOBILE | K20: N/A | M20: 18.1 | N20: HIGH
A21: INT-00020 | B21: L0644 | C21: FREE_TRIAL_SIGNUP | D21: 45707 | E21: EMAIL | F21: C003 | G21: 10 Lead Scoring Tips | H21: NO_RESPONSE | I21: 0 | J21: DESKTOP | K21: https://example.com/blog/reduce-cac | M21: 0 | N21: NONE
A22: INT-00021 | B22: L0313 | C22: PHONE_CALL | D22: 45812 | E22: EMAIL | F22: C010 | G22: Newsletter Issue #42 | H22: REGISTERED | I22: 1498 | J22: TABLET | K22: https://example.com/contact | M22: 25 | N22: HIGH
A23: INT-00022 | B23: L0208 | C23: BLOG_READ | D23: 45824 | E23: PUSH_NOTIFICATION | F23: N/A | G23: Case Study: Smb Growth Story | H23: NO_RESPONSE | I23: 1909 | J23: DESKTOP | K23: https://example.com/pricing | M23: 31.8 | N23: HIGH
A24: INT-00023 | B24: L0554 | C24: UNSUBSCRIBE | D24: 45863 | E24: SOCIAL | F24: C004 | G24: Blog: Abm Vs Demand Gen | H24: BOUNCED | I24: 0 | J24: DESKTOP | K24: https://example.com/resources/ebooks | L24: Switching From Salesforce | M24: 0 | N24: NONE
A25: INT-00024 | B25: L0011 | C25: REFERRAL_LINK_CLICK | D25: 45792 | E25: EMAIL | F25: C002 | G25: Competitor Comparison Sheet | H25: IGNORED | I25: 697 | J25: MOBILE | K25: https://example.com/contact | M25: 11.6 | N25: HIGH
A26: INT-00025 | B26: L0943 | C26: UNSUBSCRIBE | D26: 45954 | E26: IN-PERSON | F26: C002 | G26: Blog: Abm Vs Demand Gen | H26: BOUNCED | I26: 2211 | J26: UNKNOWN | K26: https://example.com/roi-calculator | M26: 36.9 | N26: HIGH
A27: INT-00026 | B27: L0465 | C27: FORM_SUBMIT | D27: 45810 | E27: PHONE | F27: C010 | G27: Webinar: Marketing Automation 101 | H27: CONVERTED | I27: 972 | J27: DESKTOP | K27: https://example.com/contact | L27: Gatekeeper — Need Executive Sponsor | M27: 16.2 | N27: HIGH
A28: INT-00027 | B28: L0071 | C28: EMAIL_OPEN | D28: 46003 | E28: SMS | F28: C002 | G28: Blog: 5 Metrics Every Cmo Needs | H28: CLICKED | I28: 777 | J28: TABLET | K28: https://example.com/blog/reduce-cac | M28: 13 | N28: HIGH
A29: INT-00028 | B29: L0217 | C29: UNSUBSCRIBE | D29: 45977 | E29: EMAIL | F29: C009 | G29: Newsletter Issue #44 | H29: NO_RESPONSE | I29: 1582 | J29: UNKNOWN | K29: https://example.com/features | M29: 26.4 | N29: HIGH
A30: INT-00029 | B30: L0891 | C30: FORM_SUBMIT | D30: 46002 | E30: SMS | F30: C004 | G30: Case Study: Smb Growth Story | H30: BOUNCED | I30: 0 | J30: MOBILE | K30: https://example.com/roi-calculator | M30: 0 | N30: NONE
A31: INT-00030 | B31: L0007 | C31: PRICING_PAGE_VIEW | D31: 45744 | E31: EMAIL | F31: C008 | G31: Unknown | H31: PARTIAL_VIEW | I31: 1745 | J31: MOBILE | K31: https://example.com/webinars | M31: 29.1 | N31: HIGH
A32: INT-00031 | B32: L0595 | C32: FREE_TRIAL_SIGNUP | D32: 45839 | E32: UNKNOWN | F32: C003 | G32: Blog: 5 Metrics Every Cmo Needs | H32: OPENED | I32: 268 | J32: MOBILE | K32: N/A | M32: 4.5 | N32: MEDIUM
A33: INT-00032 | B33: L0882 | C33: REFERRAL_LINK_CLICK | E33: WEB | F33: C001 | G33: Newsletter Issue #42 | H33: CLICKED | I33: 281 | J33: DESKTOP | K33: https://example.com/about | M33: 4.7 | N33: MEDIUM
A34: INT-00033 | B34: L0004 | C34: AD_CLICK | D34: 45976 | E34: EMAIL | F34: C001 | G34: Customer Success Story | H34: VIEWED | I34: 1666 | J34: DESKTOP | K34: https://example.com/webinars | M34: 27.8 | N34: HIGH
A35: INT-00034 | B35: L0353 | C35: REFERRAL_LINK_CLICK | D35: 45984 | E35: IN-PERSON | F35: C008 | G35: Webinar: Lead Scoring Best Practices | H35: CLICKED | I35: 2033 | J35: DESKTOP | K35: https://example.com/blog/reduce-cac | M35: 33.9 | N35: HIGH
A36: INT-00035 | B36: L0603 | C36: CHATBOT_CONVO | D36: 45855 | E36: WEB | F36: C002 | G36: Webinar: Marketing Automation 101 | H36: OPENED | I36: 1646 | J36: UNKNOWN | K36: https://example.com/competitors | L36: Needs Sso/Saml | M36: 27.4 | N36: HIGH
A37: INT-00036 | B37: L0461 | C37: WEBINAR_ATTENDED | D37: 45942 | E37: CHAT | F37: N/A | G37: Ultimate Guide To Crm | H37: CONVERTED | I37: 0 | J37: DESKTOP | K37: https://example.com/webinars | M37: 0 | N37: NONE
A38: INT-00037 | B38: L0363 | C38: REFERRAL_LINK_CLICK | D38: 45695 | E38: PHONE | F38: C007 | G38: Newsletter Issue #43 | H38: PARTIAL_VIEW | I38: 2333 | J38: DESKTOP | K38: N/A | M38: 38.9 | N38: HIGH
A39: INT-00038 | B39: L0749 | C39: PHONE_CALL | D39: 45936 | E39: PHONE | F39: C001 | G39: Roi Calculator Landing Page | H39: CONVERTED | I39: 1741 | J39: MOBILE | K39: https://example.com/about | M39: 29 | N39: HIGH
A40: INT-00039 | B40: L0740 | C40: PHONE_CALL | D40: 45876 | E40: PHONE | F40: C009 | G40: Whitepaper: State Of Gtm 2025 | H40: DOWNLOADED | I40: 0 | J40: MOBILE | K40: N/A | M40: 0 | N40: NONE
A41: INT-00040 | B41: L0269 | C41: PHONE_CALL | D41: 45793 | E41: CHAT | F41: C010 | G41: Newsletter Issue #43 | H41: UNSUBSCRIBED | I41: 1367 | J41: DESKTOP | K41: N/A | M41: 22.8 | N41: HIGH
A42: INT-00041 | B42: L0550 | C42: DEMO_REQUEST | D42: 45949 | E42: SMS | F42: C008 | G42: Whitepaper: State Of Gtm 2025 | H42: DOWNLOADED | I42: 150 | J42: DESKTOP | K42: https://example.com/demo | M42: 2.5 | N42: MEDIUM
A43: INT-00042 | B43: L0714 | C43: FORM_SUBMIT | D43: 45859 | E43: SMS | F43: C002 | G43: Ebook: Abm Playbook | H43: OPENED | I43: 461 | J43: DESKTOP | K43: https://example.com/blog/reduce-cac | M43: 7.7 | N43: HIGH
A44: INT-00043 | B44: L0986 | C44: PRICING_PAGE_VIEW | D44: 45759 | E44: SOCIAL | F44: N/A | G44: 10 Lead Scoring Tips | H44: REGISTERED | I44: 1007 | J44: MOBILE | K44: N/A | M44: 16.8 | N44: HIGH
A45: INT-00044 | B45: L0041 | C45: CONTENT_DOWNLOAD | D45: 45905 | E45: IN-PERSON | F45: N/A | G45: Guide: Email Deliverability | H45: UNSUBSCRIBED | I45: 1352 | J45: UNKNOWN | K45: https://example.com/webinars | M45: 22.5 | N45: HIGH
A46: INT-00045 | B46: L0176 | C46: EMAIL_OPEN | D46: 45970 | E46: UNKNOWN | F46: C009 | G46: Case Study: Mid-Market Win | H46: REPLIED | I46: 510 | J46: MOBILE | K46: https://example.com/webinars | M46: 8.5 | N46: HIGH
A47: INT-00046 | B47: L0413 | C47: PRICING_PAGE_VIEW | D47: 45937 | E47: PHONE | F47: N/A | G47: Case Study: Smb Growth Story | H47: CONVERTED | I47: 2340 | J47: MOBILE | K47: https://example.com/resources/ebooks | M47: 39 | N47: HIGH
A48: INT-00047 | B48: L0227 | C48: EMAIL_CLICK | D48: 45886 | E48: CHAT | F48: C006 | G48: Ultimate Guide To Crm | H48: OPENED | I48: 1137 | J48: DESKTOP | K48: N/A | M48: 19 | N48: HIGH
... A50: INT-00049 | B50: L0076 | C50: UNSUBSCRIBE | D50: 45784 | E50: PHONE | F50: N/A | G50: Event Registration: Summit 2025 | H50: REGISTERED | I50: 2062 | J50: DESKTOP | K50: https://example.com/blog/reduce-cac | M50: 34.4 | N50: HIGH
A51: INT-00050 | B51: L0507 | C51: FORM_SUBMIT | E51: SMS | F51: C003 | G51: Webinar: Lead Scoring Best Practices | H51: DOWNLOADED | I51: 0 | J51: TABLET | K51: N/A | L51: Duplicate Entry | M51: 0 | N51: NONE
A52: INT-00051 | B52: L0390 | C52: PRICING_PAGE_VIEW | D52: 45823 | E52: SMS | F52: C006 | G52: Video: Customer Testimonial | H52: DOWNLOADED | I52: 1053 | J52: TABLET | K52: https://example.com/free-trial | M52: 17.6 | N52: HIGH
A53: INT-00052 | B53: L0417 | C53: PHONE_CALL | D53: 45870 | E53: UNKNOWN | F53: C009 | G53: Unknown | H53: IGNORED | I53: 1640 | J53: DESKTOP | K53: https://example.com/about | M53: 27.3 | N53: HIGH
A54: INT-00053 | B54: L0945 | C54: PRICING_PAGE_VIEW | D54: 45786 | E54: UNKNOWN | F54: C002 | G54: Roi Calculator Landing Page | H54: OPENED | I54: 67 | J54: UNKNOWN | K54: https://example.com/resources/ebooks | M54: 1.1 | N54: MEDIUM
A55: INT-00054 | B55: L0799 | C55: BLOG_READ | D55: 45797 | E55: SOCIAL | F55: C006 | G55: Social Post: Product Launch | H55: CLICKED | I55: 472 | J55: DESKTOP | K55: https://example.com/case-studies | M55: 7.9 | N55: HIGH
A56: INT-00055 | B56: L0819 | C56: EMAIL_CLICK | D56: 45981 | E56: CHAT | F56: C010 | G56: Whitepaper: State Of Gtm 2025 | H56: REGISTERED | I56: 1008 | J56: UNKNOWN | K56: N/A | M56: 16.8 | N56: HIGH
A57: INT-00056 | B57: L0329 | C57: WEBINAR_ATTENDED | D57: 45921 | E57: EMAIL | F57: C002 | G57: Case Study: Enterprise Win | H57: IGNORED | I57: 156 | J57: TABLET | K57: https://example.com/features | M57: 2.6 | N57: MEDIUM
A58: INT-00057 | B58: L0406 | C58: EMAIL_OPEN | D58: 45848 | E58: PUSH_NOTIFICATION | F58: C003 | G58: Blog: 5 Metrics Every Cmo Needs | H58: DOWNLOADED | I58: 1372 | J58: UNKNOWN | K58: https://example.com/features | M58: 22.9 | N58: HIGH
A59: INT-00058 | B59: L0167 | C59: EMAIL_OPEN | D59: 45715 | E59: SOCIAL | F59: C006 | G59: Newsletter Issue #44 | H59: OPENED | I59: 697 | J59: MOBILE | K59: https://example.com/contact | M59: 11.6 | N59: HIGH
A60: INT-00059 | B60: L0005 | C60: CHATBOT_CONVO | D60: 45713 | E60: CHAT | F60: C004 | G60: Retargeting Ad Creative A | H60: ENGAGED | I60: 1571 | J60: DESKTOP | K60: https://example.com/demo | M60: 26.2 | N60: HIGH
A61: INT-00060 | B61: L0854 | C61: DEMO_REQUEST | D61: 45681 | E61: PUSH_NOTIFICATION | F61: C001 | G61: Video: Customer Testimonial | H61: CLICKED | I61: 1026 | J61: DESKTOP | K61: N/A | M61: 17.1 | N61: HIGH
A62: INT-00061 | B62: L0079 | C62: EMAIL_OPEN | D62: 45812 | E62: CHAT | F62: C004 | G62: Chatbot: Pricing Inquiry | H62: VIEWED | I62: 0 | J62: DESKTOP | K62: https://example.com/blog/reduce-cac | M62: 0 | N62: NONE
A63: INT-00062 | B63: L0001 | C63: UNSUBSCRIBE | D63: 45798 | E63: WEB | F63: C008 | G63: Chatbot: Pricing Inquiry | H63: OPENED | I63: 0 | J63: MOBILE | K63: https://example.com/demo | M63: 0 | N63: NONE
... A74: INT-00073 | B74: L0557 | C74: DEMO_REQUEST | D74: 45681 | E74: WEB | F74: C003 | G74: Newsletter Issue #44 | H74: OPENED | I74: 1612 | J74: MOBILE | K74: https://example.com/blog/reduce-cac | M74: 26.9 | N74: HIGH
A75: INT-00074 | B75: L0800 | C75: WEBSITE_VISIT | E75: WEB | F75: C006 | G75: Newsletter Issue #43 | H75: CLICKED | I75: 1039 | J75: MOBILE | K75: https://example.com/contact | M75: 17.3 | N75: HIGH
A76: INT-00075 | B76: L0452 | C76: AD_CLICK | E76: CHAT | F76: C008 | G76: Blog: 5 Metrics Every Cmo Needs | H76: OPENED | I76: 554 | J76: DESKTOP | K76: https://example.com/free-trial | M76: 9.2 | N76: HIGH
A77: INT-00076 | B77: L0650 | C77: FREE_TRIAL_SIGNUP | D77: 45916 | E77: SMS | F77: N/A | G77: Template: Campaign Planning | H77: NO_RESPONSE | I77: 1927 | J77: UNKNOWN | K77: https://example.com/demo | M77: 32.1 | N77: HIGH
A78: INT-00077 | B78: L0718 | C78: UNSUBSCRIBE | D78: 45885 | E78: WEB | F78: C002 | G78: 10 Lead Scoring Tips | H78: BOUNCED | I78: 734 | J78: UNKNOWN | K78: https://example.com/demo | L78: Bad Email | M78: 12.2 | N78: HIGH
A79: INT-00078 | B79: L0716 | C79: EMAIL_OPEN | D79: 45836 | E79: EMAIL | F79: C001 | G79: Case Study: Mid-Market Win | H79: VIEWED | I79: 1895 | J79: MOBILE | K79: https://example.com/blog | M79: 31.6 | N79: HIGH
A80: INT-00079 | B80: L0443 | C80: FORM_SUBMIT | D80: 45702 | E80: UNKNOWN | F80: N/A | G80: Unknown | H80: OPENED | I80: 731 | J80: MOBILE | K80: https://example.com/competitors | M80: 12.2 | N80: HIGH
A81: INT-00080 | B81: L0977 | C81: BLOG_READ | D81: 45766 | E81: IN-PERSON | F81: C006 | G81: Competitor Comparison Sheet | H81: ENGAGED | I81: 426 | J81: MOBILE | K81: https://example.com/webinars | M81: 7.1 | N81: HIGH
A82: INT-00081 | B82: L0524 | C82: PRICING_PAGE_VIEW | D82: 45859 | E82: SOCIAL | F82: N/A | G82: Pricing Page | H82: NO_RESPONSE | I82: 2252 | J82: DESKTOP | K82: https://example.com/competitors | M82: 37.5 | N82: HIGH
A83: INT-00082 | B83: L0490 | C83: UNSUBSCRIBE | D83: 45666 | E83: WEB | F83: N/A | G83: Newsletter Issue #42 | H83: UNSUBSCRIBED | I83: 1873 | J83: DESKTOP | K83: https://example.com/contact | L83: High Intent | M83: 31.2 | N83: HIGH
A84: INT-00083 | B84: L0617 | C84: FORM_SUBMIT | D84: 45715 | E84: EMAIL | F84: N/A | G84: Template: Campaign Planning | H84: CONVERTED | I84: 769 | J84: DESKTOP | K84: https://example.com/blog/reduce-cac | M84: 12.8 | N84: HIGH
A85: INT-00084 | B85: L0327 | C85: DEMO_REQUEST | D85: 45893 | E85: EMAIL | F85: C006 | G85: Ultimate Guide To Crm | H85: CLICKED | I85: 16 | J85: MOBILE | K85: N/A | M85: 0.3 | N85: LOW
A86: INT-00085 | B86: L0741 | C86: PRICING_PAGE_VIEW | D86: 45796 | E86: PHONE | F86: N/A | G86: Ultimate Guide To Crm | H86: CLICKED | I86: 1639 | J86: TABLET | K86: https://example.com/blog | M86: 27.3 | N86: HIGH
A87: INT-00086 | B87: L0517 | C87: SOCIAL_ENGAGE | D87: 45843 | E87: UNKNOWN | F87: C002 | G87: Newsletter Issue #43 | H87: DOWNLOADED | I87: 1335 | J87: DESKTOP | K87: https://example.com/blog | L87: Demo Scheduled For Next Week | M87: 22.3 | N87: HIGH
A88: INT-00087 | B88: L0566 | C88: DEMO_REQUEST | D88: 45801 | E88: WEB | F88: C003 | G88: Case Study: Smb Growth Story | H88: OPENED | I88: 415 | J88: TABLET | K88: https://example.com/free-trial | M88: 6.9 | N88: HIGH
A89: INT-00088 | B89: L0761 | C89: CONTENT_DOWNLOAD | D89: 45818 | E89: WEB | F89: C010 | G89: Video: Customer Testimonial | H89: REGISTERED | I89: 1454 | J89: MOBILE | K89: https://example.com/case-studies | L89: Multi-Year Deal Potential | M89: 24.2 | N89: HIGH
A90: INT-00089 | B90: L0510 | C90: CONTENT_DOWNLOAD | D90: 45969 | E90: UNKNOWN | F90: C007 | G90: Newsletter Issue #42 | H90: OPENED | I90: 43 | J90: UNKNOWN | K90: https://example.com/pricing | M90: 0.7 | N90: LOW
A91: INT-00090 | B91: L0504 | C91: DEMO_REQUEST | D91: 45721 | E91: SOCIAL | F91: C005 | G91: Blog: How To Reduce Cac | H91: CLICKED | I91: 1997 | J91: MOBILE | K91: N/A | M91: 33.3 | N91: HIGH
A92: INT-00091 | B92: L0981 | C92: EMAIL_OPEN | D92: 45774 | E92: PUSH_NOTIFICATION | F92: C003 | G92: Free Trial Signup Page | H92: BOUNCED | I92: 461 | J92: MOBILE | K92: N/A | L92: High Intent | M92: 7.7 | N92: HIGH
A93: INT-00092 | B93: L0909 | C93: AD_CLICK | D93: 45951 | E93: UNKNOWN | F93: C010 | G93: Newsletter Issue #42 | H93: UNSUBSCRIBED | I93: 1261 | J93: DESKTOP | K93: N/A | M93: 21 | N93: HIGH
A94: INT-00093 | B94: L0873 | C94: BLOG_READ | D94: 45743 | E94: WEB | F94: C002 | G94: Pricing Page | H94: BOUNCED | I94: 2384 | J94: MOBILE | K94: https://example.com/contact | M94: 39.7 | N94: HIGH
A95: INT-00094 | B95: L0510 | C95: UNSUBSCRIBE | D95: 45691 | E95: PHONE | F95: C010 | G95: Free Trial Signup Page | H95: ENGAGED | I95: 433 | J95: DESKTOP | K95: N/A | M95: 7.2 | N95: HIGH
A96: INT-00095 | B96: L0166 | C96: DEMO_REQUEST | E96: CHAT | F96: N/A | G96: Chatbot: Pricing Inquiry | H96: OPENED | I96: 1065 | J96: DESKTOP | K96: https://example.com/pricing | L96: Wants To Talk To Reference Customer | M96: 17.8 | N96: HIGH
A97: INT-00096 | B97: L0098 | C97: PHONE_CALL | D97: 45770 | E97: CHAT | F97: C005 | G97: Unknown | H97: UNSUBSCRIBED | I97: 156 | J97: DESKTOP | K97: https://example.com/resources/ebooks | L97: Budget Not Confirmed | M97: 2.6 | N97: MEDIUM
A98: INT-00097 | B98: L0312 | C98: EMAIL_CLICK | D98: 45675 | E98: EMAIL | F98: C008 | G98: 10 Lead Scoring Tips | H98: VIEWED | I98: 1734 | J98: DESKTOP | K98: https://example.com/competitors | M98: 28.9 | N98: HIGH
A99: INT-00098 | B99: L0482 | C99: PHONE_CALL | D99: 45968 | E99: WEB | F99: N/A | G99: Product Demo Video | H99: NO_RESPONSE | I99: 2353 | J99: MOBILE | K99: https://example.com/pricing | M99: 39.2 | N99: HIGH
A100: INT-00099 | B100: L0132 | C100: EMAIL_OPEN | D100: 45971 | E100: PUSH_NOTIFICATION | F100: C008 | G100: Newsletter Issue #44 | H100: REGISTERED | I100: 1259 | J100: UNKNOWN | K100: https://example.com/resources/ebooks | M100: 21 | N100: HIGH
A101: INT-00100 | B101: L0422 | C101: FORM_SUBMIT | D101: 45683 | E101: EMAIL | F101: C005 | G101: Video: Platform Overview 3Min | H101: OPENED | I101: 0 | J101: DESKTOP | K101: https://example.com/features | M101: 0 | N101: NONE
A102: INT-00101 | B102: L0125 | C102: DEMO_REQUEST | D102: 45832 | E102: CHAT | F102: C010 | G102: Partner Referral Landing Page | H102: VIEWED | I102: 0 | J102: MOBILE | K102: https://example.com/resources/ebooks | M102: 0 | N102: NONE
A103: INT-00102 | B103: L0131 | C103: FREE_TRIAL_SIGNUP | D103: 45822 | E103: UNKNOWN | F103: N/A | G103: Webinar: Lead Scoring Best Practices | H103: VIEWED | I103: 2006 | J103: DESKTOP | K103: https://example.com/blog/reduce-cac | M103: 33.4 | N103: HIGH
A104: INT-00103 | B104: L0820 | C104: BLOG_READ | D104: 45919 | E104: IN-PERSON | F104: C008 | G104: Unknown | H104: PARTIAL_VIEW | I104: 1862 | J104: MOBILE | K104: https://example.com/competitors | M104: 31 | N104: HIGH
A105: INT-00104 | B105: L0449 | C105: UNSUBSCRIBE | D105: 45695 | E105: IN-PERSON | F105: C008 | G105: Webinar: Lead Scoring Best Practices | H105: CONVERTED | I105: 0 | J105: TABLET | K105: https://example.com/demo | M105: 0 | N105: NONE
A106: INT-00105 | B106: L0546 | C106: PRICING_PAGE_VIEW | D106: 45890 | E106: SMS | F106: N/A | G106: Pricing Page | H106: CLICKED | I106: 1954 | J106: TABLET | K106: https://example.com/demo | M106: 32.6 | N106: HIGH
A107: INT-00106 | B107: L0120 | C107: PRICING_PAGE_VIEW | D107: 45832 | E107: IN-PERSON | F107: C007 | G107: Demo: Live Product Walkthrough | H107: OPENED | I107: 1871 | J107: TABLET | K107: https://example.com/about | M107: 31.2 | N107: HIGH
A108: INT-00107 | B108: L0569 | C108: UNSUBSCRIBE | D108: 45888 | E108: PUSH_NOTIFICATION | F108: C007 | G108: Partner Referral Landing Page | H108: NO_RESPONSE | I108: 1018 | J108: DESKTOP | K108: https://example.com/case-studies | M108: 17 | N108: HIGH
A109: INT-00108 | B109: L0497 | C109: AD_CLICK | D109: 45828 | E109: SOCIAL | F109: C010 | G109: Webinar: Marketing Automation 101 | H109: NO_RESPONSE | I109: 1335 | J109: TABLET | K109: https://example.com/roi-calculator | M109: 22.3 | N109: HIGH
... A118: INT-00117 | B118: L0577 | C118: PRICING_PAGE_VIEW | D118: 45692 | E118: UNKNOWN | F118: C001 | G118: Whitepaper: State Of Gtm 2025 | H118: VIEWED | I118: 59 | J118: TABLET | K118: https://example.com/contact | M118: 1 | N118: LOW
A119: INT-00118 | B119: L0475 | C119: BLOG_READ | E119: PHONE | F119: N/A | G119: Retargeting Ad Creative A | H119: ENGAGED | I119: 122 | J119: MOBILE | K119: https://example.com/contact | M119: 2 | N119: MEDIUM
...

Sheet raw_leads
A1: lead_id | B1: name | C1: email | D1: phone | E1: company | F1: company_size | G1: source | H1: email_opens | I1: clicks | J1: website_visits | K1: demo_requested | L1: last_activity | M1: lead_status | N1: industry | O1: job_title | P1: country | Q1: annual_revenue | R1: lead_created_date | S1: linkedin_url
A2: L0001 | B2: Liora Jackson | C2: liora.jackson@airtable.com | D2: 232-130-2535 | E2: AIRTABLE | F2: smb | H2: 35 | I2: 20 | J2: 26 | K2: n | L2: 45803 | M2: ENGAGED | N2: SaaS | O2: Product Manager | P2: Thailand | Q2: $100M-500M | R2: 45812
A3: L0002 | B3: Yara Malik | C3: yara.malik@airtable.com | E3: airtable | F3: Smb | G3: event | H3: 4 | J3: 18 | K3: YES | L3: 45701 | M3: Qualified | N3: Retail | O3: Sales Engineer | P3: india | Q3: $1B+ | R3: 46013 | S3: LinkedIn.com/in/dashiellpopov22
A4: L0003 | B4: Luna Harris | C4: luna.harris@crowdstrike.com | D4: 434.941.1525 | E4: crowd strike | F4: small business | G4: EVENT | H4: 13 | I4: 18 | J4: 20 | K4: y | L4: 45859 | M4: QUALIFIED | N4: AI/ML | O4: Business Development Rep | P4: australia | Q4: $50M - $100M | R4: 46010 | S4: https://linkedin.com/in/xylanguyen47
A5: L0004 | B5: James Nakamura | C5: james.nakamura@hubspot.com | E5: hub spot | F5: Startup | G5: Partner | H5: 35 | I5: 0 | J5: 7 | K5: 0 | L5: 45802 | M5: new | N5: Logistics | O5: RevOps Manager | P5: Netherlands | Q5: Unknown | S5: https://linkedin.com/in/ravischneider98
A6: L0005 | B6: Bastian Mishra | C6: bastian.mishra@dropbox.com | D6: +1-997-643-1009 | E6: dropbox | F6: small business | I6: 9 | J6: 15 | K6: Yes | L6: 45712 | M6: NURTURING | N6: HEALTHCARE | O6: CTO | P6: Australia | Q6: $50M - $100M | R6: 45928 | S6: linkedin.com/in/deepasaxena70
A7: L0006 | B7: Yuki Robinson | C7: yuki.robinson@cloudflare.com | E7: CLOUDFLARE | F7: small business | G7: Organic | H7: 14 | I7: 0 | K7: 1 | M7: qualified | N7: fintech | O7: Program Manager | P7: CA | Q7: 1M-10M | R7: 45765
A8: L0007 | B8: Uriel Jensen | C8: uriel.jensen@stripeinc.com | D8: (946) 155-2612 | E8: stripe inc | F8: Startup | G8: COLD_EMAIL | H8: 6 | I8: 6 | J8: 8 | K8: FALSE | L8: 45877 | M8: ENGAGED | N8: E-commerce | O8: Sales Operations | P8: DE | R8: 45660 | S8: www.linkedin.com/in/jasminesanchez53
A9: L0008 | B9: Vivian Young | C9: vivian.young@google.com | D9: 633-813-8973 | E9: google | F9: mid market | G9: social | H9: 3 | I9: 17 | K9: true | N9: Automotive | O9: Intern | P9: india | R9: 45719 | S9: www.linkedin.com/in/umbraiyer31
A10: L0009 | B10: Elena Pandey | C10: elena.pandey@elastic.com | D10: 467-309-6147 | E10: elastic | F10: SMB | G10: EVENT | H10: 19 | I10: 2 | K10: No | L10: 45691 | M10: CONVERTED | N10: Legal Tech | O10: Intern | R10: 45696
A11: L0010 | B11: Priya Muller | C11: priya.muller@paloalto.com | D11: 3069993200 | E11: palo alto | F11: mid-market | G11: PAID | H11: 9 | I11: 19 | J11: 21 | K11: y | L11: 45794 | M11: NURTURING | N11: proptech | O11: Head of Growth | P11: germany | Q11: Series C+ | R11: 45668 | S11: linkedin.com/in/liorascott21
A12: L0011 | B12: Landon Rossi | C12: landon.rossi@crowdstrike.com | D12: (351) 540-3088 | E12: crowd strike | F12: Smb | G12: event | H12: 2 | I12: 6 | J12: 42 | K12: no | L12: 45928 | M12: CONTACTED | N12: ai/ml | O12: Growth Hacker | P12: india | Q12: Series B | R12: 45839
A13: L0012 | B13: Jamal Soto | C13: jamal.soto@notion.com | D13: 681.327.4269 | E13: Notion | G13: cold email | H13: 14 | I13: 6 | J13: 17 | K13: YES | L13: 45789 | M13: new | N13: ENERGY | O13: PR Manager | P13: Mexico | Q13: $50M-100M | R13: 45783 | S13: LinkedIn.com/in/ravijones14
A14: L0013 | B14: Julian Shah | C14: julian.shah@dropbox.com | E14: Dropbox | F14: STARTUP | G14: organic | H14: 34 | I14: 6 | J14: 4 | K14: 0 | L14: 45941 | M14: contacted | N14: Cybersecurity | O14: Marketing Coordinator | P14: Ireland | Q14: 50M+ | R14: 45795
A15: L0014 | B15: Finn Torres | C15: finn.torres@databricks.com | D15: +14155406279 | E15: DataBricks | G15: partner | H15: 32 | I15: 5 | J15: 18 | K15: yes | L15: 45941 | M15: qualified | N15: insurtech | O15: Marketing Analyst | P15: Brazil | Q15: $100M-500M
A16: L0015 | B16: Tatiana Dubois | C16: tatiana.dubois@elastic.com | D16: 351.771.1090 | E16: elastic | F16: mid-market | G16: Content_Syndication | H16: 33 | I16: 17 | J16: 54 | K16: no | L16: 45891 | M16: LOST | O16: Sales Operations | P16: Thailand | Q16: $50M - $100M | R16: 45740 | S16: https://linkedin.com/in/nicoscott97
A17: L0016 | B17: Liora Adams | C17: liora.adams@datadog.com | D17: 753-182-3267 | E17: Datadog | F17: smb | G17: Event | H17: 13 | J17: 34 | L17: 45774 | M17: CONTACTED | N17: supply chain | O17: CMO | P17: South Africa | Q17: < $1M | R17: 45866 | S17: linkedin.com/in/finnolsen96
A18: L0017 | B18: Margaux Aguilar | C18: margaux.aguilar@asana.com | D18: 941-269-8657 | E18: asana | F18: Mid-market | G18: Direct | I18: 18 | J18: 5 | K18: 1 | L18: 45875 | M18: contacted | N18: CleanTech | O18: Channel Manager | P18: South Korea | Q18: 50M+ | R18: 45847 | S18: www.linkedin.com/in/finnhill11
A19: L0018 | B19: Eve Mendoza | E19: splunk | F19: smb | G19: webinar | H19: 9 | I19: 15 | J19: 36 | K19: y | L19: 45802 | M19: Converted | N19: MarTech | O19: RevOps Manager | P19: india | Q19: $50M-100M | R19: 45796 | S19: https://linkedin.com/in/umaro'brien92
A20: L0019 | B20: Tina Petrov | C20: tina.petrov@linear.com | D20: 7799011672 | E20: linear | F20: enterprise | G20: Content_Syndication | H20: 4 | I20: 10 | K20: FALSE | L20: 45702 | M20: Converted | N20: Retail | O20: Co-Founder | P20: Vietnam | Q20: $1M - $10M | R20: 45797 | S20: www.linkedin.com/in/kaiavega62
A21: L0020 | B21: Julian Mehta | C21: julian.mehta@microsoft.com | D21: (884) 488-6511 | E21: microsoft | G21: Cold_Email | H21: 13 | I21: 8 | J21: 56 | K21: No | L21: 45795 | M21: new | N21: HRTech | O21: SDR Manager | P21: BR | R21: 45770 | S21: linkedin.com/in/xiomarajohansson3
A22: L0021 | B22: Zachary Allen | C22: zachary.allen@cloudflare.com | D22: 5384608434 | E22: Cloudflare | F22: Smb | G22: Social | H22: 12 | I22: 17 | J22: 44 | K22: NO | L22: 46007 | M22: Qualified | N22: biotech | O22: Head of Sales | P22: SG | Q22: < $1M | R22: 45680 | S22: LinkedIn.com/in/ursulagarcia7
A23: L0022 | B23: Yvonne Diaz | C23: yvonne.diaz@microsoftcorp.com | D23: 388.152.5136 | E23: microsoft corp | G23: paid | H23: 25 | I23: 18 | J23: 3 | K23: No | L23: 45940 | M23: qualified | N23: PropTech | O23: CEO | P23: Indonesia | Q23: Series B | R23: 45913 | S23: www.linkedin.com/in/landonnelson76
A24: L0023 | B24: Camila Decker | C24: camila.decker@linear.com | E24: Linear | F24: MID-MARKET | G24: DIRECT | J24: 38 | L24: 45757 | M24: disqualified | N24: biotech | O24: Chief Growth Officer | P24: CA | Q24: 1M-10M | R24: 45980 | S24: LinkedIn.com/in/zarapark15
A25: L0024 | B25: George Reyes | C25: george.reyes@amazon.com | D25: +14955493037 | E25: amazon | F25: growth | G25: cold_email | H25: 17 | I25: 15 | J25: 38 | K25: Yes | L25: 46002 | N25: proptech | O25: Director of Marketing | P25: germany | Q25: $5M-$25M | R25: 45949 | S25: LinkedIn.com/in/umbramehta35
A26: L0025 | B26: Karen Ortiz | C26: karen.ortiz@datadog.com | D26: +12935816700 | E26: DATADOG | F26: small business | G26: Cold_Email | H26: 10 | I26: 15 | J26: 60 | K26: false | L26: 45902 | M26: QUALIFIED | N26: E-COMMERCE | O26: Data Analyst | Q26: Series A | R26: 45927 | S26: www.linkedin.com/in/quinlanbose70
A27: L0026 | B27: Dante Martinez | C27: dante.martinez@elastic.com | E27: ELASTIC | F27: Smb | G27: partner | H27: 31 | I27: 20 | J27: 15 | K27: NO | L27: 45675 | M27: CONTACTED | N27: E-COMMERCE | O27: Digital Marketing Manager | P27: france | Q27: $50M-100M | R27: 45732 | S27: https://www.linkedin.com/in/yvonnenakamura91
A28: L0027 | B28: Emilia Gupta | C28: emilia.gupta@hubspot.com | D28: 2713827798 | E28: hubspot | G28: SOCIAL | H28: 18 | I28: 18 | J28: 42 | L28: 45887 | M28: NURTURING | N28: logistics | O28: Program Manager | P28: South Africa | Q28: 50M+ | R28: 45999 | S28: linkedin.com/in/ivannair53
A29: L0028 | B29: Farhan Mendoza | C29: farhan.mendoza@paloalto.com | D29: 329.614.6439 | E29: PALO ALTO | F29: mid-market | G29: partner | I29: 0 | J29: 26 | K29: 1 | L29: 45704 | M29: engaged | N29: CleanTech | O29: Technical Lead | P29: Argentina | Q29: 50M+ | R29: 45913 | S29: www.linkedin.com/in/idrismedina98
A30: L0029 | B30: Leandro Jones | C30: leandro.jones@datadog.com | E30: datadog | F30: ENTERPRISE | G30: PAID | H30: 19 | I30: 1 | J30: 3 | K30: N | L30: 45843 | M30: Contacted | N30: Media | P30: IN | Q30: Under $1M | R30: 45952
A31: L0030 | B31: Xyla Thompson | D31: 3611758237 | E31: palo alto networks | F31: smb | G31: cold_email | H31: 27 | I31: 14 | J31: 12 | K31: false | L31: 45696 | M31: NEW | N31: LOGISTICS | O31: VP Revenue | P31: Netherlands | R31: 45847
A32: L0031 | B32: Xanthe Vega | C32: xanthe.vega@canva.com | E32: CANVA | F32: startup | G32: WEBINAR | H32: 16 | I32: 4 | J32: 57 | K32: 1 | L32: 45803 | M32: QUALIFIED | N32: fintech | O32: Sales Engineer | P32: Australia | R32: 46005
A33: L0032 | B33: Hassan Soto | C33: hassan.soto@datadog.com | D33: 502.864.6549 | E33: datadog | F33: mid-market | G33: Partner | H33: 9 | I33: 7 | J33: 46 | K33: 0 | L33: 45912 | M33: qualified | N33: Gaming | O33: VP Marketing | Q33: Unknown | R33: 46013
A34: L0033 | B34: Valentina Mehta | D34: (426) 763-2035 | E34: docu sign | G34: cold_email | H34: 7 | I34: 1 | J34: 31 | K34: no | L34: 45905 | M34: NEW | N34: Retail | O34: Partnerships Manager | P34: Indonesia | Q34: self-funded | R34: 45859
A35: L0034 | B35: Xiomara Dubois | C35: xiomara.dubois@cloudflare.com | D35: (902) 476-9920 | E35: Cloudflare | F35: startup | G35: organic | H35: 12 | I35: 14 | J35: 13 | K35: 1 | L35: 45659 | M35: engaged | N35: fintech | O35: Customer Success Manager | P35: Australia | Q35: $1B+ | R35: 45907 | S35: LinkedIn.com/in/ivanahmed19
A36: L0035 | B36: Alice Adams | C36: alice.adams@notionlabs.com | E36: notion labs | F36: startup | G36: social | H36: 1 | I36: 1 | J36: 26 | K36: yes | L36: 45704 | M36: QUALIFIED | N36: DevOps | O36: Associate | P36: France | Q36: 0-1M | R36: 45681 | S36: www.linkedin.com/in/quinlanhoffman39
A37: L0036 | B37: Magnus Malhotra | C37: magnus.malhotra@asana.com | E37: Asana | F37: ENTERPRISE | G37: Cold_Email | H37: 4 | I37: 19 | J37: 35 | K37: true | L37: 45947 | M37: Nurturing | N37: Retail | O37: Intern | P37: Vietnam | R37: 45982 | S37: www.linkedin.com/in/opalvargas28
A38: L0037 | B38: Nico Kapoor | C38: nico.kapoor@zendesk.com | D38: (356) 803-8770 | E38: zendesk | F38: ENTERPRISE | G38: Paid | J38: 51 | K38: No | L38: 45948 | M38: CONVERTED | N38: fintech | O38: CEO | P38: Colombia | Q38: $5M-$25M | R38: 45866 | S38: LinkedIn.com/in/nickmalhotra37
A39: L0038 | B39: Dmitri Malik | C39: dmitri.malik@freshworks.com | D39: 980.385.4705 | E39: FRESHWORKS | F39: STARTUP | G39: DIRECT | H39: 35 | J39: 53 | K39: Y | M39: Qualified | O39: Technical Lead | P39: Italy | R39: 45952 | S39: linkedin.com/in/kiraguerrero82
A40: L0039 | B40: Xander Mendoza | C40: xander.mendoza@slack.com | D40: 286-153-3549 | E40: slack | F40: Mid-market | G40: organic | H40: 17 | I40: 13 | J40: 28 | K40: FALSE | L40: 45904 | M40: Converted | N40: telecom | O40: RevOps Manager | P40: UK | Q40: $100M+ | R40: 45971
A41: L0040 | B41: Zion Novak | C41: zion.novak@linear.com | E41: LINEAR | F41: Growth | G41: Content_Syndication | H41: 24 | I41: 7 | J41: 53 | K41: 0 | L41: 45701 | M41: ENGAGED | N41: FINTECH | O41: Marketing Operations | P41: United States | Q41: $10M-50M | R41: 45944 | S41: linkedin.com/in/liorachen38
A42: L0041 | B42: Bennett Williams | C42: bennett.williams@docusign.com | D42: +1-449-546-7560 | E42: DocuSign | F42: ENTERPRISE | G42: EVENT | H42: 21 | I42: 5 | K42: 1 | L42: 45907 | M42: DISQUALIFIED | N42: logistics | O42: Engineering Manager | P42: AU | Q42: $100M-500M | R42: 45736
A43: L0042 | B43: Perseus Wilson | C43: perseus.wilson@miro.com | D43: 858.750.6295 | E43: miro | F43: ENTERPRISE | G43: Cold_Email | H43: 4 | I43: 20 | J43: 17 | K43: Yes | M43: LOST | N43: E-commerce | O43: Marketing Analyst | P43: Bangladesh | Q43: $1M-10M | R43: 45780 | S43: LinkedIn.com/in/xanderdubois77
A44: L0043 | B44: Winston Costa | C44: winston.costa@meta.com | D44: (687) 613-3471 | E44: META | G44: PAID | H44: 21 | I44: 2 | J44: 11 | K44: Yes | L44: 45884 | M44: LOST | N44: AI / ML | O44: Sales Engineer | P44: Saudi Arabia | Q44: $10M+ | R44: 45830 | S44: linkedin.com/in/juniperreyes43
A45: L0044 | B45: Isla Taylor | C45: isla.taylor@paloaltonetworks.com | E45: Palo Alto Networks | F45: mid-market | G45: Referral | H45: 19 | I45: 12 | J45: 45 | K45: YES | L45: 45859 | M45: engaged | N45: fintech | O45: CTO | P45: germany | Q45: unknown | R45: 45669
A46: L0045 | B46: Deepa Ali | C46: deepa.ali@hubspot.com | D46: (752) 955-9626 | E46: HubSpot | F46: mid-market | G46: COLD_EMAIL | H46: 8 | I46: 4 | J46: 53 | K46: No | L46: 45740 | M46: QUALIFIED | N46: FINTECH | O46: Events Manager | P46: UAE | Q46: 0-1M | R46: 45940 | S46: https://linkedin.com/in/marisolking69
A47: L0046 | B47: Dmitri Malhotra | C47: dmitri.malhotra@cloudflare.com | D47: +1-996-491-9239 | E47: Cloudflare | F47: STARTUP | G47: REFERRAL | H47: 8 | I47: 1 | J47: 55 | K47: TRUE | L47: 45711 | M47: ENGAGED | N47: Cybersecurity | O47: VP Sales | P47: Germany | Q47: 1M-10M | R47: 45905 | S47: www.linkedin.com/in/xanderverma29
A48: L0047 | B48: Nolan Tiwari | C48: nolan.tiwari@notion.com | D48: 301.959.6493 | E48: notion | F48: Mid-Market | G48: referral | I48: 15 | J48: 8 | L48: 45660 | M48: new | N48: proptech | O48: director of demand gen | P48: India | Q48: self-funded | R48: 45842 | S48: linkedin.com/in/jasminenelson16
A49: L0048 | B49: Kevin Chen | C49: kevin.chen@canva.com | E49: CANVA | F49: Mid-Market | G49: social | H49: 22 | I49: 13 | J49: 42 | K49: YES | L49: 45811 | M49: LOST | N49: energy | O49: Intern | P49: United States
A50: L0049 | B50: Thea Hill | C50: thea.hill@notion.com | D50: 5402361726 | E50: Notion | F50: enterprise | G50: COLD_EMAIL | H50: 11 | I50: 14 | J50: 30 | K50: 1 | L50: 45719 | M50: disqualified | N50: Retail | O50: Growth Lead | P50: Netherlands | Q50: Series B | R50: 45668 | S50: www.linkedin.com/in/doriano'brien70
A51: L0050 | B51: Nadia Jones | C51: nadia.jones@meta.com | D51: +16098618204 | E51: Meta | F51: small business | G51: Referral | H51: 31 | I51: 16 | J51: 5 | K51: FALSE | L51: 45957 | M51: converted | N51: BIOTECH | O51: Operations Manager | P51: France | R51: 45792 | S51: www.linkedin.com/in/henriksanchez89
A52: L0051 | B52: Nolan Johansson | C52: nolan.johansson@asana.com | E52: asana | F52: ENTERPRISE | G52: EVENT | H52: 10 | I52: 4 | J52: 43 | M52: qualified | N52: insurtech | O52: Sales Engineer | P52: UAE | Q52: $100M+
A53: L0052 | B53: Nico Verma | C53: nico.verma@hubspot.com | E53: HubSpot | F53: mid-market | G53: Organic | H53: 31 | I53: 17 | J53: 49 | K53: Y | L53: 45767 | M53: Nurturing | N53: automotive | O53: vp marketing | P53: FR | R53: 45739 | S53: https://www.linkedin.com/in/wendydominguez88
A54: L0053 | B54: Soren Shah | C54: soren.shah@snowflake.com | D54: (570) 620-4673 | E54: SNOWFLAKE | F54: mid market | G54: referral | H54: 31 | J54: 23 | L54: 45905 | N54: E-COMMERCE | O54: VP of Marketing | P54: Ireland | Q54: $25M-$100M | R54: 45914 | S54: https://www.linkedin.com/in/vesperwilson17
A55: L0054 | B55: Magnus Wilson | C55: magnus.wilson@workday.com | D55: +1-256-951-3034 | E55: WORKDAY | F55: Mid-Market | G55: cold_email | H55: 20 | I55: 7 | J55: 60 | K55: yes | L55: 45697 | M55: New | N55: BioTech | O55: CTO | P55: Sweden | Q55: $10M-50M | R55: 45735 | S55: LinkedIn.com/in/noahsanchez85
A56: L0055 | B56: Cordelia Ali | C56: cordelia.ali@googleinc.com | D56: +1-415-885-7825 | E56: GOOGLE INC | F56: ENTERPRISE | G56: Organic | H56: 34 | I56: 9 | J56: 51 | K56: 0 | L56: 45872 | M56: disqualified | N56: healthcare | O56: Product Manager | P56: Philippines | Q56: Unknown | R56: 45935
A57: L0056 | B57: Farhan Castillo | C57: farhan.castillo@linear.com | D57: 473-560-5061 | E57: linear | F57: mid-market | G57: organic | H57: 24 | I57: 13 | J57: 55 | K57: NO | L57: 45954 | M57: Lost | N57: HRTech | O57: Product Manager | P57: Turkey | Q57: Unknown | R57: 45793
A58: L0057 | B58: Yasmin Schneider | D58: (681) 392-9793 | E58: Meta | F58: mid-market | G58: Content_Syndication | H58: 16 | I58: 12 | J58: 25 | K58: Yes | L58: 45759 | M58: CONVERTED | N58: biotech | O58: Chief Marketing Officer | P58: New Zealand | Q58: Series A | R58: 45952 | S58: https://www.linkedin.com/in/ginataylor51
A59: L0058 | B59: Katrina Fischer | C59: katrina.fischer@dropbox.com | D59: 685-631-8487 | E59: Dropbox | F59: Mid-market | H59: 20 | I59: 19 | J59: 19 | K59: Yes | L59: 45918 | M59: NURTURING | O59: Head of Strategy | P59: United States | Q59: $5M-$25M | R59: 45857
A60: L0059 | B60: Yuki Ivanov | C60: yuki.ivanov@palantirtechnologies.com | E60: Palantir Technologies | F60: ENTERPRISE | G60: Event | H60: 15 | J60: 7 | K60: y | M60: Lost | N60: media | O60: Co-Founder | P60: Colombia | Q60: unknown | R60: 45946 | S60: LinkedIn.com/in/paulherrera18
A61: L0060 | B61: Carlos Fischer | C61: carlos.fischer@twilio.com | D61: +1-892-890-5331 | E61: Twilio | G61: webinar | H61: 17 | I61: 7 | J61: 19 | K61: N | L61: 46014 | M61: NURTURING | O61: Director of Analytics | P61: Italy | Q61: Series B | R61: 45781 | S61: https://www.linkedin.com/in/margauxsingh51
A62: L0061 | B62: Liam Gonzalez | C62: liam.gonzalez@intercom.com | D62: 477-675-5450 | E62: Intercom | F62: mid-market | G62: social | H62: 33 | I62: 7 | K62: FALSE | L62: 45873 | M62: contacted | N62: CYBERSECURITY | O62: Marketing Manager | P62: india | R62: 45772 | S62: linkedin.com/in/gabriellabaker83
A63: L0062 | B63: Wendy Cruz | C63: wendy.cruz@meta.com | E63: Meta | F63: Enterprise | G63: EVENT | H63: 11 | I63: 9 | J63: 0 | K63: N | L63: 45699 | M63: Nurturing | N63: Retail | O63: Junior Analyst | P63: australia | Q63: Unknown | R63: 45699
A64: L0063 | B64: Penelope Reyes | C64: penelope.reyes@snowflake.com | D64: +1-615-946-8007 | E64: Snowflake | F64: small business | G64: Paid | H64: 6 | I64: 4 | J64: 59 | K64: n | M64: NEW | N64: insurtech | O64: GTM Lead | P64: US | Q64: 10M-50M | R64: 45931
A65: L0064 | B65: Qasim Gomez | C65: qasim.gomez@slack.com | D65: (518) 806-2923 | E65: slack | F65: Smb | G65: event | H65: 14 | I65: 15 | J65: 47 | K65: No | L65: 46009 | M65: NURTURING | N65: Legal Tech | O65: Customer Success Manager | P65: Germany | Q65: $1M - $10M | R65: 45707
A66: L0065 | B66: Nikolai Joshi | C66: nikolai.joshi@atlassian.com | D66: +17001939361 | E66: atlassian | F66: Enterprise | G66: Partner | H66: 26 | I66: 1 | J66: 43 | K66: N | L66: 45847 | M66: Engaged | N66: SaaS | O66: director of demand gen | P66: CA | R66: 45706 | S66: linkedin.com/in/racheltiwari61
A67: L0066 | B67: Xavier Kim | C67: xavier.kim@airtable.com | D67: (586) 484-2314 | E67: airtable | F67: mid-market | G67: Direct | H67: 22 | J67: 25 | K67: yes | L67: 45774 | M67: new | N67: SAAS | O67: Marketing Coordinator | P67: Bangladesh | Q67: $50M - $100M | R67: 45865
A68: L0067 | B68: Penelope Shah | C68: penelope.shah@linear.com | D68: (216) 346-4376 | E68: Linear | F68: mid-market | G68: ORGANIC | H68: 3 | I68: 1 | J68: 14 | K68: no | L68: 45662 | M68: LOST | N68: BIOTECH | O68: Content Marketing Lead | P68: Israel | Q68: Series A | R68: 45816
A69: L0068 | B69: Kira Ramos | C69: kira.ramos@workday.com | D69: (637) 669-9120 | E69: workday | F69: startup | G69: Event | H69: 20 | I69: 13 | J69: 24 | K69: NO | L69: 45877 | M69: ENGAGED | N69: legaltech | O69: Marketing Coordinator | P69: AU | Q69: $1M-10M | R69: 45856 | S69: https://linkedin.com/in/ximenalopez33
A70: L0069 | B70: Isla Reyes | C70: isla.reyes@servicenow.com | D70: 817-140-2192 | E70: Service Now | F70: smb | G70: DIRECT | H70: 13 | I70: 10 | J70: 58 | K70: yes | L70: 45771 | M70: nurturing | N70: Automotive | O70: Customer Success Manager | P70: japan | Q70: 0-1M | R70: 45790 | S70: https://www.linkedin.com/in/onyxmalik40
A71: L0070 | B71: Qasim Nakamura | C71: qasim.nakamura@hashicorp.com | D71: (623) 146-4625 | E71: Hashicorp | F71: Mid-Market | G71: Organic | H71: 26 | I71: 6 | J71: 24 | K71: Yes | L71: 45887 | M71: new | N71: Logistics | O71: Account Executive | P71: Egypt | Q71: Over $1B | R71: 45875 | S71: linkedin.com/in/opheliasanchez18
A72: L0071 | B72: Margaux Moreau | C72: margaux.moreau@amazon.com | D72: +12498821104 | E72: amazon | F72: Mid-Market | G72: WEBINAR | I72: 6 | J72: 23 | K72: Yes | L72: 45981 | M72: NURTURING | N72: automotive | O72: CMO | P72: US | Q72: unknown | S72: linkedin.com/in/ursulaolsen37
A73: L0072 | B73: Adeline Chandra | C73: adeline.chandra@stripe.com | E73: stripe | G73: Social | H73: 17 | I73: 2 | J73: 25 | L73: 45999 | M73: Nurturing | N73: ecommerce | O73: Growth Lead | P73: germany | Q73: $10M+ | R73: 45678
A74: L0073 | B74: Samir Anderson | C74: samir.anderson@palantir.com | D74: 4353168790 | E74: palantir | F74: Enterprise | G74: paid | H74: 17 | I74: 18 | J74: 11 | K74: true | M74: New | N74: AI/ML | O74: Communications Director | P74: CA | Q74: $100M+ | R74: 45860 | S74: linkedin.com/in/islakumar97
A75: L0074 | B75: James Rojas | D75: 987.728.7499 | E75: mongodb | F75: small business | G75: Organic | H75: 28 | I75: 11 | J75: 24 | K75: FALSE | L75: 45952 | M75: NEW | N75: ecommerce | O75: VP Revenue | Q75: $10M-50M | R75: 45861 | S75: https://www.linkedin.com/in/noahguerrero50
A76: L0075 | B76: Qasim Moore | C76: qasim.moore@linear.com | D76: (768) 624-7685 | E76: linear | F76: enterprise | G76: Paid | H76: 5 | I76: 10 | J76: 0 | K76: N | L76: 45712 | M76: CONVERTED | N76: PropTech | O76: Senior Associate | P76: IN | Q76: $500M-1B | R76: 45786 | S76: https://www.linkedin.com/in/quinnsanchez56
A77: L0076 | B77: Finn Nelson | C77: finn.nelson@notion.com | D77: +13384111110 | E77: Notion | F77: small business | G77: Event | H77: 21 | I77: 13 | J77: 55 | K77: 1 | L77: 45726 | M77: Lost | N77: hrtech | O77: Director of Analytics | P77: Israel | Q77: $10M+ | R77: 45801 | S77: https://linkedin.com/in/xiomaramalhotra74
A78: L0077 | B78: Hugo Singh | C78: hugo.singh@palantir.com | D78: (227) 844-8563 | E78: palantir | F78: mid market | G78: partner | H78: 4 | I78: 13 | J78: 8 | K78: 1 | L78: 45799 | M78: lost | N78: Telecom | O78: Channel Manager | P78: CA | Q78: Under $1M | R78: 45856 | S78: linkedin.com/in/zinniachen70
A79: L0078 | B79: Qasim Diaz | C79: qasim.diaz@amazoninc.com | E79: Amazon Inc | F79: Mid-market | G79: ORGANIC | H79: 25 | I79: 10 | J79: 27 | K79: no | M79: Qualified | N79: legaltech | O79: Associate | P79: Brazil | Q79: $10M+ | R79: 45980 | S79: www.linkedin.com/in/mayashah4
A80: L0079 | B80: Aisha Gonzalez | C80: aisha.gonzalez@airtable.com | E80: airtable | G80: cold email | H80: 28 | I80: 14 | J80: 19 | K80: Yes | L80: 45689 | M80: ENGAGED | N80: Logistics | O80: Revenue Operations | P80: IN | Q80: self-funded | R80: 45734
A81: L0080 | B81: Raphael Park | C81: raphael.park@stripe.com | D81: +14025608037 | E81: STRIPE | F81: enterprise | G81: Webinar | H81: 4 | I81: 17 | J81: 20 | K81: y | L81: 45799 | M81: ENGAGED | N81: automotive | O81: Data Analyst | P81: New Zealand | Q81: $100M+ | R81: 45836 | S81: linkedin.com/in/tarachandra87
A82: L0081 | B82: Amara Das | C82: amara.das@salesforce.com | E82: SALESFORCE | F82: Startup | G82: content_syndication | H82: 24 | I82: 15 | J82: 44 | K82: 1 | L82: 45734 | M82: converted | N82: automotive | O82: VP Sales | P82: australia | Q82: Series C+ | R82: 45685
A83: L0082 | B83: Charlie Moreau | C83: charlie.moreau@dropbox.com | D83: (654) 600-3740 | E83: dropbox | F83: smb | G83: Organic | H83: 14 | I83: 8 | J83: 18 | K83: NO | L83: 45954 | M83: DISQUALIFIED | N83: Energy | O83: Associate | P83: france | Q83: 1M-10M | R83: 45826 | S83: www.linkedin.com/in/karenortiz93
A84: L0083 | B84: Margaux Young | C84: margaux.young@miro.com | D84: 289.549.2923 | E84: MIRO | F84: smb | G84: Webinar | H84: 22 | I84: 19 | J84: 10 | K84: No | L84: 45774 | M84: New | N84: healthcare | O84: Engineering Manager | P84: United states | Q84: $500M-1B | R84: 46001
A85: L0084 | B85: Sophie Verma | C85: sophie.verma@microsoft.com | E85: MICROSOFT | F85: SMB | G85: referral | H85: 8 | I85: 10 | J85: 48 | K85: 0 | L85: 45735 | M85: new | N85: cleantech | O85: Field Marketing Manager | P85: South Africa | Q85: Over $1B | R85: 45701 | S85: www.linkedin.com/in/vikramgomez48
A86: L0085 | B86: Wesley Khan | C86: wesley.khan@microsoft.com | D86: +12649149756 | E86: Microsoft | F86: mid market | G86: Content_Syndication | H86: 31 | I86: 9 | J86: 36 | K86: No | L86: 45895 | M86: Lost | N86: Healthcare | O86: Demand Gen Manager | P86: DE | Q86: Series C+ | R86: 45716
A87: L0086 | B87: Orion Johnson | C87: orion.johnson@salesforcecom.com | D87: 2957706905 | E87: Salesforce.com | F87: ENTERPRISE | G87: event | H87: 10 | J87: 46 | K87: n | L87: 45711 | M87: nurturing | N87: SaaS | O87: director of demand gen | P87: Kenya | R87: 45922 | S87: linkedin.com/in/charliediaz44
A88: L0087 | B88: Genevieve Gomez | C88: genevieve.gomez@airtable.com | D88: (591) 892-3181 | E88: Airtable | F88: mid-market | G88: Referral | I88: 19 | J88: 28 | K88: TRUE | L88: 45985 | M88: lost | N88: Media | O88: Sales Operations | P88: JP | R88: 45707 | S88: https://www.linkedin.com/in/nolanmalhotra55
A89: L0088 | B89: James Lopez | C89: james.lopez@databricks.com | E89: databricks | F89: mid-market | G89: cold_email | H89: 32 | I89: 12 | J89: 3 | K89: n | L89: 45696 | M89: NURTURING | N89: E-commerce | O89: VP Marketing | P89: UAE | Q89: $100M-500M | R89: 45944
A90: L0089 | B90: Winona Clark | C90: winona.clark@google.com | D90: (607) 618-5693 | E90: google | F90: growth | H90: 27 | I90: 2 | J90: 34 | K90: No | L90: 45698 | M90: qualified | N90: ENERGY | O90: MARKETING MANAGER | P90: India | Q90: $10M+ | R90: 45983 | S90: linkedin.com/in/dmitridiaz56
A91: L0090 | B91: Kevin Davis | C91: kevin.davis@databricks.com | D91: (322) 112-3248 | E91: Databricks | F91: enterprise | G91: REFERRAL | H91: 22 | I91: 8 | J91: 8 | K91: Y | L91: 45713 | M91: new | N91: fintech | O91: ABM Manager | P91: US | Q91: 1M-10M | R91: 45951
A92: L0091 | B92: Orion Nakamura | C92: orion.nakamura@cloudflare.com | D92: (318) 333-9336 | E92: Cloudflare | F92: Enterprise | G92: organic | H92: 30 | I92: 4 | J92: 54 | K92: Yes | L92: 46015 | M92: new | N92: media | O92: Digital Marketing Manager | P92: South Korea | Q92: self-funded | R92: 45707
A93: L0092 | B93: Adeline Flores | C93: adeline.flores@meta.com | D93: +1-518-435-2415 | E93: meta | G93: organic | H93: 18 | I93: 9 | J93: 15 | L93: 45894 | M93: DISQUALIFIED | N93: hrtech | O93: Customer Success Manager | P93: India | R93: 45765
A94: L0093 | B94: Zinnia Chopra | C94: zinnia.chopra@cloudflare.com | D94: (443) 529-9061 | E94: cloudflare | F94: Mid-Market | G94: SOCIAL | I94: 16 | J94: 57 | K94: TRUE | L94: 45994 | N94: EdTech | O94: Intern | P94: australia | Q94: $10M+ | R94: 45932 | S94: https://www.linkedin.com/in/hassanwright38
A95: L0094 | B95: Elise Saxena | C95: elise.saxena@twilio.com | E95: TWILIO | F95: smb | G95: PAID | H95: 10 | I95: 10 | J95: 34 | K95: TRUE | L95: 45762 | M95: Nurturing | N95: retail | O95: Business Development Rep | P95: FR | R95: 45804 | S95: https://www.linkedin.com/in/cordeliagarcia28
A96: L0095 | B96: Liam Thomas | C96: liam.thomas@meta.com | E96: Meta | F96: Startup | G96: partner | H96: 35 | I96: 14 | J96: 50 | K96: No | L96: 45684 | M96: DISQUALIFIED | N96: legaltech | O96: CTO | P96: Japan | Q96: < $1M | R96: 45964 | S96: linkedin.com/in/piperdas10
A97: L0096 | B97: Quinn Robinson | C97: quinn.robinson@atlassian.com | D97: +16439417471 | E97: Atlassian | F97: enterprise | G97: Event | H97: 11 | I97: 5 | J97: 28 | K97: No | N97: PropTech | O97: VP Revenue | P97: Turkey | Q97: $50M - $100M | R97: 45697
A98: L0097 | B98: Finn Robinson | C98: finn.robinson@workday.com | D98: 7579008940 | E98: workday | F98: smb | H98: 17 | I98: 10 | J98: 1 | K98: Y | M98: NURTURING | N98: LOGISTICS | O98: Content Marketing Lead | P98: india | R98: 45795 | S98: LinkedIn.com/in/oliviaortiz29
A99: L0098 | B99: Ximena Malik | C99: ximena.malik@notion.com | D99: +1-228-820-6761 | E99: notion | F99: smb | G99: Referral | H99: 12 | I99: 15 | J99: 11 | M99: contacted | N99: InsurTech | O99: Digital Marketing Manager | P99: United States | Q99: $0-1M | R99: 45937 | S99: https://www.linkedin.com/in/lorenzomedina23
A100: L0099 | B100: Paul Williams | C100: paul.williams@salesforce.com | D100: 8785052655 | E100: salesforce | F100: Smb | G100: Cold_Email | H100: 10 | I100: 13 | J100: 31 | K100: 1 | L100: 46009 | M100: disqualified | N100: LOGISTICS | O100: Digital Marketing Manager | P100: Singapore | Q100: self-funded | R100: 45722 | S100: LinkedIn.com/in/urielo'brien99
...

Sheet raw_spend
A1: campaign_id | B1: campaign_name | C1: campaign_desc | D1: source | E1: channel | F1: monthly_spend | G1: month | H1: impressions | I1: clicks_generated | J1: leads_generated | K1: conversions | L1: revenue_attributed
A2: C007 | B2: SEO content program | C2: SEO Content Program | D2: organic | E2: Blog/SEO | F2: 4423 | G2: 2025-12 | H2: 108294 | I2: 5972 | J2: 99 | K2: 21 | L2: 77911
A3: C001 | B3: Google ads - Search | C3: Google Ads — Search | D3: paid | E3: SEARCH | F3: 6401 | G3: 2025-01 | H3: 61308 | I3: 2283 | J3: 48 | K3: 5 | L3: 12313
A4: C001 | B4: Google Ads Search | C4: Google Ads — Search | D4: Paid | E4: search | F4: 6171 | G4: 2025-02 | H4: 54265 | I4: 1683 | J4: 34 | K4: 7 | L4: 33082
A5: C001 | B5: google ads search | C5: Google Ads — Search | D5: PAID | E5: SEARCH | F5: 6022 | G5: 2025-03 | H5: 45356 | I5: 1769 | J5: 36 | K5: 10 | L5: 24392
A6: C001 | B6: GOOGLE ADS SEARCH | C6: Google Ads — Search | D6: paid | E6: search | F6: 6863 | G6: 2025-04 | H6: 62990 | I6: 2113 | J6: 48 | K6: 6 | L6: 9330
A7: C001 | B7: google ads search | C7: Google Ads — Search | D7: paid | E7: SEARCH | F7: 6982 | G7: 2025-05 | H7: 49599 | I7: 2197 | J7: 60 | K7: 7 | L7: 11457
A8: C001 | B8: Google Ads Search | C8: Google Ads — Search | D8: Paid | E8: SEARCH | F8: 6013 | G8: 2025-06 | H8: 56402 | I8: 1617 | J8: 48 | K8: 10 | L8: 17657
A9: C006 | B9: Referral Program | C9: Referral Program | D9: Referral | E9: PARTNER | F9: 2199 | G9: 2025-03 | H9: 5080 | I9: 1128 | J9: 56 | K9: 12 | L9: 19507
A10: C001 | B10: GOOGLE ADS SEARCH | C10: Google Ads — Search | D10: Paid | E10: SEARCH | F10: 6560 | G10: 2025-07 | H10: 48495 | I10: 2278 | J10: 61 | K10: 12 | L10: 38764
A11: C001 | B11: Google ads - Search | C11: Google Ads — Search | D11: PAID | E11: SEARCH | F11: 6885 | G11: 2025-08 | H11: 62783 | I11: 2670 | J11: 56 | K11: 6 | L11: 26525
A12: C001 | B12: Google Ads Search | C12: Google Ads — Search | D12: PAID | E12: Search | F12: 7831 | G12: 2025-09 | H12: 72266 | I12: 2799 | J12: 63 | K12: 14 | L12: 39525
A13: C001 | B13: Google ads - Search | C13: Google Ads — Search | D13: paid | E13: SEARCH | F13: 9046 | G13: 2025-10 | H13: 66262 | I13: 2551 | J13: 85 | K13: 9 | L13: 10705
... A136: C010 | B136: content synd | C136: Content Syndication | D136: content_syndication | E136: 3rd Party | F136: 5929 | G136: 2025-12 | H136: 40080 | I136: 1247 | J136: 27 | K136: 2 | L136: 4823

Sheet raw_interactions
A1: interaction_id | B1: lead_id | C1: interaction_type | D1: interaction_date | E1: channel | F1: campaign_id | G1: content_asset | H1: response | I1: time_spent_seconds | J1: device | K1: page_url | L1: notes
A2: INT-00001 | B2: L0268 | C2: CASE_STUDY_VIEW | D2: 45939 | E2: social | F2: C007 | G2: Newsletter Issue #42 | H2: downloaded | I2: 1508 | J2: Mobile | K2: https://example.com/case-studies
A3: INT-00002 | B3: L0445 | C3: form_submit | D3: 45803 | E3: SOCIAL | F3: C003 | G3: 10 Lead Scoring Tips | H3: clicked | I3: 362 | J3: windows
A4: INT-00003 | B4: L0257 | C4: chatbot_convo | D4: 45813 | E4: Email | F4: C004 | G4: Event Registration: Summit 2025 | H4: bounced | I4: 382 | J4: Windows
A5: INT-00004 | B5: L0967 | C5: Free_Trial_Signup | E5: Phone | F5: C007 | G5: Case Study: SMB Growth Story | H5: BOUNCED | J5: Tablet | K5: https://example.com/integrations
A6: INT-00005 | B6: L0561 | C6: Content_Download | E6: EMAIL | G6: Newsletter Issue #44 | H6: registered | I6: 764 | J6: Windows
A7: INT-00006 | B7: L0488 | C7: Unsubscribe | D7: 45998 | E7: WEB | F7: C008 | G7: CRM Buyer's Guide 2025 | I7: 1146 | J7: Mobile | K7: https://example.com/free-trial
A8: INT-00007 | B8: L0099 | C8: email_open | D8: 46017 | E8: In-Person | F8: C010 | G8: Product Demo Video | I8: 180 | J8: Desktop | K8: https://example.com/blog
A9: INT-00008 | B9: L0618 | C9: Email_Click | D9: 45823 | E9: Sms | G9: Retargeting Ad Creative A | H9: OPENED | I9: 1667 | K9: HTTPS://EXAMPLE.COM/DEMO
A10: INT-00009 | B10: L0342 | C10: Referral_Link_Click | D10: 45680 | E10: WEB | F10: C006 | G10: Template: Campaign Planning | H10: converted | I10: 1190 | J10: tablet | K10: https://example.com/integrations
A11: INT-00010 | B11: L0516 | C11: AD_CLICK | D11: 45805 | E11: email | G11: Guide: Email Deliverability | H11: Converted | I11: 1503 | J11: mobile | K11: https://example.com/contact | L11: HIGH INTENT
A12: INT-00011 | B12: L0012 | C12: case_study_view | D12: 45720 | E12: chat | F12: C009 | G12: CRM Buyer's Guide 2025 | H12: Bounced | I12: 826 | J12: iOS | K12: https://example.com/case-studies
A13: INT-00012 | B13: L0458 | C13: demo_request | D13: 45718 | E13: phone | F13: C004 | G13: Case Study: Enterprise Win | H13: CLICKED | K13: https://example.com/contact
A14: INT-00013 | B14: L0184 | C14: social_engage | D14: 45821 | E14: Email | F14: C003 | G14: Newsletter Issue #42 | H14: registered | I14: 1698 | K14: https://example.com/integrations
A15: INT-00014 | B15: L0429 | C15: Blog_Read | D15: 45880 | E15: Phone | F15: C006 | G15: Ebook: ABM Playbook | H15: Clicked | I15: 571 | J15: Desktop | K15: https://example.com/contact
A16: INT-00015 | B16: L0914 | C16: Chatbot_Convo | D16: 45731 | F16: C006 | G16: Whitepaper: State of GTM 2025 | H16: opened | K16: https://example.com/competitors
A17: INT-00016 | B17: L0043 | C17: Social_Engage | D17: 45823 | E17: EMAIL | G17: Product Demo Video | H17: downloaded | J17: ios | K17: https://example.com/blog/reduce-cac
A18: INT-00017 | B18: L0465 | C18: REFERRAL_LINK_CLICK | D18: 45773 | E18: WEB | F18: C004 | G18: Case Study: SMB Growth Story | H18: opened | I18: 2355 | J18: Tablet | K18: https://example.com/contact | L18: proposal under review
A19: INT-00018 | B19: L0280 | C19: Phone_Call | D19: 45953 | E19: Phone | F19: C002 | G19: Video: Customer Testimonial | H19: ignored | I19: 232 | J19: iOS | K19: https://example.com/pricing
A20: INT-00019 | B20: L0149 | C20: REFERRAL_LINK_CLICK | D20: 45908 | E20: Email | F20: C003 | G20: Social Post: Product Launch | H20: downloaded | I20: 1088 | J20: Mobile
A21: INT-00020 | B21: L0644 | C21: FREE_TRIAL_SIGNUP | D21: 45707 | E21: email | F21: C003 | G21: 10 Lead Scoring Tips | H21: no_response | J21: mac | K21: https://example.com/blog/reduce-cac
A22: INT-00021 | B22: L0313 | C22: PHONE_CALL | D22: 45812 | E22: Email | F22: C010 | G22: Newsletter Issue #42 | H22: registered | I22: 1498 | J22: Tablet | K22: https://example.com/contact
A23: INT-00022 | B23: L0208 | C23: Blog_Read | D23: 45824 | E23: Push_Notification | G23: Case Study: SMB Growth Story | I23: 1909 | J23: Desktop | K23: https://example.com/pricing
A24: INT-00023 | B24: L0554 | C24: Unsubscribe | D24: 45863 | E24: SOCIAL | F24: C004 | G24: Blog: ABM vs Demand Gen | H24: Bounced | J24: mac | K24: https://example.com/resources/ebooks | L24: switching from Salesforce
A25: INT-00024 | B25: L0011 | C25: referral_link_click | D25: 45792 | E25: Email | F25: C002 | G25: Competitor Comparison Sheet | H25: ignored | I25: 697 | J25: android | K25: https://example.com/contact
A26: INT-00025 | B26: L0943 | C26: UNSUBSCRIBE | D26: 45954 | E26: in-person | F26: C002 | G26: Blog: ABM vs Demand Gen | H26: BOUNCED | I26: 2211 | K26: https://example.com/roi-calculator
A27: INT-00026 | B27: L0465 | C27: FORM_SUBMIT | D27: 45810 | E27: PHONE | F27: C010 | G27: Webinar: Marketing Automation 101 | H27: Converted | I27: 972 | J27: Windows | K27: https://example.com/contact | L27: gatekeeper — need executive sponsor
A28: INT-00027 | B28: L0071 | C28: email open | D28: 46003 | E28: sms | F28: C002 | G28: Blog: 5 Metrics Every CMO Needs | H28: CLICKED | I28: 777 | J28: Tablet | K28: https://example.com/blog/reduce-cac
A29: INT-00028 | B29: L0217 | C29: unsubscribe | D29: 45977 | E29: email | F29: C009 | G29: Newsletter Issue #44 | I29: 1582 | K29: https://example.com/features
A30: INT-00029 | B30: L0891 | C30: form_submit | D30: 46002 | E30: sms | F30: C004 | G30: Case Study: SMB Growth Story | H30: Bounced | J30: Android | K30: https://example.com/roi-calculator
A31: INT-00030 | B31: L0007 | C31: Pricing_Page_View | D31: 45744 | E31: email | F31: C008 | H31: Partial_View | I31: 1745 | J31: Mobile | K31: https://example.com/webinars
A32: INT-00031 | B32: L0595 | C32: Free_Trial_Signup | D32: 45839 | F32: C003 | G32: Blog: 5 Metrics Every CMO Needs | H32: opened | I32: 268 | J32: mobile
A33: INT-00032 | B33: L0882 | C33: REFERRAL_LINK_CLICK | E33: web | F33: C001 | G33: Newsletter Issue #42 | H33: Clicked | I33: 281 | J33: Windows | K33: https://example.com/about
A34: INT-00033 | B34: L0004 | C34: AD_CLICK | D34: 45976 | E34: Email | F34: C001 | G34: Customer Success Story | H34: viewed | I34: 1666 | J34: windows | K34: https://example.com/webinars
A35: INT-00034 | B35: L0353 | C35: Referral_Link_Click | D35: 45984 | E35: In-Person | F35: C008 | G35: Webinar: Lead Scoring Best Practices | H35: clicked | I35: 2033 | J35: Desktop | K35: https://example.com/blog/reduce-cac
A36: INT-00035 | B36: L0603 | C36: chatbot_convo | D36: 45855 | E36: Web | F36: C002 | G36: Webinar: Marketing Automation 101 | H36: OPENED | I36: 1646 | K36: https://example.com/competitors | L36: needs SSO/SAML
A37: INT-00036 | B37: L0461 | C37: webinar_attended | D37: 45942 | E37: chat | G37: Ultimate Guide to CRM | H37: CONVERTED | J37: Windows | K37: https://example.com/webinars
A38: INT-00037 | B38: L0363 | C38: REFERRAL_LINK_CLICK | D38: 45695 | E38: PHONE | F38: C007 | G38: Newsletter Issue #43 | H38: partial_view | I38: 2333 | J38: windows
A39: INT-00038 | B39: L0749 | C39: Phone_Call | D39: 45936 | E39: PHONE | F39: C001 | G39: ROI Calculator Landing Page | H39: Converted | I39: 1741 | J39: iOS | K39: https://example.com/about
A40: INT-00039 | B40: L0740 | C40: Phone_Call | D40: 45876 | E40: PHONE | F40: C009 | G40: Whitepaper: State of GTM 2025 | H40: Downloaded | J40: mobile
A41: INT-00040 | B41: L0269 | C41: phone_call | D41: 45793 | E41: CHAT | F41: C010 | G41: Newsletter Issue #43 | H41: unsubscribed | I41: 1367 | J41: mac
A42: INT-00041 | B42: L0550 | C42: demo_request | D42: 45949 | E42: sms | F42: C008 | G42: Whitepaper: State of GTM 2025 | H42: downloaded | I42: 150 | J42: DESKTOP | K42: HTTPS://EXAMPLE.COM/DEMO
A43: INT-00042 | B43: L0714 | C43: FORM_SUBMIT | D43: 45859 | E43: sms | F43: C002 | G43: Ebook: ABM Playbook | H43: Opened | I43: 461 | J43: Windows | K43: https://example.com/blog/reduce-cac
A44: INT-00043 | B44: L0986 | C44: PRICING_PAGE_VIEW | D44: 45759 | E44: Social | G44: 10 Lead Scoring Tips | H44: registered | I44: 1007 | J44: android
A45: INT-00044 | B45: L0041 | C45: Content_Download | D45: 45905 | E45: In-Person | G45: Guide: Email Deliverability | H45: unsubscribed | I45: 1352 | K45: https://example.com/webinars
A46: INT-00045 | B46: L0176 | C46: email open | D46: 45970 | F46: C009 | G46: Case Study: Mid-Market Win | H46: replied | I46: 510 | J46: mobile | K46: https://example.com/webinars
A47: INT-00046 | B47: L0413 | C47: PRICING_PAGE_VIEW | D47: 45937 | E47: phone | G47: Case Study: SMB Growth Story | H47: converted | I47: 2340 | J47: MOBILE | K47: https://example.com/resources/ebooks
A48: INT-00047 | B48: L0227 | C48: Email_Click | D48: 45886 | E48: Chat | F48: C006 | G48: Ultimate Guide to CRM | H48: opened | I48: 1137 | J48: windows
A49: INT-00048 | B49: L0777 | C49: free_trial_signup | D49: 45819 | E49: in-person | G49: Case Study: Mid-Market Win | I49: 2307 | J49: DESKTOP
A50: INT-00049 | B50: L0076 | C50: UNSUBSCRIBE | D50: 45784 | E50: phone | G50: Event Registration: Summit 2025 | H50: registered | I50: 2062 | J50: DESKTOP | K50: https://example.com/blog/reduce-cac
A51: INT-00050 | B51: L0507 | C51: form_submit | E51: sms | F51: C003 | G51: Webinar: Lead Scoring Best Practices | H51: downloaded | J51: TABLET | L51: duplicate entry
A52: INT-00051 | B52: L0390 | C52: PRICING_PAGE_VIEW | D52: 45823 | E52: Sms | F52: C006 | G52: Video: Customer Testimonial | H52: downloaded | I52: 1053 | J52: tablet | K52: https://example.com/free-trial
A53: INT-00052 | B53: L0417 | C53: PHONE_CALL | D53: 45870 | F53: C009 | H53: ignored | I53: 1640 | J53: Windows | K53: https://example.com/about
A54: INT-00053 | B54: L0945 | C54: PRICING_PAGE_VIEW | D54: 45786 | F54: C002 | G54: ROI Calculator Landing Page | H54: opened | I54: 67 | K54: https://example.com/resources/ebooks
A55: INT-00054 | B55: L0799 | C55: blog_read | D55: 45797 | E55: social | F55: C006 | G55: Social Post: Product Launch | H55: clicked | I55: 472 | J55: desktop | K55: https://example.com/case-studies
A56: INT-00055 | B56: L0819 | C56: email_click | D56: 45981 | E56: Chat | F56: C010 | G56: Whitepaper: State of GTM 2025 | H56: registered | I56: 1008
A57: INT-00056 | B57: L0329 | C57: Webinar_Attended | D57: 45921 | E57: EMAIL | F57: C002 | G57: Case Study: Enterprise Win | H57: ignored | I57: 156 | J57: tablet | K57: https://example.com/features
A58: INT-00057 | B58: L0406 | C58: email open | D58: 45848 | E58: push_notification | F58: C003 | G58: Blog: 5 Metrics Every CMO Needs | H58: downloaded | I58: 1372 | K58: https://example.com/features
A59: INT-00058 | B59: L0167 | C59: email_open | D59: 45715 | E59: Social | F59: C006 | G59: Newsletter Issue #44 | H59: opened | I59: 697 | J59: Mobile | K59: https://example.com/contact
A60: INT-00059 | B60: L0005 | C60: CHATBOT_CONVO | D60: 45713 | E60: CHAT | F60: C004 | G60: Retargeting Ad Creative A | H60: engaged | I60: 1571 | J60: Desktop | K60: HTTPS://EXAMPLE.COM/DEMO
A61: INT-00060 | B61: L0854 | C61: Demo_Request | D61: 45681 | E61: push_notification | F61: C001 | G61: Video: Customer Testimonial | H61: clicked | I61: 1026 | J61: Windows
A62: INT-00061 | B62: L0079 | C62: email open | D62: 45812 | E62: chat | F62: C004 | G62: Chatbot: Pricing Inquiry | H62: viewed | J62: mac | K62: https://example.com/blog/reduce-cac
A63: INT-00062 | B63: L0001 | C63: UNSUBSCRIBE | D63: 45798 | E63: web | F63: C008 | G63: Chatbot: Pricing Inquiry | H63: Opened | J63: ios | K63: https://example.com/demo
A64: INT-00063 | B64: L0346 | C64: Social_Engage | D64: 45705 | F64: C006 | G64: Social Post: Product Launch | H64: converted | I64: 810 | J64: Mobile | K64: https://example.com/roi-calculator
A65: INT-00064 | B65: L0823 | C65: email_open | D65: 45828 | F65: C002 | G65: Chatbot: Pricing Inquiry | H65: Partial_View | I65: 1311 | J65: android | K65: https://example.com/case-studies
A66: INT-00065 | B66: L0628 | C66: EMAIL_CLICK | D66: 46007 | E66: IN-PERSON | F66: C003 | G66: Ultimate Guide to CRM | H66: clicked | I66: 730 | K66: https://example.com/pricing
A67: INT-00066 | B67: L0088 | C67: AD_CLICK | D67: 45709 | E67: push_notification | F67: C002 | G67: Retargeting Ad Creative A | H67: downloaded | I67: 1110 | J67: ios | K67: https://example.com/case-studies
A68: INT-00067 | B68: L0292 | C68: email_open | D68: 45774 | E68: In-Person | F68: C006 | G68: Video: Platform Overview 3min | H68: Partial_View | I68: 779 | J68: Windows | K68: https://example.com/case-studies
A69: INT-00068 | B69: L0173 | C69: social_engage | D69: 45661 | E69: WEB | G69: CRM Buyer's Guide 2025 | H69: converted | I69: 178 | J69: Mobile | K69: https://example.com/demo
A70: INT-00069 | B70: L0519 | C70: free_trial_signup | D70: 45791 | E70: SMS | F70: C009 | G70: Demo: Live Product Walkthrough | H70: Viewed | I70: 1493 | J70: Mac | K70: https://example.com/features
A71: INT-00070 | B71: L0708 | C71: PHONE_CALL | D71: 45742 | E71: SMS | F71: C002 | G71: Newsletter Issue #43 | H71: CONVERTED | I71: 1342 | J71: Mac | K71: https://example.com/case-studies
A72: INT-00071 | B72: L0320 | C72: DEMO_REQUEST | D72: 45934 | E72: Phone | F72: C004 | G72: Ebook: ABM Playbook | J72: mac | K72: https://example.com/pricing
A73: INT-00072 | B73: L0101 | C73: webinar_attended | D73: 45813 | E73: social | F73: C002 | G73: Webinar: Advanced Analytics Deep Dive | H73: Opened | I73: 2188 | J73: MOBILE | K73: https://example.com/contact
A74: INT-00073 | B74: L0557 | C74: Demo_Request | D74: 45681 | E74: Web | F74: C003 | G74: Newsletter Issue #44 | H74: Opened | I74: 1612 | J74: Android | K74: https://example.com/blog/reduce-cac
A75: INT-00074 | B75: L0800 | C75: WEBSITE_VISIT | E75: Web | F75: C006 | G75: Newsletter Issue #43 | H75: clicked | I75: 1039 | J75: MOBILE | K75: https://example.com/contact
A76: INT-00075 | B76: L0452 | C76: Ad_Click | E76: CHAT | F76: C008 | G76: Blog: 5 Metrics Every CMO Needs | H76: opened | I76: 554 | J76: Mac | K76: https://example.com/free-trial
A77: INT-00076 | B77: L0650 | C77: Free_Trial_Signup | D77: 45916 | E77: Sms | G77: Template: Campaign Planning | I77: 1927 | K77: https://example.com/demo
A78: INT-00077 | B78: L0718 | C78: unsubscribe | D78: 45885 | E78: Web | F78: C002 | G78: 10 Lead Scoring Tips | H78: Bounced | I78: 734 | K78: https://example.com/demo | L78: bad email
A79: INT-00078 | B79: L0716 | C79: EMAIL_OPEN | D79: 45836 | E79: EMAIL | F79: C001 | G79: Case Study: Mid-Market Win | H79: viewed | I79: 1895 | J79: Mobile | K79: https://example.com/blog
A80: INT-00079 | B80: L0443 | C80: form_submit | D80: 45702 | H80: OPENED | I80: 731 | J80: Android | K80: https://example.com/competitors
A81: INT-00080 | B81: L0977 | C81: Blog_Read | D81: 45766 | E81: IN-PERSON | F81: C006 | G81: Competitor Comparison Sheet | H81: engaged | I81: 426 | J81: android | K81: https://example.com/webinars
A82: INT-00081 | B82: L0524 | C82: Pricing_Page_View | D82: 45859 | E82: social | G82: Pricing Page | I82: 2252 | J82: mac | K82: https://example.com/competitors
A83: INT-00082 | B83: L0490 | C83: unsubscribe | D83: 45666 | E83: WEB | G83: Newsletter Issue #42 | H83: unsubscribed | I83: 1873 | J83: mac | K83: https://example.com/contact | L83: HIGH INTENT
A84: INT-00083 | B84: L0617 | C84: Form_Submit | D84: 45715 | E84: EMAIL | G84: Template: Campaign Planning | H84: CONVERTED | I84: 769 | J84: windows | K84: https://example.com/blog/reduce-cac
A85: INT-00084 | B85: L0327 | C85: demo_request | D85: 45893 | E85: Email | F85: C006 | G85: Ultimate Guide to CRM | H85: clicked | I85: 16 | J85: Android
A86: INT-00085 | B86: L0741 | C86: pricing_page_view | D86: 45796 | E86: phone | G86: Ultimate Guide to CRM | H86: CLICKED | I86: 1639 | J86: tablet | K86: https://example.com/blog
A87: INT-00086 | B87: L0517 | C87: social_engage | D87: 45843 | F87: C002 | G87: Newsletter Issue #43 | H87: Downloaded | I87: 1335 | J87: Windows | K87: https://example.com/blog | L87: demo scheduled for next week
A88: INT-00087 | B88: L0566 | C88: DEMO_REQUEST | D88: 45801 | E88: WEB | F88: C003 | G88: Case Study: SMB Growth Story | H88: OPENED | I88: 415 | J88: tablet | K88: https://example.com/free-trial
A89: INT-00088 | B89: L0761 | C89: Content_Download | D89: 45818 | E89: web | F89: C010 | G89: Video: Customer Testimonial | H89: registered | I89: 1454 | J89: mobile | K89: https://example.com/case-studies | L89: multi-year deal potential
A90: INT-00089 | B90: L0510 | C90: content_download | D90: 45969 | F90: C007 | G90: Newsletter Issue #42 | H90: Opened | I90: 43 | K90: https://example.com/pricing
A91: INT-00090 | B91: L0504 | C91: demo_request | D91: 45721 | E91: Social | F91: C005 | G91: Blog: How to Reduce CAC | H91: Clicked | I91: 1997 | J91: ios
A92: INT-00091 | B92: L0981 | C92: EMAIL_OPEN | D92: 45774 | E92: push_notification | F92: C003 | G92: Free Trial Signup Page | H92: BOUNCED | I92: 461 | J92: Mobile | L92: HIGH INTENT
A93: INT-00092 | B93: L0909 | C93: ad_click | D93: 45951 | F93: C010 | G93: Newsletter Issue #42 | H93: unsubscribed | I93: 1261 | J93: windows
A94: INT-00093 | B94: L0873 | C94: blog_read | D94: 45743 | E94: web | F94: C002 | G94: Pricing Page | H94: Bounced | I94: 2384 | J94: Mobile | K94: https://example.com/contact
A95: INT-00094 | B95: L0510 | C95: Unsubscribe | D95: 45691 | E95: phone | F95: C010 | G95: Free Trial Signup Page | H95: engaged | I95: 433 | J95: desktop
A96: INT-00095 | B96: L0166 | C96: demo_request | E96: Chat | G96: Chatbot: Pricing Inquiry | H96: opened | I96: 1065 | J96: windows | K96: https://example.com/pricing | L96: wants to talk to reference customer
A97: INT-00096 | B97: L0098 | C97: phone_call | D97: 45770 | E97: Chat | F97: C005 | H97: unsubscribed | I97: 156 | J97: Desktop | K97: https://example.com/resources/ebooks | L97: budget not confirmed
A98: INT-00097 | B98: L0312 | C98: email_click | D98: 45675 | E98: EMAIL | F98: C008 | G98: 10 Lead Scoring Tips | H98: viewed | I98: 1734 | J98: DESKTOP | K98: https://example.com/competitors
A99: INT-00098 | B99: L0482 | C99: PHONE_CALL | D99: 45968 | E99: WEB | G99: Product Demo Video | H99: no_response | I99: 2353 | J99: Android | K99: https://example.com/pricing
A100: INT-00099 | B100: L0132 | C100: Email_Open | D100: 45971 | E100: push_notification | F100: C008 | G100: Newsletter Issue #44 | H100: registered | I100: 1259 | K100: https://example.com/resources/ebooks
...
